Workbook
Name Slicer_Attribute: #N/A
Name Slicer_ID: #N/A
Name Slicer_Impact_Analysis_Bucket: #N/A
Name Slicer_Target_Domain: #N/A
Name tbl_DDX_Renovate_Backlog: 'DDX Renovate Backlog'!$B$4:$S$179

Sheet READ ME
B2: DOCUMENT OVERVIEW
B3: Purpose | C3: This document outlines the business requirements for the data that will exist in the Gold Layer. It identifies the critical data fields required for Activation and Analytics/Reporting use cases and organizes them by domain + sub-domain, to guide the tech teams in building our final table structures.
B5: Context | C5: The fields listed here are a curated subset of the entire L'Oréal data ecosystem, compiled from three main sources: 1) Global Granular Data Model (GDM): The mandated analytcis data model from L'Oréal Global 2) One Consumer Profile: The mandated activation data model from L'Oréal Global 3) LUSA B2C Business Glossary: Our glossary of critical data fields that have been identified and validated by LUSA stakeholders across business & IT teams to date (also accounting for the subset of these fields that exist in the C360 data model tables in DDX)
B6: ** ALL Domains, BAR Activation KPIs, and KPI Catalog sheets are the three sources of truth when it comes to what needs to be in the golden layer**
B7: DOCUMENT NAVIGATION (SHEET GUIDE)
B8: All Domains | C8: This sheet provides a comprehensive list of all critical data fields, organized by Domain and Subdomain. The purpose of this categorization is to propose a logical structure for the tables in the Gold Layer. This view should be used to understand what data is required and how it's grouped together.
B9: BAR Activation KPIs | C9: A focused and highly prioritized subset of calculated metrics that were historically used to populate the BAR dashboards and are now critical for immediate digital activation. These are derived from the foundational attributes defined in the All Domains view, with all of them being prioritized for the Golden Layer build.
B10: KPI Catalog | C10: The holistic, comprehensive master list of LUSA's business-critical metrics for all measurement needs. It encompasses the entire set of KPIs, including the subset listed under BAR Activation KPIs. The purpose of this sheet is to serve as the definitive source of truth for metrics leveraged in long-term reporting, advanced analytics (e.g., the DDX Tech dashboard), and overall strategic business intelligence.
B11: Gap Analysis | C11: This sheet provides a comparative view of our required fields against the two source assets (GDM and the Business Glossary). It highlights overlaps, identifies net-new fields required by the US market, and shows domain fill rates. This context is crucial for understanding the source and completeness of our data requirements.
B13: KEY CONCEPTS FOR TABLE DESIGN
B14: Customer Relationship (1-to-1 vs. 1-to-Many) | C14: This is the most critical concept. It defines how data relates back to a single, unique customer. 1.) 1-to-1: The data point is an attribute of the customer and can be represented once per person (e.g., a customer's single date of birth). These fields belong in the core customer table. 2.) 1-to-Many: The data point represents an event or item associated with the customer, where one customer can have many records (e.g., a customer's many transactions over time). These fields belong in separate, related tables.
B21: Domain Object Relationship (1-to-1 vs. 1-to-many) | C21: This defines how data relates to the primary object of its domain (e.g., a single Campaign ID or a single Order ID). 1.) 1-to-1: The data represents a single record for that object (e.g., the Order Header contains one row of summary data for one order). 2.) 1-to-Many: The data can have many records for that single object (e.g., the Order Line table can contain many product lines for one order).
B29: ALL DOMAINS SHEET STRUCTURE & LOGIC GUIDE
B30: Customer Domain | C30: The Customer domain is the central entity. Its core principle is that each row represents a single, unique customer (1-to-1 relationship). All subdomains here are attributes that can be directly assigned to an individual. - Identity: Basic 1st-party identifiers and descriptive information. - Contactability: High-level KPIs that summarize a customer's contact status. - Acquisition Data: Information detailing how and when a customer was first acquired. - BMDM (Beauty Data): The customer's "Beauty Profile" (e.g., hair color, eye color). - Loyalty: Aggregated KPIs related to the customer's loyalty status (e.g., current tier). - Interaction KPIs: Aggregated metrics summarizing customer engagement. - Transactional KPIs: Aggregated metrics summarizing purchasing behavior (e.g., LTV). - 3P Demographic Data: Appended demographic data from TransUnion.
B42: Contacts Domain | C42: This domain contains all specific contact points on file for a customer, such as every email address or phone number. - Key Design Consideration: We have intentionally separated this from the Customer domain for data processing efficiency. It is designed with a 1-to-many relationship to the customer, meaning a single customer can have multiple rows (one for each contact point). This structure is more scalable and easier to query for activation than trying to fit multiple contacts into a single customer row.
B50: Transactions Domain | C50: This domain holds event-level purchase data. The primary object is the Order. - Order Header: Provides information aggregated to a single order, such as net sales, promotional value, and order date. (Customer Relationship: 1-to-many; Domain Object Relationship: 1-to-1 with Order). - Order Line: Contains granular information for each item within an order, such as line number, line type, and product-level promotional value. (Customer Relationship: 1-to-many; Domain Object Relationship: 1-to-many with Order).L
B58: Campaign Domain | C58: This domain contains all information related to our marketing campaigns. The primary object is the Campaign. - Campaign Master: The aggregate view of a campaign, including total net sales, message channel, and start/end dates. This data is not at the customer level. (Customer Relationship: N/A; Domain Object Relationship: 1-to-1 with Campaign). - Campaign Interactions: Event-level data tracking individual customer interactions with a campaign, such as an email open, a click, or a promo application. (Customer Relationship: 1-to-many; Domain Object Relationship: 1-to-many with Campaign). - Loyalty Campaign Interactions: Similar to the above, but focused on interactions within loyalty-specific campaigns, such as a customer upgrading their tier as a result of the campaign. (Customer Relationship: 1-to-many; Domain Object Relationship: 1-to-many with Campaign).
B69: Interactions Domain | C69: This domain is a log of all granular, event-level customer engagements. The primary object is the individual Interaction Event. - Interaction Tracking: A comprehensive log of all customer interactions, both online and offline (e.g., subscription changes, loyalty events, orders). Every row is a single interaction. (Customer Relationship: 1-to-many; Domain Object Relationship: 1-to-1 with Interaction). - Website Interactions: A specific log for all customer interactions happening online, with data sourced directly from Google Analytics 4 (GA4), which has a unique data structure. (Customer Relationship: 1-to-many; Domain Object Relationship: 1-to-1 with Interaction).
B79: Link to GA4 glossary
B80: Link to OneConsumerModel

Sheet TAXONOMY GUIDE
D2: Purpose of This Reference
D3: This document explains how Gold Layer data is organized in the "All Domains" sheet so the CDP team can build an accurate, business-friendly taxonomy in HighTouch without misinterpreting table structure or data grain. The most important concept to keep in mind is that not all attributes behave like customer-level traits. Understanding the relationship between Domain, Sub-Domain, and Object grain is critical to avoiding duplicate counts, incorrect joins, and confusing marketer experiences. If field nuances are still unclear with this added context, check definitions for greater clarity.
D5: Key Terms | E5: Definition | G5: How to use it (CDP quick guidance)
D6: Domain | E6: The high-level category (Customer, Transactions, etc…) individual data fields belong to, strongly related to the "Object in Focus" for any given field. | G6: Start here to understand what type of data / object you’re working with.
D7: Sub-Domain | E7: The high level data sub-category individual data fields belong to, providing guidance for table-level grouping (typically maps to a unique Gold table or tight table set). | G7: Use as the primary “table context” for taxonomy placement.
D8: Object in focus | E8: The primary (but often not only) entity a given domain + sub-domain/table describes (e.g., Customer, Customer Order, Campaign, Interaction, Product). | G8: Identify the specific object the sub-domain tables + fields are related to. Helps distinguish similar-looking fields that mean different things in different tables.
D9: Customer Relationship | E9: Relationship to customer: 1:1 = one row per customer; 1:many = multiple rows per customer. | G9: Always check this first. If 1:many, treat as record/event-level unless explicitly rolled up. Helps distinguish similar-looking fields + contextualize field utility for any given use case.
D10: Domain Object Relationship | E10: Relationship to the domain’s object (e.g., Order Header = 1 row per order vs Order Line = many rows per order). | G10: Use to tell “master/aggregate tables” vs “detail/event tables.” Helps distinguish similar-looking fields + contextualize field utility for any given use case.
D12: [Customer] Domain Object in focus: Unique Customer (customer-level traits, rollups, and customer-level enrichments). Goal: Sub-domains here all contain data that can be represented on a single row per customer, making them our primary source of truth for audience segmentation
D13: Sub-Domain Overview (1:1 Unique Customer Relationship)
D14: Domain (Object) | E14: Sub-Domain | F14: What this table/sub-domain represents (business view) | G14: Customer Relationship | H14: Domain Object (Customer) Relationship | I14: Gold Table mapping (from All Domains)
D15: Customer | E15: Identity | F15: Core customer identifiers + foundational profile attributes used across the ecosystem (IDs, brand/division, basic profile fields). | G15: one-to-one | H15: one-to-one | I15: prod_us_catalog.ddx_b2c_gold.cdp__identity_v
D16: Customer | E16: Campaign Control Group | F16: Customer-level flags/dates indicating control-group assignment status for campaign measurement. | G16: one-to-one | H16: one-to-one | I16: TBD
D17: Customer | E17: Contactability | F17: Customer-level “rollups” that summarize contactability/permission status (intended to be customer-safe traits). | G17: one-to-one | H17: one-to-one | I17: prod_us_catalog.ddx_b2c_gold.cdp__contactability_v
D18: Customer | E18: Loyalty | F18: Customer-level loyalty membership attributes and loyalty KPIs/balances at the customer grain. | G18: one-to-one | H18: one-to-one | I18: prod_us_catalog.ddx_b2c_gold.cdp__loyalty_v
D19: Customer | E19: Transactional KPIs | F19: Customer-level purchase rollups (e.g., frequency/recency/aggregates) computed from transactional data. | G19: one-to-one | H19: one-to-one | I19: prod_us_catalog.ddx_b2c_gold.cdp__transactional_kpis_v
D20: Customer | E20: Interaction KPIs | F20: Customer-level interaction rollups (derived metrics summarizing customer interaction behavior). | G20: one-to-one | H20: one-to-one | I20: prod_us_catalog.ddx_b2c_gold.cdp__acquisition_interaction_data_v
D21: Customer | E21: Acquisition Data | F21: Customer-level acquisition descriptors (current-state view; undergoing reconciliation into cleaner outputs). | G21: one-to-one | H21: one-to-one | I21: prod_us_catalog.ddx_b2c_gold.cdp__acquisition_interaction_data_v
D22: Customer | E22: BMDM (Beauty Data) | F22: Customer-level “beauty profile” attributes (enriched beauty-related descriptors at customer grain). | G22: one-to-one | H22: one-to-one | I22: prod_us_catalog.ddx_b2c_gold.cdp__beauty_profile_v
D23: Customer | E23: 3P Demographic Data | F23: Customer-level appended/enriched 3P demographic signals (e.g., TransUnion attributes) including appended location fields. | G23: one-to-one | H23: one-to-one | I23: prod_us_catalog.ddx_b2c_gold.3p_demographic_v
D25: [Customer - Contacts] Domain Object in focus: Unique contact value (email, phone, and other contact records) tied back to the customer. What this means in practice: These tables are inherently customer 1:many and are record-level. They house the customer PII data critical to executing marketing campaigns across platforms in just 3 fields (contact_type, _sub_type, and _value), allowing for multiple rows per unique customer. This format offers greater efficiency and agility vs. representing all contact values in the main 1:1 customer table - allowing users to strategically match only relevant contact info to customer segments in HighTouch vs. parsing/querying through dozens of redundant fields. Still, they require careful treatment if aggregated /transformed/processed to ensure that the opt-in statuses attached to individual customer contact values stay accurate (Ex.- customers often have multiple emails/phone numbers, each with their own unique opt-in status).
D26: Sub-Domain Overview (1:M Unique Customer Relationship | 1:1 Contact Value Relationship)
D27: Domain (Object) | E27: Sub-Domain | F27: What this table/sub-domain represents (business view) | G27: Customer Relationship | H27: Domain Object (Contact Value) Relationship | I27: Gold Table mapping (from All Domains)
D28: Customer – Contacts | E28: Contact Info | F28: Contact-value-level records (e.g., each email / phone / contact value). Used for granular consent and contact-value attributes. | G28: one-to-many | H28: one-to-one | I28: prod_us_catalog.ddx_b2c_gold.cdp__contact_info_v
D30: [Customer] - AA Models Domain Object in focus: Unique Advanced Analytics Model Output (customer classifications/scores), tied back to the customer. What this means in practice: Typically customer 1:M because one customer can have multiple model outputs (different models, scores, or segments). This is not customer-level and not event-level; it’s “model output record” level. This format allows advanced analytics based segmentation to be multi-dimensional.
D31: Sub-Domain Overview (1:M Unique Customer Relationship | 1:1 Customer Model Output Relationship)
D32: Domain (Object) | E32: Sub-Domain | F32: What this table/sub-domain represents (business view) | G32: Customer Relationship | H32: Domain Object (Model Output) Relationship | I32: Gold Table mapping (from All Domains)
D33: Customer - AA Models | E33: Predictive attributes | F33: Model-driven customer attributes (scores/segments/classes). Often one row per customer per model output type/version. | G33: one-to-many | H33: one-to-one | I33: prod_us_catalog.ddx_b2c_gold.cdp__bar_customer_models_v
D35: [Interactions] Domain Object in focus: Unique Customer Interaction (events/activities) connected to known customers Goal: Almost universally customer 1:M because one customer typically records multiple interactions with a given brand (sign-ups, clicks, purchases, etc..). This is customer event-level data at the smallest grain possible, allowing for nuanced customer segmentation to aide complex analysis and activation efforts.
D36: Sub-Domain Overview (1:M Unique Customer Relationship | 1:1 Interaction Relationship)
D37: Domain (Object) | E37: Sub-Domain | F37: What this table/sub-domain represents (business view) | G37: Customer Relationship | H37: Domain Object (Interaction) Relationship | I37: Gold Table mapping (from All Domains)
D38: Interactions | E38: Interaction Tracking | F38: Master table of known-customer interaction records across sources (customer-linked interactions), including roll-ups from loyalty, campaign, and GA4 tables. | G38: one-to-many | H38: one-to-one | I38: prod_us_catalog.ddx_b2c_gold.cdp__acquisition_interaction_level_data_v
D39: Interactions | E39: Loyalty Interactions | F39: Loyalty interaction/event records kept separate for cleaner loyalty analytics and modeling. | G39: one-to-many | H39: one-to-one | I39: prod_us_catalog.ddx_b2c_gold.cdp__loyalty_event_v
D41: [Website Browsing (GA4)] Domain Object in focus: Unique GA4 User ID connected to known & unknown (anonymous) customers Goal: A comination of customer 1:M and 1:1 because one known customer will commonly have multiple GA4 IDs associated with them given the constraints associated with GA4 identity resolution. Any IDs we can reconcile to known customer IDs enable customer profile enrichment. When GA4 User IDs can be matched to known customers, we pull their interaction data into our master Interaction Tracking table.
D42: Sub-Domain Overview (1:M Unique Customer Relationship | Mixed GA4 User Relationship)
D43: Domain (Object) | E43: Sub-Domain | F43: What this table/sub-domain represents (business view) | G43: Customer Relationship | H43: Domain Object (GA4 User) Relationship | I43: Gold Table mapping (from All Domains)
D44: GA4 User | E44: Website Interactions - User view | F44: GA4 user-level view (GA4 users with associated fields; may include known/anonymous handling depending on GA4 joinability). | G44: one-to-many | H44: one-to-one | I44: prod_us_catalog..ddx_b2c_gold.fact_ga4_users
D45: GA4 User | E45: Website interactions - Daily event table | F45: GA4 daily event-level table (interaction events aggregated/represented at daily event grain). | G45: one-to-many | H45: one-to-many | I45: prod_us_catalog..ddx_b2c_gold.fact_ga4_daily_events
D47: [Transactions] Domain Object in focus: Unique Order / Transaction (any purchase) connected to known & unknown (anonymous) customers Goal: Customer → transactions is customer 1:many. Within the domain, header vs line are different object grains, both relating to customer transactions over time. Line-level data is our primary source of truth to calculate order-level KPIs (Header table) and identify product-level customer purchase patterns. Meanwhile, order-level data is our primary source of truth to calculate customer-level transactional KPIs.
D48: Sub-Domain Overview (1:M Unique Customer Relationship | Mixed Order Relationship)
D49: Domain (Object) | E49: Sub-Domain | F49: What this table/sub-domain represents (business view) | G49: Customer Relationship | H49: Domain Object (Transaction) Relationship | I49: Gold Table mapping (from All Domains)
D50: Transactions | E50: Order Header | F50: One row per order. Order-level summary attributes (order identifiers, order-level totals, channel, order metadata). | G50: one-to-many | H50: one-to-one | I50: prod_us_catalog.ddx_b2c_gold.cdp__order_header_v
D51: Transactions | E51: Order Line | F51: Multiple rows per order. Line-item detail (product-level rows per order). Used for basket analysis, product affinity, etc. | G51: one-to-many | H51: one-to-many | I51: prod_us_catalog.ddx_b2c_gold.cdp__order_lineitem_v
D53: [Campaign] Domain Object in focus: Unique Marketing Campaign (email and/or SMS) connected to known customers Goal: Customer → campaign engagement is typically customer 1:many. Campaign Master is one row per campaign; Campaign Interactions is many rows per campaign over time/customers. Interaction-level data is our primary source of truth to calculate campaign-level KPIs and identify customer campaign engagement patterns. Meanwhile, campaign-level data is our primary source of truth to evaluate campaign efficacy and overall brand strategy.
D54: Sub-Domain Overview (1:M Unique Customer Relationship | Mixed Campaign Relationship)
D55: Domain (Object) | E55: Sub-Domain | F55: What this table/sub-domain represents (business view) | G55: Customer Relationship | H55: Domain Object (Campaign) Relationship | I55: Gold Table mapping (from All Domains)
D56: Campaign | E56: Campaign Master | F56: One row per campaign: campaign descriptors/metadata (campaign identity and properties). | G56: one-to-many | H56: one-to-one | I56: prod_us_catalog.ddx_b2c_gold.cdp__campaign_master_v
D57: Campaign | E57: Campaign Interactions | F57: Customer/campaign engagement records over time (event-like rows tracking interaction/engagement). | G57: one-to-many | H57: one-to-many | I57: prod_us_catalog.ddx_b2c_gold.cdp__campaign_interactions_metrics_v
D59: [Product] Domain Object in focus: Unique Product ID (any unique product sold by a L'Oreal brand) Goal: The product table is product-grain (one row per product) and can be easily linked to the Order Line table (by matching unique product IDs) to enrich transactional analyses with nuanced product information. Customer relationship is “one-to-many” only in the sense that customers touch many products via orders/interactions.
D60: Sub-Domain Overview (1:M Unique Customer Relationship | 1:1 Product Relationship)
D61: Domain (Object) | E61: Sub-Domain | F61: What this table/sub-domain represents (business view) | G61: Customer Relationship | H61: Domain Object (Product) Relationship | I61: Gold Table mapping (from All Domains)
D62: Product | E62: Product Dimensions | F62: One row per product/SKU: product hierarchy and attributes used for enrichment and analysis. | G62: one-to-many | H62: one-to-one | I62: prod_us_catalog.ddx_b2c_gold.cdp__dim_product_hierarchy_v

Sheet Renovate Timeline
I1: We are here
F3: M1 - Jan | H3: M2-Feb | L3: M3-Mar | Q3: M4-April | U3: M5-May | Y3: M6-June | AD3: M7-July | AH3: M8-AUG | AM3: M9-SEP | AQ3: M10-Oct | AU3: M11- Nov
F4: Wk1 | G4: Wk2 | H4: Wk3 | I4: Wk4 | J4: Wk5 | K4: Wk6 | L4: Wk7 | M4: Wk8 | N4: Wk9 | O4: Wk10 | P4: Wk11 | Q4: Wk12 | R4: Wk13 | S4: Wk14 | T4: Wk15 | U4: Wk15 | V4: Wk17 | W4: Wk18 | X4: Wk19 | Y4: Wk20 | Z4: Wk21 | AA4: Wk22 | AB4: Wk23 | AC4: Wk24 | AD4: Wk25 | AE4: Wk26 | AF4: Wk27 | AG4: Wk28 | AH4: Wk29 | AI4: Wk30 | AJ4: Wk31 | AK4: Wk32 | AL4: Wk33 | AM4: Wk34 | AN4: Wk35 | AO4: Wk36 | AP4: Wk37 | AQ4: Wk38 | AR4: Wk39 | AS4: Wk40 | AT4: Wk41 | AU4: Wk42 | AV4: Wk43 | AW4: Wk44 | AX4: Wk45 | AY4: Wk46 | AZ4: Wk47
F5: 46041 | G5: =+F5+7 -> 46048 | H5: =+G5+7 -> 46055 | I5: =+H5+7 -> 46062 | J5: =+I5+7 -> 46069 | K5: =+J5+7 -> 46076 | L5: =+K5+7 -> 46083 | M5: =+L5+7 -> 46090 | N5: =+M5+7 -> 46097 | ... AZ5: =+AY5+7 -> 46363
F6: 46045 | G6: =+F6+7 -> 46052 | H6: =+G6+7 -> 46059 | I6: =+H6+7 -> 46066 | J6: =+I6+7 -> 46073 | K6: =+J6+7 -> 46080 | L6: =+K6+7 -> 46087 | M6: =+L6+7 -> 46094 | N6: =+M6+7 -> 46101 | ... AZ6: =+AY6+7 -> 46367
A7: Project/Phase | B7: Owner | C7: Status | D7: Start Date | E7: End Date
A8: P0 Attributes
A9: P0 Attributes - Refactoring | B9: Databricks | C9: Complete | D9: 46041 | E9: 46052
A10: P0 Data Quality validation | B10: L'Oreal IT | C10: Complete | D10: 46041 | E10: 46052
A11: P0 Data quality remediation | B11: Databricks | C11: Complete | D11: 46041 | E11: 46052
A12: P0 Deploy to Staging / Production Wave 1 | B12: L'Oreal IT | C12: Complete | D12: 46041 | E12: 46052 | F12: * Go Live
A13: P0 Deploy to Staging / Production Wave 2 | B13: L'Oreal IT | C13: Complete | D13: 46041 | E13: 46052 | G13: * Go Live
A14: P0 - Available for CDP in Prod | B14: Sapient | C14: Complete | D14: 46041 | E14: 46052
A16: P1 , P2 Attributes and Bar Activation KPIs
A17: Sprint 1
A18: Sprint 1 Refactoring (Domains: P1 ) | B18: Databricks | C18: Complete | D18: 46041 | E18: 46052
A19: Sprint 1 - IT DQ validation | B19: L'Oreal IT | C19: In-Progress | D19: 46055 | E19: 13-Feb
A20: Sprint 1 - CDMO DQ validation | B20: L'Oreal CDMO | C20: In-Progress | D20: 46055 | E20: 13-Feb
A21: Sprint 1 - DQ remediation ( Fix All defects and feedback | B21: Databricks | C21: In-Progress | D21: 13-Feb | E21: 20-Feb
A22: Sprint 1 Sign off - ( Regression Test Loreal IT and CDMO) | B22: L'Oreal IT & CDMO | C22: Not Started | D22: 16-Feb | E22: 20-Feb
A23: Sprint 1 - Prod Deployment | B23: Loreal IT | C23: Not Started | D23: 23-Feb | E23: 25-Feb | K23: * Go Live
A24: Sprint 1 - Available for CDP in Prod | B24: Sapient | C24: Not Started | D24: 46083 | E24: 46087
A26: Sprint 2
A27: Sprint 2 Refactoring (Domains: P1 ) | B27: Databricks | C27: Complete | D27: 2-Feb | E27: 13-Feb
A28: Sprint 2 - IT DQ validation | B28: L'Oreal IT | C28: In-Progress | D28: 16-Feb | E28: 27-Feb
A29: Sprint 2 - CDMO DQ validation | B29: L'Oreal IT | C29: In-Progress | D29: 16-Feb | E29: 27-Feb
A30: Sprint 2 - DQ remediation ( Fix All defects and feedback | B30: Databricks | C30: In-Progress | D30: 23-Feb | E30: 46087
A31: Sprint 2 Sign off - ( Regression Test Loreal IT and CDMO) | B31: L'Oreal IT & CDMO | C31: Not Started | D31: 46083 | E31: 46087
A32: Sprint 2 - Prod Deployment | B32: Loreal IT | C32: Not Started | D32: 46090 | E32: 46094 | M32: * Go Live
A33: Sprint 2 - Available for CDP in Prod | B33: Sapient | C33: Not Started | D33: 46097 | E33: 46108
A35: Sprint 3
A36: Sprint 3 Refactoring (Domains: P2 and Bar KPIs) | B36: Databricks | C36: In-Progress | D36: 16-Feb | E36: 27-Feb
A37: Sprint 3 - IT DQ validation | B37: L'Oreal IT | C37: Not Started | D37: 46083 | E37: 46094
A38: Sprint 3 - CDMO DQ validation | B38: L'Oreal IT | C38: Not Started | D38: 46083 | E38: 46094
A39: Sprint 3 - DQ remediation ( Fix All defects and feedback | B39: Databricks | C39: Not Started | D39: 46090 | E39: 46101
A40: Sprint 3 Sign off - ( Regression Test Loreal IT and CDMO) | B40: L'Oreal IT & CDMO | C40: Not Started | D40: 46097 | E40: 46101
A41: Sprint 3 - Prod Deployment | B41: Loreal IT | C41: Not Started | D41: 46104 | E41: 46108 | O41: * Go Live
A42: Sprint 3 - Available for CDP in Prod | B42: Sapient | C42: Not Started | D42: 46111 | E42: 46115
A44: Sprint 4
A45: Sprint 4 Refactoring (P2, Bar KPIs and chance to pull KPI Catalog) | B45: Databricks | C45: Not Started | D45: 46083 | E45: 46094
A46: Sprint 4 - IT DQ validation | B46: L'Oreal IT | C46: Not Started | D46: 46097 | E46: 46108
A47: Sprint 4 - CDMO DQ validation | B47: L'Oreal IT | C47: Not Started | D47: 46097 | E47: 46108
A48: Sprint 4 - DQ remediation ( Fix All defects and feedback | B48: Databricks | C48: Not Started | D48: 46104 | E48: 46108
A49: Sprint 4 Sign off - ( Regression Test Loreal IT and CDMO) | B49: L'Oreal IT & CDMO | C49: Not Started | D49: 46097 | E49: 46115
A50: Sprint 4 - Prod Deployment | B50: Loreal IT | C50: Not Started | D50: 46118 | E50: 46122 | Q50: * Go Live
A51: Sprint 4 - Available for CDP in Prod | B51: Sapient | C51: Not Started | D51: 46125 | E51: 17-apr
A53: Sprint 1,2 & 3( Rregression tests ) | D53: 46125 | E53: 24-april
A55: KPI Catalog / Reporting | B55: L'Oreal IT and Databricks | C55: Not Started | D55: 4-April | E55: 15-May | L55: To be reviewed
A56: Critical Pipeline Refactoring (Bronze) - Beauty | B56: L'Oreal IT and Databricks | C56: Not Started | D56: TBD | E56: TBD
A57: Business to Business (B2B) Integration - Still Scoping | B57: L'Oreal IT and Databricks | C57: Not Started | D57: TBD | E57: TBD
A58: LATAM and Canada Integration with US Global workpace | B58: L'Oreal IT and Databricks | C58: Not Started | D58: TBD | E58: TBD

Sheet All Domains (Old Version)
D2: Please DO NOT sort column in default view - please create a separate view.
K3: Global Data Presence | N3: DDX Data Availability | Q3: Strategic Value & Activation | T3: Data Structure & Relationship | V3: Attribute Prioritization | AA3: Attribute Data Complexity | AC3: Pilot Use Case | AI3: Divisional Prioritization | AO3: WIP - JULIA
B4: Domain | C4: Sub-Domain | D4: Global Domain | E4: Global Sub Domain | F4: Business Term | G4: DDX Source Fields | H4: Reason For Review (Remove / Deprioritize) | I4: DDX Source Tables (Key DDX End Table Source of Truth) | J4: Business Definition | K4: In GDM Analytics Version? | L4: In Global One Consumer Profile? | M4: Exists in GDM | N4: In C360 Tables? | O4: In Glossary | P4: Exists in DDX | Q4: LiveRamp | R4: Attentive | S4: KPI | T4: Customer Relationship | U4: Domain Object Relationship | V4: Global One Consumer Profile Waves | W4: Priority | X4: Reason | Y4: First Pass Priority Level | Z4: Reason (from fist pass - ignore) | AA4: Data Complexities | AB4: Notes ( from Databricks) | AC4: LOP | AD4: SkinC | AE4: Valentino | AF4: Kerastase | AG4: Valentino Data Migration | AH4: In a Use Case? | AI4: CPD | AJ4: LDB | AK4: LUXE | AL4: PPD | AM4: ALL | AN4: ANY | AO4: Attribute Exists? | AP4: Planned for Gold Layer? | AQ4: Attribute Exists in Gold Layer?
B5: Customer | C5: BMDM (Beauty Data) | D5: Beauty Profile | E5: Beauty Preference | F5: Colorful hair | G5: colorful_hair | I5: crm_base.customer360 | J5: Blue, Pink, Green, Red, Yellow, Purple, Rainbow, Multiple | K5: N | L5: Y | M5: Y | N5: Y | O5: Y | P5: Y | Q5: Y | S5: N | T5: one-to-one | U5: one-to-one | V5: BPD | W5: 0 | X5: Use Case (Sapient) | Y5: N/A | Z5: DDX | AA5: Already have | AF5: X | AH5: =IF(OR(AC5="X", AD5 = "X", AE5="X", AF5="X", AG5="X"), "Y", "") -> Y | AI5: Y | AM5: =AND(AI5="Y",AJ5="Y",AK5="Y",AL5="Y") -> FALSE | AN5: =OR(AI5="Y",AJ5="Y",AK5="Y",AL5="Y") -> TRUE | AO5: Y
B6: Customer | C6: BMDM (Beauty Data) | D6: Beauty Profile | E6: Priorities | F6: Concern | G6: concern_improvement_goal | H6: LUXE Priority | I6: crm_base.customer360 | J6: Concern improvement goal | K6: N | L6: Y | M6: Y | N6: Y | O6: Y | P6: Y | Q6: Y | S6: N | T6: one-to-one | U6: one-to-one | V6: BPP | W6: 0 | X6: Use Case | Y6: 1 | Z6: DDX | AA6: Already have | AE6: X | AF6: X | AH6: =IF(OR(AC6="X", AD6 = "X", AE6="X", AF6="X", AG6="X"), "Y", "") -> Y | AI6: Y | AJ6: Y | AK6: Y | AL6: Y | AM6: =AND(AI6="Y",AJ6="Y",AK6="Y",AL6="Y") -> TRUE | AN6: =OR(AI6="Y",AJ6="Y",AK6="Y",AL6="Y") -> TRUE | AO6: Y
B7: Customer | C7: BMDM (Beauty Data) | D7: Beauty Profile | E7: N/A | F7: curls texture | G7: curls_texture | I7: crm_base.customer360 | J7: Curls texture of the customer | K7: N | L7: N | M7: N | N7: Y | O7: Y | P7: Y | Q7: Y | S7: N | T7: one-to-one | U7: one-to-one | W7: 0 | X7: Use Case | Y7: 1 | Z7: In Global One Consumer Profile & GDM Analytics | AA7: Already have | AF7: X | AH7: =IF(OR(AC7="X", AD7 = "X", AE7="X", AF7="X", AG7="X"), "Y", "") -> Y | AI7: Y | AL7: Y | AM7: =AND(AI7="Y",AJ7="Y",AK7="Y",AL7="Y") -> FALSE | AN7: =OR(AI7="Y",AJ7="Y",AK7="Y",AL7="Y") -> TRUE | AO7: Y
B8: Customer | C8: BMDM (Beauty Data) | D8: Beauty Profile | E8: N/A | F8: drugstore preference | G8: drugstore | H8: more data here | I8: crm_base.customer360 | J8: CVS, Walgreens | K8: N | L8: N | M8: N | N8: Y | O8: Y | P8: Y | Q8: Y | S8: N | T8: one-to-one | U8: one-to-one | W8: 1 | X8: Liveramp | Y8: 2 | Z8: In GDM & C360 | AA8: Already have | AH8: =IF(OR(AC8="X", AD8 = "X", AE8="X", AF8="X", AG8="X"), "Y", "") | AJ8: Y | AK8: Y | AL8: Y | AM8: =AND(AI8="Y",AJ8="Y",AK8="Y",AL8="Y") -> FALSE | AN8: =OR(AI8="Y",AJ8="Y",AK8="Y",AL8="Y") -> TRUE | AO8: Y
B9: Customer | C9: BMDM (Beauty Data) | D9: Beauty Profile | E9: Description | F9: Eye Color | G9: eye_color | I9: crm_base.customer360 | J9: Eye color of the customer | K9: N | L9: Y | M9: Y | N9: Y | O9: Y | P9: Y | Q9: Y | S9: N | T9: one-to-one | U9: one-to-one | V9: BPD | W9: 1 | X9: One Consumer Profile, C360, Liveramp | Y9: 2 | Z9: Need to Clarify with Global | AA9: Already have | AH9: =IF(OR(AC9="X", AD9 = "X", AE9="X", AF9="X", AG9="X"), "Y", "") | AK9: Y | AM9: =AND(AI9="Y",AJ9="Y",AK9="Y",AL9="Y") -> FALSE | AN9: =OR(AI9="Y",AJ9="Y",AK9="Y",AL9="Y") -> TRUE | AO9: Y
B10: Customer | C10: BMDM (Beauty Data) | D10: Beauty Profile | E10: N/A | F10: fragrance family | G10: fragrance_family | H10: LUXE Priority | I10: crm_base.customer360 | J10: Citrus, Floral, Fougere, Oriental, Woody, Musk, Chype | K10: N | L10: N | M10: N | N10: Y | O10: Y | P10: Y | Q10: Y | S10: N | T10: one-to-one | U10: one-to-one | W10: 0 | X10: Use Case | Y10: 1 | Z10: In GDM & C360 | AA10: Already have | AE10: X | AH10: =IF(OR(AC10="X", AD10 = "X", AE10="X", AF10="X", AG10="X"), "Y", "") -> Y | AK10: Y | AM10: =AND(AI10="Y",AJ10="Y",AK10="Y",AL10="Y") -> FALSE | AN10: =OR(AI10="Y",AJ10="Y",AK10="Y",AL10="Y") -> TRUE | AO10: Y
B11: Customer | C11: BMDM (Beauty Data) | D11: Beauty Profile | E11: N/A | F11: fragrance note | G11: fragrance_note | I11: crm_base.customer360 | J11: Aqua, Green, Aromatic, Fruity, White floral, Rose, Violet, Musk, Power musk, Leather, Amber, Spicy | K11: N | L11: N | M11: N | N11: Y | O11: Y | P11: Y | Q11: Y | S11: N | T11: one-to-one | U11: one-to-one | W11: 0 | X11: Use Case | Y11: 1 | Z11: In GDM & C360 | AA11: Already have | AE11: X | AH11: =IF(OR(AC11="X", AD11 = "X", AE11="X", AF11="X", AG11="X"), "Y", "") -> Y | AK11: Y | AM11: =AND(AI11="Y",AJ11="Y",AK11="Y",AL11="Y") -> FALSE | AN11: =OR(AI11="Y",AJ11="Y",AK11="Y",AL11="Y") -> TRUE | AO11: Y
B12: Customer | C12: BMDM (Beauty Data) | D12: Beauty Profile | E12: N/A | F12: grocery store/supermarket preference | G12: grocery_supermarket | H12: cvs, kroger, ulta | I12: crm_base.customer360 | J12: Grocery Supermarket | K12: N | L12: N | M12: N | N12: Y | O12: Y | P12: Y | Q12: Y | S12: N | T12: one-to-one | U12: one-to-one | W12: 1 | X12: One Consumer Profile, C360, Liveramp | Y12: 1 | Z12: In GDM & C360 | AA12: Already have | AH12: =IF(OR(AC12="X", AD12 = "X", AE12="X", AF12="X", AG12="X"), "Y", "") | AK12: Y | AL12: Y | AM12: =AND(AI12="Y",AJ12="Y",AK12="Y",AL12="Y") -> FALSE | AN12: =OR(AI12="Y",AJ12="Y",AK12="Y",AL12="Y") -> TRUE | AO12: Y
B13: Customer | C13: BMDM (Beauty Data) | D13: Beauty Profile | E13: N/A | F13: hair care product | G13: hair_care_product | I13: crm_base.customer360 | J13: Hair care products | K13: N | L13: N | M13: N | N13: Y | O13: Y | P13: Y | Q13: Y | S13: N | T13: one-to-one | U13: one-to-one | W13: 0 | X13: Use Case | Y13: 1 | Z13: In GDM & C360 | AA13: Already have | AF13: X | AH13: =IF(OR(AC13="X", AD13 = "X", AE13="X", AF13="X", AG13="X"), "Y", "") -> Y | AL13: Y | AM13: =AND(AI13="Y",AJ13="Y",AK13="Y",AL13="Y") -> FALSE | AN13: =OR(AI13="Y",AJ13="Y",AK13="Y",AL13="Y") -> TRUE | AO13: Y
B14: Customer | C14: BMDM (Beauty Data) | D14: Beauty Profile | E14: Description | F14: Hair Color | G14: hair_color | I14: crm_base.customer360 | J14: Hair color of the customer | K14: N | L14: Y | M14: Y | N14: Y | O14: Y | P14: Y | Q14: Y | S14: N | T14: one-to-one | U14: one-to-one | V14: BPD | W14: 0 | X14: Use Case | Y14: 1 | Z14: In GDM & C360 | AA14: Already have | AF14: X | AH14: =IF(OR(AC14="X", AD14 = "X", AE14="X", AF14="X", AG14="X"), "Y", "") -> Y | AI14: Y | AJ14: Y | AL14: Y | AM14: =AND(AI14="Y",AJ14="Y",AK14="Y",AL14="Y") -> FALSE | AN14: =OR(AI14="Y",AJ14="Y",AK14="Y",AL14="Y") -> TRUE | AO14: Y
B15: Customer | C15: BMDM (Beauty Data) | D15: Beauty Profile | E15: N/A | F15: hair color cover | G15: hair_color_cover | I15: crm_base.customer360 | J15: Hair color cover | K15: N | L15: N | M15: N | N15: Y | O15: Y | P15: Y | Q15: Y | S15: N | T15: one-to-one | U15: one-to-one | W15: 0 | X15: Use Case | Y15: 1 | Z15: In GDM & C360 | AA15: Already have | AF15: X | AH15: =IF(OR(AC15="X", AD15 = "X", AE15="X", AF15="X", AG15="X"), "Y", "") -> Y | AI15: Y | AL15: Y | AM15: =AND(AI15="Y",AJ15="Y",AK15="Y",AL15="Y") -> FALSE | AN15: =OR(AI15="Y",AJ15="Y",AK15="Y",AL15="Y") -> TRUE | AO15: Y
B16: Customer | C16: BMDM (Beauty Data) | D16: Beauty Profile | E16: N/A | F16: hair color finish | G16: hair_color_finish | I16: prod_us_catalog.crm_base.fact_gdm_beauty_profile | J16: Hair color finish | K16: N | L16: N | M16: N | N16: Y | O16: Y | P16: Y | S16: N | T16: one-to-one | U16: one-to-one | W16: 1 | X16: One Consumer Profile, C360 | Y16: 1 | Z16: Need to Clarify with Global | AA16: Easy Add | AB16: in crm_base.fact_gdm_beauty_profile | AH16: =IF(OR(AC16="X", AD16 = "X", AE16="X", AF16="X", AG16="X"), "Y", "") | AL16: Y | AM16: =AND(AI16="Y",AJ16="Y",AK16="Y",AL16="Y") -> FALSE | AN16: =OR(AI16="Y",AJ16="Y",AK16="Y",AL16="Y") -> TRUE | AO16: Y
B17: Customer | C17: BMDM (Beauty Data) | D17: Beauty Profile | E17: N/A | F17: hair color service | G17: hair_color_service | I17: crm_base.customer360 | J17: Hair color service | K17: N | L17: N | M17: N | N17: Y | O17: Y | P17: Y | Q17: Y | S17: N | T17: one-to-one | U17: one-to-one | W17: 0 | X17: Use Case | Y17: 1 | Z17: In GDM & C360 | AA17: Already have | AF17: X | AH17: =IF(OR(AC17="X", AD17 = "X", AE17="X", AF17="X", AG17="X"), "Y", "") -> Y | AI17: Y | AL17: Y | AM17: =AND(AI17="Y",AJ17="Y",AK17="Y",AL17="Y") -> FALSE | AN17: =OR(AI17="Y",AJ17="Y",AK17="Y",AL17="Y") -> TRUE | AO17: Y
B18: Customer | C18: BMDM (Beauty Data) | D18: Beauty Profile | E18: Description | F18: Hair state | G18: hair_state | I18: crm_base.customer360 | J18: Straight, Wavy, Loose waves, Curls, Curly, Coily, Kinky, Frizzy, Tight Curls | K18: N | L18: Y | M18: Y | N18: Y | O18: Y | P18: Y | Q18: Y | S18: N | T18: one-to-one | U18: one-to-one | V18: 0 | W18: 0 | X18: Use Case | Y18: 1 | Z18: Need to Clarify with Global | AA18: Already have | AE18: X | AF18: X | AH18: =IF(OR(AC18="X", AD18 = "X", AE18="X", AF18="X", AG18="X"), "Y", "") -> Y | AI18: Y | AJ18: Y | AM18: =AND(AI18="Y",AJ18="Y",AK18="Y",AL18="Y") -> FALSE | AN18: =OR(AI18="Y",AJ18="Y",AK18="Y",AL18="Y") -> TRUE | AO18: Y
B19: Customer | C19: BMDM (Beauty Data) | D19: Beauty Profile | E19: N/A | F19: hair style service | G19: hair_style_service | I19: crm_base.customer360 | J19: Straightener, Brazilian keratin treatment, Perm, Relaxer, None | K19: N | L19: N | M19: N | N19: Y | O19: Y | P19: Y | Q19: Y | S19: N | T19: one-to-one | U19: one-to-one | W19: 0 | X19: Use Case | Y19: 1 | Z19: Need Info from Global | AA19: Already have | AH19: =IF(OR(AC19="X", AD19 = "X", AE19="X", AF19="X", AG19="X"), "Y", "") | AL19: Y | AM19: =AND(AI19="Y",AJ19="Y",AK19="Y",AL19="Y") -> FALSE | AN19: =OR(AI19="Y",AJ19="Y",AK19="Y",AL19="Y") -> TRUE | AO19: Y
B20: Customer | C20: BMDM (Beauty Data) | D20: Beauty Profile | E20: Description | F20: Hair texture | G20: hair_texture | I20: crm_base.customer360 | J20: Hair texture of the customer: Thin, Medium, Normal, Coarse, Thick, Don't Know | K20: N | L20: Y | M20: Y | N20: Y | O20: Y | P20: Y | Q20: Y | S20: N | T20: one-to-one | U20: one-to-one | V20: BPD | W20: 0 | X20: Use Case | Y20: 1 | Z20: Need info from Global | AA20: Already have | AE20: X | AF20: X | AH20: =IF(OR(AC20="X", AD20 = "X", AE20="X", AF20="X", AG20="X"), "Y", "") -> Y | AJ20: Y | AM20: =AND(AI20="Y",AJ20="Y",AK20="Y",AL20="Y") -> FALSE | AN20: =OR(AI20="Y",AJ20="Y",AK20="Y",AL20="Y") -> TRUE | AO20: Y
B21: Customer | C21: BMDM (Beauty Data) | D21: Beauty Profile | E21: N/A | F21: hair treatment | G21: hair_treatment | I21: prod_us_catalog.crm_base.fact_gdm_beauty_profile | K21: N | L21: N | M21: N | N21: Y | O21: Y | P21: Y | S21: N | T21: one-to-one | U21: one-to-one | W21: 1 | X21: One Consumer Profile, C360 | Y21: 1 | Z21: Need info from Global | AA21: Easy Add | AB21: in crm_base.fact_gdm_beauty_profile | AH21: =IF(OR(AC21="X", AD21 = "X", AE21="X", AF21="X", AG21="X"), "Y", "") | AL21: Y | AM21: =AND(AI21="Y",AJ21="Y",AK21="Y",AL21="Y") -> FALSE | AN21: =OR(AI21="Y",AJ21="Y",AK21="Y",AL21="Y") -> TRUE | AO21: Y
B22: Customer | C22: BMDM (Beauty Data) | D22: Beauty Profile | E22: Description | F22: Hair type | G22: hair_type | I22: crm_base.customer360 | J22: Very Dry, Somewhat Dry, Normal, Somewhat Oily, Somewhat greasy, Very Oily, Very greasy, Combination, Greasy roots and dry ends, Don't Know | K22: N | L22: Y | M22: Y | N22: Y | O22: Y | P22: Y | Q22: Y | S22: N | T22: one-to-one | U22: one-to-one | V22: BPD | W22: 0 | X22: Use Case (Sapient) | Y22: 1 | Z22: DDX & Global One Consumer Data Profile | AA22: Already have | AB22: in customer_profile | AF22: X | AH22: =IF(OR(AC22="X", AD22 = "X", AE22="X", AF22="X", AG22="X"), "Y", "") -> Y | AI22: Y | AJ22: Y | AL22: Y | AM22: =AND(AI22="Y",AJ22="Y",AK22="Y",AL22="Y") -> FALSE | AN22: =OR(AI22="Y",AJ22="Y",AK22="Y",AL22="Y") -> TRUE | AO22: Y
B23: Customer | C23: BMDM (Beauty Data) | D23: Beauty Profile | E23: Routines | F23: Hair wash frequency | G23: hair_wash_frequency | I23: crm_base.customer360 | J23: Represents the frequency of hair washing, providing insights into hair care habits. | K23: N | L23: Y | M23: Y | N23: N | O23: Y | P23: Y | S23: N | T23: one-to-one | U23: one-to-one | V23: BPR | W23: 2 | X23: Global Request that we need to fulfil | Y23: 2 | Z23: In GDM & C360 | AA23: Easy Add | AB23: in crm_base.fact_gdm_beauty_profile | AH23: =IF(OR(AC23="X", AD23 = "X", AE23="X", AF23="X", AG23="X"), "Y", "") | AL23: Y | AM23: =AND(AI23="Y",AJ23="Y",AK23="Y",AL23="Y") -> FALSE | AN23: =OR(AI23="Y",AJ23="Y",AK23="Y",AL23="Y") -> TRUE | AO23: Y
B24: Customer | C24: BMDM (Beauty Data) | D24: Beauty Profile | E24: Routines | F24: Heating tool | G24: heating_tool | I24: crm_base.customer360 | K24: N | L24: Y | M24: Y | N24: N | O24: Y | P24: Y | S24: N | T24: one-to-one | U24: one-to-one | V24: BPR | W24: 1 | X24: One Consumer Profile, C360 | Y24: 1 | Z24: DDX & GDM Analytics | AA24: Easy Add | AB24: in crm_base.fact_gdm_beauty_profile | AH24: =IF(OR(AC24="X", AD24 = "X", AE24="X", AF24="X", AG24="X"), "Y", "") | AL24: Y | AM24: =AND(AI24="Y",AJ24="Y",AK24="Y",AL24="Y") -> FALSE | AN24: =OR(AI24="Y",AJ24="Y",AK24="Y",AL24="Y") -> TRUE | AO24: Y
B25: Customer | C25: BMDM (Beauty Data) | D25: Beauty Profile | E25: N/A | F25: lash look priority | G25: lash_look_priority | H25: LUXE Priority | I25: crm_base.customer360 | J25: Volume, Volumizing / Thickening, Length Lenghtening / Long lashes, Definition, Seperate lashes, Curl, Curling, Waterproof | K25: N | L25: N | M25: N | N25: Y | O25: Y | P25: Y | Q25: Y | S25: N | T25: one-to-one | U25: one-to-one | W25: 1 | X25: TransUnion | Y25: 1 | Z25: DDX & GDM Analytics | AA25: Already have | AH25: =IF(OR(AC25="X", AD25 = "X", AE25="X", AF25="X", AG25="X"), "Y", "") | AK25: Y | AM25: =AND(AI25="Y",AJ25="Y",AK25="Y",AL25="Y") -> FALSE | AN25: =OR(AI25="Y",AJ25="Y",AK25="Y",AL25="Y") -> TRUE | AO25: Y
B26: Customer | C26: BMDM (Beauty Data) | D26: Beauty Profile | E26: N/A | F26: makeup expectation | G26: makeup_expectation | I26: crm_base.customer360 | J26: Makeup Expectation of the customer | K26: N | L26: N | M26: N | N26: Y | O26: Y | P26: Y | Q26: Y | S26: N | T26: one-to-one | U26: one-to-one | W26: 1 | X26: Liveramp | Y26: 2 | Z26: DDX & Global One Consumer Data Profile | AA26: Already have | AH26: =IF(OR(AC26="X", AD26 = "X", AE26="X", AF26="X", AG26="X"), "Y", "") | AI26: Y | AM26: =AND(AI26="Y",AJ26="Y",AK26="Y",AL26="Y") -> FALSE | AN26: =OR(AI26="Y",AJ26="Y",AK26="Y",AL26="Y") -> TRUE | AO26: Y
B27: Customer | C27: BMDM (Beauty Data) | D27: Beauty Profile | E27: N/A | F27: makeup look | G27: makeup_look | H27: LUXE Priority | I27: crm_base.customer360 | J27: Make up look | K27: N | L27: N | M27: N | N27: Y | O27: Y | P27: Y | Q27: Y | S27: N | T27: one-to-one | U27: one-to-one | W27: 1 | X27: GDM Analytics | Y27: 2 | Z27: In GDM & C360 | AA27: Already have | AH27: =IF(OR(AC27="X", AD27 = "X", AE27="X", AF27="X", AG27="X"), "Y", "") | AI27: Y | AK27: Y | AM27: =AND(AI27="Y",AJ27="Y",AK27="Y",AL27="Y") -> FALSE | AN27: =OR(AI27="Y",AJ27="Y",AK27="Y",AL27="Y") -> TRUE | AO27: Y
B28: Customer | C28: BMDM (Beauty Data) | D28: Beauty Profile | E28: N/A | F28: makeup skill level | G28: makeup_skill_level | I28: crm_base.customer360 | J28: Make up skill level | K28: N | L28: N | M28: N | N28: Y | O28: Y | P28: Y | Q28: Y | S28: N | T28: one-to-one | U28: one-to-one | W28: 1 | X28: GDM Analytics | Y28: 1 | Z28: DDX & GDM Analytics | AA28: Already have | AH28: =IF(OR(AC28="X", AD28 = "X", AE28="X", AF28="X", AG28="X"), "Y", "") | AI28: Y | AM28: =AND(AI28="Y",AJ28="Y",AK28="Y",AL28="Y") -> FALSE | AN28: =OR(AI28="Y",AJ28="Y",AK28="Y",AL28="Y") -> TRUE | AO28: Y
B29: Customer | C29: BMDM (Beauty Data) | D29: Beauty Profile | E29: N/A | F29: nail aesthetic | G29: nail_aesthetic | I29: crm_base.customer360 | J29: Nail Aesthetic | K29: N | L29: N | M29: N | N29: Y | O29: Y | P29: Y | Q29: Y | S29: N | T29: one-to-one | U29: one-to-one | W29: 1 | X29: GDM Analytics | Y29: 1 | Z29: DDX & GDM Analytics | AA29: Already have | AH29: =IF(OR(AC29="X", AD29 = "X", AE29="X", AF29="X", AG29="X"), "Y", "") | AI29: Y | AM29: =AND(AI29="Y",AJ29="Y",AK29="Y",AL29="Y") -> FALSE | AN29: =OR(AI29="Y",AJ29="Y",AK29="Y",AL29="Y") -> TRUE | AO29: Y
B30: Customer | C30: BMDM (Beauty Data) | D30: Beauty Profile | E30: N/A | F30: nail color | G30: nail_color | I30: crm_base.customer360 | J30: Nail color of the customer | K30: N | L30: N | M30: N | N30: Y | O30: Y | P30: Y | Q30: Y | S30: N | T30: one-to-one | U30: one-to-one | W30: 1 | X30: Prioritized by Division(s) | Y30: 2 | Z30: Not in C360, reporting | AA30: Already have | AH30: =IF(OR(AC30="X", AD30 = "X", AE30="X", AF30="X", AG30="X"), "Y", "") | AI30: Y | AM30: =AND(AI30="Y",AJ30="Y",AK30="Y",AL30="Y") -> FALSE | AN30: =OR(AI30="Y",AJ30="Y",AK30="Y",AL30="Y") -> TRUE | AO30: Y
B31: Customer | C31: BMDM (Beauty Data) | D31: Beauty Profile | E31: N/A | F31: nail skill level | G31: nail_skill_level | I31: crm_base.customer360 | J31: Nail skill level | K31: N | L31: N | M31: N | N31: Y | O31: Y | P31: Y | Q31: Y | S31: N | T31: one-to-one | U31: one-to-one | W31: 1 | X31: Prioritized by Division(s) | Y31: 2 | Z31: In GDM & C360 | AA31: Already have | AH31: =IF(OR(AC31="X", AD31 = "X", AE31="X", AF31="X", AG31="X"), "Y", "") | AI31: Y | AM31: =AND(AI31="Y",AJ31="Y",AK31="Y",AL31="Y") -> FALSE | AN31: =OR(AI31="Y",AJ31="Y",AK31="Y",AL31="Y") -> TRUE | AO31: Y
B32: Customer | C32: BMDM (Beauty Data) | D32: Beauty Profile | E32: N/A | F32: pro teatments | G32: pro_treatments | I32: prod_us_catalog.crm_base.fact_gdm_beauty_profile | J32: Pro treatments | K32: N | L32: N | M32: N | N32: Y | O32: Y | P32: Y | S32: N | T32: one-to-one | U32: one-to-one | W32: 1 | X32: One Consumer Profile & C360 | Y32: 1 | Z32: Not in C360, no waves, reporting | AA32: Easy Add | AB32: in crm_base.fact_gdm_beauty_profile | AH32: =IF(OR(AC32="X", AD32 = "X", AE32="X", AF32="X", AG32="X"), "Y", "") | AJ32: Y | AM32: =AND(AI32="Y",AJ32="Y",AK32="Y",AL32="Y") -> FALSE | AN32: =OR(AI32="Y",AJ32="Y",AK32="Y",AL32="Y") -> TRUE | AO32: Y
B33: Customer | C33: BMDM (Beauty Data) | D33: Beauty Profile | E33: N/A | F33: pro treatment regimen | G33: pro_treatment_regimen | I33: prod_us_catalog.crm_base.fact_gdm_beauty_profile | J33: Pro Treatment regimen | K33: N | L33: N | M33: N | N33: Y | O33: Y | P33: Y | S33: N | T33: one-to-one | U33: one-to-one | W33: 1 | X33: One Consumer Profile, C360 | Y33: 1 | Z33: Not in C360, no waves, reporting | AA33: Easy Add | AB33: in crm_base.fact_gdm_beauty_profile | AH33: =IF(OR(AC33="X", AD33 = "X", AE33="X", AF33="X", AG33="X"), "Y", "") | AJ33: Y | AM33: =AND(AI33="Y",AJ33="Y",AK33="Y",AL33="Y") -> FALSE | AN33: =OR(AI33="Y",AJ33="Y",AK33="Y",AL33="Y") -> TRUE | AO33: Y
B34: Customer | C34: BMDM (Beauty Data) | D34: Beauty Profile | E34: N/A | F34: product category | G34: product_category | H34: LUXE Priority | I34: crm_base.customer360 | J34: Product category | K34: N | L34: N | M34: N | N34: Y | O34: Y | P34: Y | Q34: Y | S34: N | T34: one-to-one | U34: one-to-one | W34: 0 | X34: Use Case | Y34: 1 | AA34: Already have | AE34: X | AF34: X | AH34: =IF(OR(AC34="X", AD34 = "X", AE34="X", AF34="X", AG34="X"), "Y", "") -> Y | AI34: Y | AJ34: Y | AM34: =AND(AI34="Y",AJ34="Y",AK34="Y",AL34="Y") -> FALSE | AN34: =OR(AI34="Y",AJ34="Y",AK34="Y",AL34="Y") -> TRUE | AO34: Y
B35: Customer | C35: BMDM (Beauty Data) | D35: Beauty Profile | E35: N/A | F35: product coverage | G35: product_coverage | I35: crm_base.customer360 | J35: Product coverage | K35: N | L35: N | M35: N | N35: Y | O35: Y | P35: Y | Q35: Y | S35: N | T35: one-to-one | U35: one-to-one | W35: 0 | X35: Use Case | Y35: 1 | Z35: Reporting | AA35: Already have | AH35: =IF(OR(AC35="X", AD35 = "X", AE35="X", AF35="X", AG35="X"), "Y", "") | AK35: Y | AM35: =AND(AI35="Y",AJ35="Y",AK35="Y",AL35="Y") -> FALSE | AN35: =OR(AI35="Y",AJ35="Y",AK35="Y",AL35="Y") -> TRUE | AO35: Y
B36: Customer | C36: BMDM (Beauty Data) | D36: Beauty Profile | E36: N/A | F36: product finish | G36: product_finish | H36: LUXE Priority | I36: crm_base.customer360 | J36: Describes the finish of the product, such as matte, glossy, or semi-matte. | K36: N | L36: N | M36: N | N36: Y | O36: Y | P36: Y | Q36: Y | S36: N | T36: one-to-one | U36: one-to-one | W36: 1 | X36: One Consumer Profile, C360, Liveramp | Y36: 1 | Z36: Not in C360, reporting | AA36: Already have | AF36: X | AH36: =IF(OR(AC36="X", AD36 = "X", AE36="X", AF36="X", AG36="X"), "Y", "") -> Y | AM36: =AND(AI36="Y",AJ36="Y",AK36="Y",AL36="Y") -> FALSE | AN36: =OR(AI36="Y",AJ36="Y",AK36="Y",AL36="Y") -> FALSE | AO36: Y
B37: Customer | C37: BMDM (Beauty Data) | D37: Beauty Profile | E37: Recommendation | F37: Product Recommendation | G37: N/A | H37: Talking to Grant 11/13 | I37: N/A | J37: Consumer product recommendation | K37: Y | L37: Y | M37: Y | N37: N | O37: N | P37: N | S37: N | T37: one-to-one | U37: one-to-one | V37: PRD | W37: 2 | X37: No Use Case | Y37: 1 | Z37: Not in C360, no waves, reporting | AH37: =IF(OR(AC37="X", AD37 = "X", AE37="X", AF37="X", AG37="X"), "Y", "") | AI37: N/A | AJ37: N/A | AK37: N/A | AL37: N/A | AM37: =AND(AI37="Y",AJ37="Y",AK37="Y",AL37="Y") -> FALSE | AN37: =OR(AI37="Y",AJ37="Y",AK37="Y",AL37="Y") -> FALSE | AO37: Y
B38: Customer | C38: BMDM (Beauty Data) | D38: Beauty Profile | E38: N/A | F38: product type | G38: product_type | I38: crm_base.customer360 | J38: Product type | K38: N | L38: N | M38: N | N38: Y | O38: Y | P38: Y | Q38: Y | S38: N | T38: one-to-one | U38: one-to-one | W38: 0 | X38: Use Case | Y38: 1 | Z38: Reporting | AA38: Already have | AH38: =IF(OR(AC38="X", AD38 = "X", AE38="X", AF38="X", AG38="X"), "Y", "") | AI38: Y | AM38: =AND(AI38="Y",AJ38="Y",AK38="Y",AL38="Y") -> FALSE | AN38: =OR(AI38="Y",AJ38="Y",AK38="Y",AL38="Y") -> TRUE | AO38: Y
B39: Customer | C39: BMDM (Beauty Data) | D39: Beauty Profile | E39: N/A | F39: pure player preference | G39: pure_players | I39: crm_base.customer360 | J39: Amazon, Ebay, Jet | K39: N | L39: N | M39: N | N39: Y | O39: Y | P39: Y | Q39: Y | S39: N | T39: one-to-one | U39: one-to-one | W39: 0 | X39: Use Case | Y39: 1 | Z39: Not in C360, reporting | AA39: Already have | AH39: =IF(OR(AC39="X", AD39 = "X", AE39="X", AF39="X", AG39="X"), "Y", "") | AL39: Y | AM39: =AND(AI39="Y",AJ39="Y",AK39="Y",AL39="Y") -> FALSE | AN39: =OR(AI39="Y",AJ39="Y",AK39="Y",AL39="Y") -> TRUE | AO39: Y
B40: Customer | C40: BMDM (Beauty Data) | D40: Beauty Profile | E40: Description | F40: Scalp type | G40: scalp_type | I40: crm_base.customer360 | J40: Very Dry, Somewhat Dry, Normal, Somewhat Oily, Somewhat greasy, Very Oily, Greasy scalp, Don’t Know | K40: N | L40: Y | M40: Y | N40: Y | O40: Y | P40: Y | Q40: Y | S40: N | T40: one-to-one | U40: one-to-one | V40: BPD | W40: 0 | X40: Use Case | Y40: 1 | Z40: In GDM & C360 | AA40: Already have | AE40: X | AF40: X | AH40: =IF(OR(AC40="X", AD40 = "X", AE40="X", AF40="X", AG40="X"), "Y", "") -> Y | AJ40: Y | AL40: Y | AM40: =AND(AI40="Y",AJ40="Y",AK40="Y",AL40="Y") -> FALSE | AN40: =OR(AI40="Y",AJ40="Y",AK40="Y",AL40="Y") -> TRUE | AO40: Y
B41: Customer | C41: BMDM (Beauty Data) | D41: Beauty Profile | E41: Description | F41: Skin tone | G41: skin_tone | H41: LUXE Priority | I41: crm_base.customer360 | J41: Skin tone of the customer. Possible Values- Light, Fair, Medium, Tan, Brown, Very deep, Black, Don't Know | K41: N | L41: Y | M41: Y | N41: Y | O41: Y | P41: Y | Q41: Y | S41: N | T41: one-to-one | U41: one-to-one | V41: BPD | W41: 1 | X41: No Use Case | Y41: 2 | Z41: Not in C360, no waves, reporting | AA41: Already have | AF41: X | AH41: =IF(OR(AC41="X", AD41 = "X", AE41="X", AF41="X", AG41="X"), "Y", "") -> Y | AI41: Y | AJ41: Y | AK41: Y | AM41: =AND(AI41="Y",AJ41="Y",AK41="Y",AL41="Y") -> FALSE | AN41: =OR(AI41="Y",AJ41="Y",AK41="Y",AL41="Y") -> TRUE | AO41: Y
B42: Customer | C42: BMDM (Beauty Data) | D42: Beauty Profile | E42: Description | F42: Skin type | G42: skin_type | I42: crm_base.customer360 | J42: Skin type of the customer | K42: N | L42: Y | M42: Y | N42: Y | O42: Y | P42: Y | Q42: Y | S42: N | T42: one-to-one | U42: one-to-one | V42: BPD | W42: 0 | X42: Use Case | Y42: 1 | Z42: In GDM & C360 | AA42: Already have | AF42: X | AH42: =IF(OR(AC42="X", AD42 = "X", AE42="X", AF42="X", AG42="X"), "Y", "") -> Y | AI42: Y | AJ42: Y | AK42: Y | AM42: =AND(AI42="Y",AJ42="Y",AK42="Y",AL42="Y") -> FALSE | AN42: =OR(AI42="Y",AJ42="Y",AK42="Y",AL42="Y") -> TRUE | AO42: Y
B43: Customer | C43: BMDM (Beauty Data) | D43: Beauty Profile | E43: N/A | F43: skin undertone | G43: skin_undertone | H43: LUXE Priority | I43: crm_base.customer360 | J43: Color underneath the surface of the skin. - Cool, Warm, Neutral, Don't Know | K43: N | L43: N | M43: N | N43: Y | O43: Y | P43: Y | Q43: Y | S43: N | T43: one-to-one | U43: one-to-one | W43: 1 | X43: No Use Case | Y43: 2 | Z43: In GDM & C360 | AA43: Already have | AF43: X | AH43: =IF(OR(AC43="X", AD43 = "X", AE43="X", AF43="X", AG43="X"), "Y", "") -> Y | AJ43: Y | AM43: =AND(AI43="Y",AJ43="Y",AK43="Y",AL43="Y") -> FALSE | AN43: =OR(AI43="Y",AJ43="Y",AK43="Y",AL43="Y") -> TRUE | AO43: Y
B44: Customer | C44: BMDM (Beauty Data) | D44: Beauty Profile | E44: N/A | F44: specialty multi-brand beauty store preference | G44: beauty_specialty_multi_brand | I44: crm_base.customer360 | J44: Sephora, Ulta | K44: N | L44: N | M44: N | N44: Y | O44: Y | P44: Y | Q44: Y | S44: N | T44: one-to-one | U44: one-to-one | W44: 0 | X44: Use Case | Y44: 2 | Z44: Not in C360, reporting | AA44: Already have | AF44: X | AH44: =IF(OR(AC44="X", AD44 = "X", AE44="X", AF44="X", AG44="X"), "Y", "") -> Y | AJ44: Y | AK44: Y | AL44: Y | AM44: =AND(AI44="Y",AJ44="Y",AK44="Y",AL44="Y") -> FALSE | AN44: =OR(AI44="Y",AJ44="Y",AK44="Y",AL44="Y") -> TRUE | AO44: Y
B45: Customer | C45: BMDM (Beauty Data) | D45: Beauty Profile | E45: Beauty Preference | F45: Usual face makeup | G45: face_product_finish_preference | I45: crm_base.customer360 | J45: Matte, Glowy, "Dewy, Satin", Natural, "Semi-matte, Natural radiance", Long wearing | K45: N | L45: Y | M45: Y | N45: Y | O45: Y | P45: Y | Q45: Y | S45: N | T45: one-to-one | U45: one-to-one | V45: BPD | W45: 1 | X45: GDM Analytics | Y45: 2 | Z45: In GDM & C360 | AA45: Already have | AH45: =IF(OR(AC45="X", AD45 = "X", AE45="X", AF45="X", AG45="X"), "Y", "") | AI45: Y | AM45: =AND(AI45="Y",AJ45="Y",AK45="Y",AL45="Y") -> FALSE | AN45: =OR(AI45="Y",AJ45="Y",AK45="Y",AL45="Y") -> TRUE | AO45: Y
B46: Customer | C46: BMDM (Beauty Data) | D46: Beauty Profile | E46: Beauty Preference | F46: Usual lip makeup | G46: makeup_lip_product | H46: LUXE Priority | I46: crm_base.customer360 | J46: Makeup lip product | K46: N | L46: Y | M46: Y | N46: Y | O46: Y | P46: Y | Q46: Y | S46: N | T46: one-to-one | U46: one-to-one | V46: BPD | W46: 1 | X46: GDM Analytics | Y46: 1 | Z46: In GDM & C360 | AA46: Already have | AH46: =IF(OR(AC46="X", AD46 = "X", AE46="X", AF46="X", AG46="X"), "Y", "") | AK46: Y | AM46: =AND(AI46="Y",AJ46="Y",AK46="Y",AL46="Y") -> FALSE | AN46: =OR(AI46="Y",AJ46="Y",AK46="Y",AL46="Y") -> TRUE | AO46: Y
B47: Customer | C47: BMDM (Beauty Data) | D47: Beauty Profile | E47: Beauty Preference | F47: Usual nail makeup | G47: makeup_nail_product | I47: crm_base.customer360 | J47: Make up nail product | K47: N | L47: Y | M47: Y | N47: Y | O47: Y | P47: Y | Q47: Y | S47: N | T47: one-to-one | U47: one-to-one | W47: 0 | X47: Use Case | Y47: 2 | AA47: Easy Add | AH47: =IF(OR(AC47="X", AD47 = "X", AE47="X", AF47="X", AG47="X"), "Y", "") | AM47: =AND(AI47="Y",AJ47="Y",AK47="Y",AL47="Y") -> FALSE | AN47: =OR(AI47="Y",AJ47="Y",AK47="Y",AL47="Y") -> FALSE
B48: Customer | C48: BMDM (Beauty Data) | D48: Beauty Profile | E48: Description | F48: Zones | G48: zones | I48: crm_base.customer360 | J48: Zones | K48: N | L48: Y | M48: Y | N48: Y | O48: Y | P48: Y | Q48: Y | S48: N | T48: one-to-one | U48: one-to-one | W48: 1 | X48: Need to Clarify with Global | Y48: N/A | AA48: Already have | AH48: =IF(OR(AC48="X", AD48 = "X", AE48="X", AF48="X", AG48="X"), "Y", "") | AM48: =AND(AI48="Y",AJ48="Y",AK48="Y",AL48="Y") -> FALSE | AN48: =OR(AI48="Y",AJ48="Y",AK48="Y",AL48="Y") -> FALSE
B49: Customer | C49: Interaction KPIs | D49: Beauty Profile | E49: Sampling activity | F49: Last Sample Requested Date | G49: N/A | H49: Talking to Grant 11/13 | I49: N/A | J49: Most recent sample request | K49: Y | L49: Y | M49: Y | N49: N | O49: N | P49: N | S49: Y | T49: one-to-one | U49: one-to-one | W49: 1 | X49: OCP & GDM | Y49: 2 | Z49: GA Data | AA49: Need info | AH49: =IF(OR(AC49="X", AD49 = "X", AE49="X", AF49="X", AG49="X"), "Y", "") | AI49: N/A | AJ49: N/A | AK49: N/A | AL49: N/A | AM49: =AND(AI49="Y",AJ49="Y",AK49="Y",AL49="Y") -> FALSE | AN49: =OR(AI49="Y",AJ49="Y",AK49="Y",AL49="Y") -> FALSE | AO49: Y
B50: Customer | C50: Identity | D50: Contact Information | E50: Contact Detail | F50: Brand Code | G50: brand_code | I50: crm_base.customer360 | J50: Specifies the brand_code to which the customer belongs | K50: Y | L50: Y | M50: Y | N50: Y | O50: Y | P50: Y | Q50: Y | R50: Y | S50: N | T50: one-to-one | U50: one-to-one | V50: CIC | W50: 0 | X50: Use Case | Y50: 2 | Z50: In GDM & C360 | AA50: Already have | AC50: X | AD50: X | AE50: X | AF50: X | AG50: X | AH50: =IF(OR(AC50="X", AD50 = "X", AE50="X", AF50="X", AG50="X"), "Y", "") -> Y | AI50: Y | AJ50: Y | AK50: Y | AL50: Y | AM50: =AND(AI50="Y",AJ50="Y",AK50="Y",AL50="Y") -> TRUE | AN50: =OR(AI50="Y",AJ50="Y",AK50="Y",AL50="Y") -> TRUE | AO50: Y
B51: Customer | C51: Identity | D51: Contact Information | E51: Contact Detail | F51: Division Code | G51: division_code | I51: crm_base.customer360 | J51: Specifies the division to which the customer belongs | K51: Y | L51: Y | M51: Y | N51: Y | O51: Y | P51: Y | Q51: Y | S51: N | T51: one-to-one | U51: one-to-one | W51: 0 | X51: Use Case | Y51: 1 | Z51: Not in C360, reporting | AA51: Already have | AD51: X | AH51: =IF(OR(AC51="X", AD51 = "X", AE51="X", AF51="X", AG51="X"), "Y", "") -> Y | AI51: Y | AJ51: Y | AK51: Y | AL51: Y | AM51: =AND(AI51="Y",AJ51="Y",AK51="Y",AL51="Y") -> TRUE | AN51: =OR(AI51="Y",AJ51="Y",AK51="Y",AL51="Y") -> TRUE | AO51: Y
B52: Customer | C52: Contactability | D52: Contact Information | E52: Contact Preference | F52: Contactability key | G52: contactability_key | I52: crm_base.customer360 | J52: Indicates whether the customer can be contacted through email, direct mail or both If email_perm_status=’OPTIN’ AND address_perm_status!=’OPTIN’ AND phone_perm_status!=’OPTIN’ Then ‘CONEML’ If email_perm_status!=’OPTIN’ AND address_perm_staus!=’OPTIN’ AND phone_perm_status=’OPTIN’ Then ‘CONPHN’ If email_perm_status!=’OPTIN’ ANDa address_perm_status=’OPTIN’ AND phone_perm_status!=’OPTIN’ THEN ‘CONDML’ If email_perm_status=’OPTIN’ AND address_perm_status=’OPTIN’ AND phone_perm_status!=’OPTIN’ THEN ‘CONEMLDML’ If email_perm_status=’OPTIN’ AND address_perm_status!=’OPTIN’ AND phone_perm_status=’OPTIN’ THEN ‘CONEMLPHN’ If email_perm_status!=’OPTIN’ AND address_perm_status=’OPTIN’ AND phone_perm_status=’OPTIN’ THEN ‘CONDMLPHN’ | K52: Y | L52: Y | M52: Y | N52: Y | O52: Y | P52: Y | Q52: Y | S52: Y | T52: one-to-one | U52: one-to-one | V52: CIC | W52: 0 | X52: Use Case | Y52: 1 | Z52: In GDM & C360 | AA52: Already have | AH52: =IF(OR(AC52="X", AD52 = "X", AE52="X", AF52="X", AG52="X"), "Y", "") | AI52: Y | AJ52: Y | AK52: Y | AL52: Y | AM52: =AND(AI52="Y",AJ52="Y",AK52="Y",AL52="Y") -> TRUE | AN52: =OR(AI52="Y",AJ52="Y",AK52="Y",AL52="Y") -> TRUE | AO52: Y
B53: Customer | C53: Contactability | D53: Contact Information | E53: Contact Preference | F53: Email contact permission/OptIn | G53: email_perm_status | I53: crm_base.customer360 | J53: Indicates if account/professional has given permission (subscribed) to contact her on any given email, examing the opt-in status attached to every email on file for the customer | K53: Y | L53: Y | M53: Y | N53: Y | O53: Y | P53: Y | Q53: Y | R53: Y | S53: Y | T53: one-to-one | U53: one-to-one | V53: CID | W53: 0 | X53: Use Case | Y53: 1 | Z53: KPI, Not in C360 | AA53: Already have | AC53: X | AE53: X | AG53: X | AH53: =IF(OR(AC53="X", AD53 = "X", AE53="X", AF53="X", AG53="X"), "Y", "") -> Y | AI53: Y | AJ53: Y | AK53: Y | AL53: Y | AM53: =AND(AI53="Y",AJ53="Y",AK53="Y",AL53="Y") -> TRUE | AN53: =OR(AI53="Y",AJ53="Y",AK53="Y",AL53="Y") -> TRUE | AO53: Y
B54: Customer | C54: Contactability | D54: Contact Information | E54: Contact Preference | F54: OptInGroup | G54: N/A | H54: We can create a field for this | I54: N/A | J54: Group marketing preference | K54: Y | L54: Y | M54: Y | N54: N | O54: N | P54: Y | S54: N | T54: one-to-one | U54: one-to-one | W54: 2 | X54: Global Ask | Y54: 1 | Z54: Transunion Key | AA54: Need info | AH54: =IF(OR(AC54="X", AD54 = "X", AE54="X", AF54="X", AG54="X"), "Y", "") | AI54: N/A | AJ54: N/A | AK54: N/A | AL54: N/A | AM54: =AND(AI54="Y",AJ54="Y",AK54="Y",AL54="Y") -> FALSE | AN54: =OR(AI54="Y",AJ54="Y",AK54="Y",AL54="Y") -> FALSE | AO54: Y
B55: Customer | C55: Contactability | D55: Contact Information | E55: Contact Preference | F55: OptInOther | G55: N/A | H55: We can create a field for this | I55: N/A | J55: Other marketing preference | K55: Y | L55: Y | M55: Y | N55: N | O55: N | P55: Y | S55: N | T55: one-to-one | U55: one-to-one | W55: 2 | X55: Global Ask | Y55: 2 | Z55: In GDM & C360 | AA55: Need info | AH55: =IF(OR(AC55="X", AD55 = "X", AE55="X", AF55="X", AG55="X"), "Y", "") | AI55: N/A | AJ55: N/A | AK55: N/A | AL55: N/A | AM55: =AND(AI55="Y",AJ55="Y",AK55="Y",AL55="Y") -> FALSE | AN55: =OR(AI55="Y",AJ55="Y",AK55="Y",AL55="Y") -> FALSE | AO55: Y
B56: Customer | C56: Contactability | D56: Contact Information | E56: Contact Preference | F56: OptInSNS | G56: N/A | H56: We can create a field for this | I56: N/A | J56: Social Media marketing | K56: Y | L56: Y | M56: Y | N56: N | O56: N | P56: Y | S56: N | T56: one-to-one | U56: one-to-one | W56: 2 | X56: Global Ask | Y56: 1 | Z56: In GDM & C360 | AH56: =IF(OR(AC56="X", AD56 = "X", AE56="X", AF56="X", AG56="X"), "Y", "") | AI56: N/A | AJ56: N/A | AK56: N/A | AL56: N/A | AM56: =AND(AI56="Y",AJ56="Y",AK56="Y",AL56="Y") -> FALSE | AN56: =OR(AI56="Y",AJ56="Y",AK56="Y",AL56="Y") -> FALSE | AO56: Y
B57: Customer | C57: Contactability | D57: Contact Information | E57: Contact Preference | F57: Phone contact permission/OptIn | G57: phone_perm_status | I57: crm_reporting.fact_customer_segment_by_brand_latest_snap | J57: Indicates if account/professional has given permission (subscribed) to contact (call) her on any given phone number, examing the opt-in status attached to every phone number on file for the customer | K57: Y | L57: Y | M57: Y | N57: N | O57: Y | P57: Y | Q57: Y | S57: Y | T57: one-to-one | U57: one-to-one | V57: CIP | W57: 0 | X57: Use Case | Y57: 2 | Z57: In GDM & C360 | AA57: Easy Add | AB57: in customer_contacts. DONE | AE57: X | AF57: X | AH57: =IF(OR(AC57="X", AD57 = "X", AE57="X", AF57="X", AG57="X"), "Y", "") -> Y | AI57: Y | AJ57: Y | AK57: Y | AL57: Y | AM57: =AND(AI57="Y",AJ57="Y",AK57="Y",AL57="Y") -> TRUE | AN57: =OR(AI57="Y",AJ57="Y",AK57="Y",AL57="Y") -> TRUE | AO57: Y
B58: Customer | C58: Contactability | D58: Contact Information | E58: Contact Preference | F58: Postal contact permission/OptIn | G58: address_perm_status | I58: crm_reporting.fact_customer_segment_by_brand_latest_snap | J58: Specifies if the account/professional can be contacted through direct mail or not at any given address, examing the opt-in status attached to every address on file for the customer | K58: Y | L58: Y | M58: Y | N58: N | O58: Y | P58: Y | Q58: Y | S58: Y | T58: one-to-one | U58: one-to-one | V58: 0 | W58: 0 | X58: Use Case | Y58: 1 | Z58: Need to Clarify with Global | AA58: Easy Add | AB58: in customer_contacts. DONE | AH58: =IF(OR(AC58="X", AD58 = "X", AE58="X", AF58="X", AG58="X"), "Y", "") | AI58: Y | AJ58: Y | AK58: Y | AL58: Y | AM58: =AND(AI58="Y",AJ58="Y",AK58="Y",AL58="Y") -> TRUE | AN58: =OR(AI58="Y",AJ58="Y",AK58="Y",AL58="Y") -> TRUE | AO58: Y
B59: Customer | C59: Contactability | D59: Contact Information | E59: Contact Preference | F59: Sms contact permission/OptIn | G59: sms_double_optin | I59: crm_reporting.fact_customer_segment_by_brand_latest_snap | J59: Represents the permission status of SMS communication, indicating whether the customer has given permission to be contacted via SMS or not on any provided phone number, examing the opt-in status attached to every phone number on file for the customer | K59: Y | L59: Y | M59: Y | N59: N | O59: Y | P59: Y | Q59: Y | R59: Y | S59: Y | T59: one-to-one | U59: one-to-one | V59: CIP | W59: 0 | X59: Use Case | Y59: 2 | Z59: In GDM & C360 | AA59: Easy Add | AB59: in customer_contacts. DONE | AC59: X | AD59: X | AE59: X | AF59: X | AH59: =IF(OR(AC59="X", AD59 = "X", AE59="X", AF59="X", AG59="X"), "Y", "") -> Y | AI59: Y | AJ59: Y | AK59: Y | AL59: Y | AM59: =AND(AI59="Y",AJ59="Y",AK59="Y",AL59="Y") -> TRUE | AN59: =OR(AI59="Y",AJ59="Y",AK59="Y",AL59="Y") -> TRUE | AO59: Y
B60: Customer | C60: Contactability | D60: Contact Information | E60: Contact Preference | F60: Targeted advertisement flag | G60: targeted_advertisement_flag | I60: crm_base.customer360 | J60: Indicates if a consumer has opted into receive targeted ads (only applicable for certain States) | K60: N | L60: Y | M60: Y | N60: Y | O60: Y | P60: Y | Q60: Y | S60: N | T60: one-to-one | U60: one-to-one | V60: CIC | W60: 0 | X60: Use Case | Y60: 2 | Z60: Not in C360, reporting | AA60: Already have | AC60: X | AD60: X | AE60: X | AF60: X | AG60: X | AH60: =IF(OR(AC60="X", AD60 = "X", AE60="X", AF60="X", AG60="X"), "Y", "") -> Y | AM60: =AND(AI60="Y",AJ60="Y",AK60="Y",AL60="Y") -> FALSE | AN60: =OR(AI60="Y",AJ60="Y",AK60="Y",AL60="Y") -> FALSE | AO60: Y
B61: Customer | C61: Contactability | D61: Contact Information | E61: Digital Contact | F61: Valid contact email | G61: ValidEmail | I61: crm_data_sharing.sdds_contacts | J61: Indicates whether or not the customer record has a valid email address | K61: Y | L61: Y | M61: Y | N61: N | O61: N | P61: Y | S61: N | T61: one-to-one | U61: one-to-one | W61: 2 | X61: GDM | Y61: 1 | AA61: Very Difficult | AH61: =IF(OR(AC61="X", AD61 = "X", AE61="X", AF61="X", AG61="X"), "Y", "")
B62: Customer | C62: Contactability | D62: Contact Information | E62: Digital Contact | F62: Valid contact phone | G62: ValidMobileNumber | I62: crm_data_sharing.sdds_contacts | J62: Indicates whether or not the customer record has a valid phone number | K62: Y | L62: Y | M62: Y | N62: N | O62: N | P62: Y | S62: N | T62: one-to-one | U62: one-to-one | W62: 2 | X62: GDM | Y62: 1 | AA62: Very Difficult | AH62: =IF(OR(AC62="X", AD62 = "X", AE62="X", AF62="X", AG62="X"), "Y", "")
B63: Customer | C63: Contactability | D63: Contact Information | E63: Physical Contact | F63: Valid contact postal address | G63: ValidAddress | I63: crm_data_sharing.sdds_contacts | J63: Indicates whether or not the customer record has a valid mailing address | K63: Y | L63: Y | M63: Y | N63: N | O63: N | P63: Y | S63: N | T63: one-to-one | U63: one-to-one | W63: 2 | X63: GDM | Y63: 2 | AA63: Very Difficult | AH63: =IF(OR(AC63="X", AD63 = "X", AE63="X", AF63="X", AG63="X"), "Y", "")
B64: Customer | C64: BMDM (Beauty Data) | D64: Contact Information | E64: Digital Contact | F64: HasBeautyProfileData | G64: has_beauty_profile | I64: crm_reporting.fact_customer_enriched | K64: Y | L64: Y | M64: Y | N64: N | O64: N | P64: Y | S64: N | T64: one-to-one | U64: one-to-one | V64: BPD | W64: 1 | X64: One Consumer Profile, C360 | Y64: 1 | Z64: DDX & GDM Analytics | AA64: Need info | AB64: It depends, if the value reflects the fact that the customer is in the beauty profile table | AH64: =IF(OR(AC64="X", AD64 = "X", AE64="X", AF64="X", AG64="X"), "Y", "") | AM64: =AND(AI64="Y",AJ64="Y",AK64="Y",AL64="Y") -> FALSE | AN64: =OR(AI64="Y",AJ64="Y",AK64="Y",AL64="Y") -> FALSE | AO64: Y
B65: Customer - Contacts | C65: Contact Info | D65: Contact Information | E65: Contact Detail | F65: Customer ID (within Brand) | G65: brand_customer_id | I65: crm_reporting.fact_customer_segment_by_brand_latest_snap | K65: N | L65: Y | M65: Y | N65: Y | O65: Y | P65: Y | Q65: Y | S65: N | T65: one-to-one | U65: one-to-one | W65: 1 | X65: Loyalty | Y65: 2 | Z65: In C360 | AA65: Already have | AH65: =IF(OR(AC65="X", AD65 = "X", AE65="X", AF65="X", AG65="X"), "Y", "") | AM65: =AND(AI65="Y",AJ65="Y",AK65="Y",AL65="Y") -> FALSE | AN65: =OR(AI65="Y",AJ65="Y",AK65="Y",AL65="Y") -> FALSE | AO65: Y
B66: Customer - Contacts | C66: Contact Info | D66: Contact Information | E66: Contact Detail | F66: Brand Code | G66: brand_code | I66: crm_base.mv_customer360_contacts | J66: Specifies the brand_code to which the customer belongs | K66: Y | L66: Y | M66: Y | N66: Y | O66: Y | P66: Y | Q66: Y | R66: Y | S66: N | T66: one-to-one | U66: one-to-one | V66: CIC | W66: 0 | X66: Use Case | Y66: 2 | Z66: Reporting | AA66: Already have | AC66: X | AD66: X | AE66: X | AF66: X | AG66: X | AH66: =IF(OR(AC66="X", AD66 = "X", AE66="X", AF66="X", AG66="X"), "Y", "") -> Y | AI66: Y | AJ66: Y | AK66: Y | AL66: Y | AM66: =AND(AI66="Y",AJ66="Y",AK66="Y",AL66="Y") -> TRUE | AN66: =OR(AI66="Y",AJ66="Y",AK66="Y",AL66="Y") -> TRUE | AO66: Y
B67: Customer - Contacts | C67: Contact Info | D67: Contact Information | E67: Contact Detail | F67: Division Code | G67: division_code | I67: crm_base.mv_customer360_contacts | J67: Specifies the division to which the customer belongs | K67: Y | L67: Y | M67: Y | N67: Y | O67: Y | P67: Y | Q67: Y | S67: N | T67: one-to-one | U67: one-to-one | W67: 0 | X67: Use Case | Z67: In Global One Consumer Profile & GDM Analytics | AA67: Already have | AD67: X | AH67: =IF(OR(AC67="X", AD67 = "X", AE67="X", AF67="X", AG67="X"), "Y", "") -> Y | AI67: Y | AJ67: Y | AK67: Y | AL67: Y | AM67: =AND(AI67="Y",AJ67="Y",AK67="Y",AL67="Y") -> TRUE | AN67: =OR(AI67="Y",AJ67="Y",AK67="Y",AL67="Y") -> TRUE | AO67: Y
B68: Customer - Contacts | C68: Contact Info | D68: Contact Information | E68: Physical Contact | F68: Country | G68: country_code | I68: crm_base.mv_customer360_contacts | K68: Y | L68: Y | M68: Y | N68: Y | O68: Y | P68: Y | Q68: Y | S68: N | T68: one-to-one | U68: one-to-one | V68: CIP | W68: 1 | X68: Liveramp | Y68: 2 | Z68: Not in C360 | AA68: Very Difficult | AB68: C | AH68: =IF(OR(AC68="X", AD68 = "X", AE68="X", AF68="X", AG68="X"), "Y", "") | AI68: Y | AJ68: Y | AK68: Y | AL68: Y | AM68: =AND(AI68="Y",AJ68="Y",AK68="Y",AL68="Y") -> TRUE | AN68: =OR(AI68="Y",AJ68="Y",AK68="Y",AL68="Y") -> TRUE | AO68: Y
B69: Customer - Contacts | C69: Contact Info | D69: Contact Information | E69: N/A | F69: brand country | G69: brand_country | I69: crm_base.mv_customer360_contacts | K69: N | L69: N | M69: N | N69: Y | O69: Y | P69: Y | Q69: Y | S69: N | T69: one-to-one | U69: one-to-one | W69: 1 | X69: One Consumer Profile, C360, Liveramp | Y69: 1 | Z69: Not in C360, no waves, reporting | AA69: Easy Add | AB69: DONE | AH69: =IF(OR(AC69="X", AD69 = "X", AE69="X", AF69="X", AG69="X"), "Y", "") | AM69: =AND(AI69="Y",AJ69="Y",AK69="Y",AL69="Y") -> FALSE | AN69: =OR(AI69="Y",AJ69="Y",AK69="Y",AL69="Y") -> FALSE | AO69: Y
B70: Customer - Contacts | C70: Contact Info | D70: Contact Information | E70: N/A | F70: address line 1 | G70: address_line1 | I70: crm_base.mv_customer360_contacts | K70: N | L70: N | M70: N | N70: Y | O70: Y | P70: Y | Q70: Y | S70: N | T70: one-to-one | U70: one-to-one | W70: 1 | X70: One Consumer Profile, C360, Liveramp | Y70: 2 | Z70: In C360 | AA70: Easy Add | AH70: =IF(OR(AC70="X", AD70 = "X", AE70="X", AF70="X", AG70="X"), "Y", "") | AI70: Y | AJ70: Y | AK70: Y | AL70: Y | AM70: =AND(AI70="Y",AJ70="Y",AK70="Y",AL70="Y") -> TRUE | AN70: =OR(AI70="Y",AJ70="Y",AK70="Y",AL70="Y") -> TRUE | AO70: Y
B71: Customer - Contacts | C71: Contact Info | D71: Contact Information | E71: N/A | F71: address line 2 | G71: address_line2 | I71: crm_base.mv_customer360_contacts | K71: N | L71: N | M71: N | N71: Y | O71: Y | P71: Y | Q71: Y | S71: N | T71: one-to-one | U71: one-to-one | W71: 1 | X71: Liveramp | Y71: 1 | Z71: Mostly null | AA71: Easy Add | AB71: in dim_customer_extn_hist | AH71: =IF(OR(AC71="X", AD71 = "X", AE71="X", AF71="X", AG71="X"), "Y", "") | AI71: Y | AJ71: Y | AK71: Y | AL71: Y | AM71: =AND(AI71="Y",AJ71="Y",AK71="Y",AL71="Y") -> TRUE | AN71: =OR(AI71="Y",AJ71="Y",AK71="Y",AL71="Y") -> TRUE | AO71: Y
B72: Customer - Contacts | C72: Contact Info | D72: Contact Information | E72: Physical Contact | F72: City | G72: city | I72: crm_base.mv_customer360_contacts | K72: N | L72: Y | M72: Y | N72: Y | O72: Y | P72: Y | Q72: Y | S72: N | T72: one-to-one | U72: one-to-one | V72: CIP | W72: 1 | X72: Liveramp | Y72: 2 | Z72: In GDM & C360 | AA72: Need Info | AB72: address_city in dim_customer_extn_hist? | AH72: =IF(OR(AC72="X", AD72 = "X", AE72="X", AF72="X", AG72="X"), "Y", "") | AI72: Y | AJ72: Y | AK72: Y | AL72: Y | AM72: =AND(AI72="Y",AJ72="Y",AK72="Y",AL72="Y") -> TRUE | AN72: =OR(AI72="Y",AJ72="Y",AK72="Y",AL72="Y") -> TRUE | AO72: N
B73: Customer - Contacts | C73: Contact Info | D73: Contact Information | E73: Physical Contact | F73: State | G73: state_code | I73: crm_base.mv_customer360_contacts | K73: N | L73: Y | M73: Y | N73: Y | O73: Y | P73: Y | Q73: Y | S73: N | T73: one-to-one | U73: one-to-one | W73: 2 | X73: No Use Case | Y73: 1 | Z73: In GDM & C360 | AA73: ? | AB73: address_state in dim_customer_extn_hist? | AH73: =IF(OR(AC73="X", AD73 = "X", AE73="X", AF73="X", AG73="X"), "Y", "") | AI73: Y | AJ73: Y | AK73: Y | AL73: Y | AM73: =AND(AI73="Y",AJ73="Y",AK73="Y",AL73="Y") -> TRUE | AN73: =OR(AI73="Y",AJ73="Y",AK73="Y",AL73="Y") -> TRUE | AO73: Y
B74: Customer - Contacts | C74: Contact Info | D74: Contact Information | E74: N/A | F74: zip code (4) | G74: zip4 | I74: crm_base.mv_customer360_contacts | K74: N | L74: N | M74: N | N74: Y | O74: Y | P74: Y | Q74: Y | S74: N | T74: one-to-one | U74: one-to-one | W74: 1 | X74: Liveramp | Y74: 2 | AA74: Easy Add | AH74: =IF(OR(AC74="X", AD74 = "X", AE74="X", AF74="X", AG74="X"), "Y", "") | AM74: =AND(AI74="Y",AJ74="Y",AK74="Y",AL74="Y") -> FALSE | AN74: =OR(AI74="Y",AJ74="Y",AK74="Y",AL74="Y") -> FALSE
B75: Customer - Contacts | C75: Contact Info | D75: Contact Information | E75: N/A | F75: zip code (5) | G75: zip5 | I75: crm_base.mv_customer360_contacts | K75: N | L75: N | M75: N | N75: Y | O75: Y | P75: Y | S75: N | T75: one-to-one | U75: one-to-one | W75: 1 | X75: In GDM & C360 | Y75: 1 | AA75: Easy Add | AH75: =IF(OR(AC75="X", AD75 = "X", AE75="X", AF75="X", AG75="X"), "Y", "") | AM75: =AND(AI75="Y",AJ75="Y",AK75="Y",AL75="Y") -> FALSE | AN75: =OR(AI75="Y",AJ75="Y",AK75="Y",AL75="Y") -> FALSE
B76: Customer - Contacts | C76: Contact Info | D76: Contact Information | E76: N/A | F76: postal code | G76: postal_code | I76: crm_base.mv_customer360_contacts | K76: N | L76: N | M76: N | N76: Y | O76: Y | P76: Y | Q76: Y | S76: N | T76: one-to-one | U76: one-to-one | W76: 1 | X76: One Consumer Profile, C360, Liveramp | Y76: 2 | Z76: Check if null | AA76: Easy Add | AB76: in dim_customer_extn_hist | AH76: =IF(OR(AC76="X", AD76 = "X", AE76="X", AF76="X", AG76="X"), "Y", "") | AI76: Y | AJ76: Y | AK76: Y | AL76: Y | AM76: =AND(AI76="Y",AJ76="Y",AK76="Y",AL76="Y") -> TRUE | AN76: =OR(AI76="Y",AJ76="Y",AK76="Y",AL76="Y") -> TRUE | AO76: Y
B77: Customer - Contacts | C77: Contact Info | D77: Contact Information | E77: Contact Preference | F77: Postal contact permission/OptIn | G77: address_perm_status | I77: crm_base.dim_subscriber | J77: Specifies if the account/professional can be contacted through direct mail or not | K77: N | L77: Y | M77: Y | N77: N | O77: Y | P77: Y | Q77: Y | S77: N | T77: one-to-one | U77: one-to-one | V77: CIP | W77: 1 | X77: One Consumer Profile, C360, Liveramp | Y77: 2 | Z77: Need Info from Global | AA77: Easy Add | AB77: in customer_contacts. DONE | AH77: =IF(OR(AC77="X", AD77 = "X", AE77="X", AF77="X", AG77="X"), "Y", "") | AI77: Y | AJ77: Y | AK77: Y | AL77: Y | AM77: =AND(AI77="Y",AJ77="Y",AK77="Y",AL77="Y") -> TRUE | AN77: =OR(AI77="Y",AJ77="Y",AK77="Y",AL77="Y") -> TRUE | AO77: Y
B78: Customer - Contacts | C78: Contact Info | D78: Contact Information | E78: Contact Detail | F78: Last update date and time / Last update type | G78: address_last_updated_dt | I78: crm_base.mv_customer360_contacts | K78: N | L78: Y | M78: Y | N78: Y | O78: Y | P78: Y | S78: N | T78: one-to-one | U78: one-to-one | W78: 1 | X78: OCP | Y78: 1 | Z78: GA Data | AA78: Easy Add | AB78: in dim_customer_extn_hist, field address_last_updated_dt | AH78: =IF(OR(AC78="X", AD78 = "X", AE78="X", AF78="X", AG78="X"), "Y", "") | AM78: =AND(AI78="Y",AJ78="Y",AK78="Y",AL78="Y") -> FALSE | AN78: =OR(AI78="Y",AJ78="Y",AK78="Y",AL78="Y") -> FALSE | AO78: Y
B79: Customer - Contacts | C79: Contact Info | D79: Contact Information | E79: Contact Detail | F79: Last update date and time / Last update type | G79: address_perm_status_modified_dt | I79: crm_data_sharing.sdds_direct_campaign_master | J79: The date and time when the customer's address contact permission status was last modified. This can be used to track changes made to the record over time. | K79: N | L79: Y | M79: Y | N79: N | O79: Y | P79: Y | Q79: Y | S79: N | T79: one-to-one | U79: one-to-one | W79: 1 | X79: TransUnion | Y79: 1 | Z79: In GDM & C360 | AA79: Need info | AB79: not found | AH79: =IF(OR(AC79="X", AD79 = "X", AE79="X", AF79="X", AG79="X"), "Y", "") | AM79: =AND(AI79="Y",AJ79="Y",AK79="Y",AL79="Y") -> FALSE | AN79: =OR(AI79="Y",AJ79="Y",AK79="Y",AL79="Y") -> FALSE | AO79: Y
B80: Customer - Contacts | C80: Contact Info | D80: Contact Information | E80: Physical Contact | F80: Phone Number / Cell Number / Email Address | G80: contact_value | I80: crm_base.mv_customer360_contacts | J80: Together, contact_type, contact_sub_type, and contact value provide the contact information for a given consumer where present. Possible values for contact_type | K80: N | L80: Y | M80: Y | N80: Y | O80: Y | P80: Y | S80: N | T80: one-to-many | U80: one-to-one | W80: 0 | X80: Use Case | Y80: N/A | Z80: In GDM & C360 | AA80: Easy Add | AB80: DONE | AC80: X | AD80: X | AE80: X | AF80: X | AG80: X | AH80: =IF(OR(AC80="X", AD80 = "X", AE80="X", AF80="X", AG80="X"), "Y", "") -> Y | AM80: =AND(AI80="Y",AJ80="Y",AK80="Y",AL80="Y") -> FALSE | AN80: =OR(AI80="Y",AJ80="Y",AK80="Y",AL80="Y") -> FALSE | AO80: Y
B81: Customer - Contacts | C81: Contact Info | D81: Contact Information | E81: Physical Contact | F81: Phone Number / Cell Number / Email Address | G81: contact_type | I81: crm_base.mv_customer360_contacts | K81: N | L81: Y | M81: Y | N81: Y | O81: Y | P81: Y | S81: N | T81: one-to-many | U81: one-to-one | W81: 0 | X81: Use Case | Y81: N/A | Z81: In GDM & C360 | AA81: Easy Add | AB81: DONE | AC81: X | AD81: X | AE81: X | AF81: X | AG81: X | AH81: =IF(OR(AC81="X", AD81 = "X", AE81="X", AF81="X", AG81="X"), "Y", "") -> Y | AM81: =AND(AI81="Y",AJ81="Y",AK81="Y",AL81="Y") -> FALSE | AN81: =OR(AI81="Y",AJ81="Y",AK81="Y",AL81="Y") -> FALSE | AO81: Y
B82: Customer - Contacts | C82: Contact Info | D82: Contact Information | E82: Physical Contact | F82: Phone Number / Cell Number / Email Address | G82: contact_sub_type | I82: crm_base.mv_customer360_contacts | K82: N | L82: Y | M82: Y | N82: Y | O82: Y | P82: Y | S82: N | T82: one-to-many | U82: one-to-one | W82: 0 | X82: Use Case | Y82: 2 | Z82: In C360 | AA82: Easy Add | AB82: DONE | AC82: X | AD82: X | AE82: X | AF82: X | AG82: X | AH82: =IF(OR(AC82="X", AD82 = "X", AE82="X", AF82="X", AG82="X"), "Y", "") -> Y | AM82: =AND(AI82="Y",AJ82="Y",AK82="Y",AL82="Y") -> FALSE | AN82: =OR(AI82="Y",AJ82="Y",AK82="Y",AL82="Y") -> FALSE | AO82: Y
B83: Customer - Contacts | C83: Contact Info | D83: Contact Information | E83: Contact Preference | F83: Email contact permission/OptIn | G83: email_perm_status | I83: crm_base.mv_customer360_contacts | K83: N | L83: Y | M83: Y | N83: Y | O83: Y | P83: Y | Q83: Y | R83: Y | S83: N | T83: one-to-one | U83: one-to-one | W83: 0 | X83: Use Case | Y83: 1 | Z83: Need to Clarify with Global | AA83: Already have | AC83: X | AG83: X | AH83: =IF(OR(AC83="X", AD83 = "X", AE83="X", AF83="X", AG83="X"), "Y", "") -> Y | AI83: Y | AJ83: Y | AK83: Y | AL83: Y | AM83: =AND(AI83="Y",AJ83="Y",AK83="Y",AL83="Y") -> TRUE | AN83: =OR(AI83="Y",AJ83="Y",AK83="Y",AL83="Y") -> TRUE | AO83: Y
B84: Customer - Contacts | C84: Contact Info | D84: Contact Information | E84: Contact Preference | F84: Source of email opt-in collection | G84: Source of email opt-in collection | H84: Dependent on interaction table | I84: TO CREATE PER NEW GDM SPECS | K84: N | L84: Y | M84: Y | N84: N | O84: N | P84: Y | S84: N | T84: one-to-one | U84: one-to-one | V84: CID | W84: 2 | X84: No Use Case | Y84: 2 | Z84: In Global One Consumer Profile & GDM Analytics | AA84: ? | AB84: if contact_perm_status_modified_src field in dim_subscriber else provide source | AH84: =IF(OR(AC84="X", AD84 = "X", AE84="X", AF84="X", AG84="X"), "Y", "") | AM84: =AND(AI84="Y",AJ84="Y",AK84="Y",AL84="Y") -> FALSE | AN84: =OR(AI84="Y",AJ84="Y",AK84="Y",AL84="Y") -> FALSE | AO84: Y
B85: Customer - Contacts | C85: Contact Info | D85: Contact Information | E85: Contact Detail | F85: Last update date and time / Last update type | G85: email_perm_status_modified_dt | I85: crm_base.mv_customer360_contacts | K85: N | L85: Y | M85: Y | N85: Y | O85: Y | P85: Y | Q85: Y | R85: Y | S85: N | T85: one-to-one | U85: one-to-one | W85: 1 | X85: Liveramp, Attentive | Y85: N/A | Z85: Reporting | AA85: Easy Add | AB85: in dim_subscriber as contact_perm_status_modified_dt? or is it sys_last_modified_dt for the record in dim_customer_extn_hist | AH85: =IF(OR(AC85="X", AD85 = "X", AE85="X", AF85="X", AG85="X"), "Y", "") | AM85: =AND(AI85="Y",AJ85="Y",AK85="Y",AL85="Y") -> FALSE | AN85: =OR(AI85="Y",AJ85="Y",AK85="Y",AL85="Y") -> FALSE | AO85: Y
B86: Customer - Contacts | C86: Contact Info | D86: Contact Information | E86: Contact Preference | F86: Phone contact permission/OptIn | G86: phone_perm_status | I86: crm_base.mv_customer360_contacts | K86: N | L86: Y | M86: Y | N86: Y | O86: Y | P86: Y | Q86: Y | S86: N | T86: one-to-one | U86: one-to-one | V86: CIP | W86: 1 | X86: Liveramp | Y86: N/A | Z86: Not in C360, reporting | AA86: Easy Add | AB86: in customer_contacts. DONE | AH86: =IF(OR(AC86="X", AD86 = "X", AE86="X", AF86="X", AG86="X"), "Y", "") | AI86: Y | AJ86: Y | AK86: Y | AL86: Y | AM86: =AND(AI86="Y",AJ86="Y",AK86="Y",AL86="Y") -> TRUE | AN86: =OR(AI86="Y",AJ86="Y",AK86="Y",AL86="Y") -> TRUE | AO86: Y
B87: Customer - Contacts | C87: Contact Info | D87: Contact Information | E87: Contact Detail | F87: Last update date and time / Last update type | G87: phone_perm_status_modified_dt | I87: crm_base.mv_customer360_contacts | K87: N | L87: Y | M87: Y | N87: Y | O87: Y | P87: Y | Q87: Y | S87: N | T87: one-to-one | U87: one-to-one | W87: 1 | X87: Liveramp | Y87: 1 | Z87: Reporting | AA87: Easy Add | AB87: in dim_subscriber as contact_perm_status_modified_dt? or is it sys_last_modified_dt for the record in dim_customer_extn_hist | AH87: =IF(OR(AC87="X", AD87 = "X", AE87="X", AF87="X", AG87="X"), "Y", "") | AM87: =AND(AI87="Y",AJ87="Y",AK87="Y",AL87="Y") -> FALSE | AN87: =OR(AI87="Y",AJ87="Y",AK87="Y",AL87="Y") -> FALSE | AO87: Y
B88: Customer - Contacts | C88: Contact Info | D88: Contact Information | E88: Contact Preference | F88: Sms contact permission/OptIn | G88: sms_perm_status | I88: crm_base.mv_customer360_contacts | K88: N | L88: Y | M88: Y | N88: Y | O88: Y | P88: Y | Q88: Y | S88: N | T88: one-to-one | U88: one-to-one | V88: CIP | W88: 0 | X88: Use Case | Y88: 1 | Z88: In Global One Consumer Profile & GDM Analytics | AA88: Easy Add | AB88: DONE | AC88: X | AE88: X | AF88: X | AG88: X | AH88: =IF(OR(AC88="X", AD88 = "X", AE88="X", AF88="X", AG88="X"), "Y", "") -> Y | AI88: Y | AJ88: Y | AK88: Y | AL88: Y | AM88: =AND(AI88="Y",AJ88="Y",AK88="Y",AL88="Y") -> TRUE | AN88: =OR(AI88="Y",AJ88="Y",AK88="Y",AL88="Y") -> TRUE | AO88: Y
B89: Customer - Contacts | C89: Contact Info | D89: Contact Information | E89: Contact Preference | F89: Source of SMS opt-in collection | G89: sms_perm_status_modified_src | I89: crm_base.dim_subscriber | K89: N | L89: Y | M89: Y | N89: N | O89: N | P89: Y | S89: N | T89: one-to-one | U89: one-to-one | V89: CIP | W89: 2 | X89: No Use Case | Y89: 1 | Z89: Not in C360, no waves, reporting | AA89: Easy Add | AB89: in dim_subscriber | AH89: =IF(OR(AC89="X", AD89 = "X", AE89="X", AF89="X", AG89="X"), "Y", "") | AM89: =AND(AI89="Y",AJ89="Y",AK89="Y",AL89="Y") -> FALSE | AN89: =OR(AI89="Y",AJ89="Y",AK89="Y",AL89="Y") -> FALSE | AO89: Y
B90: Customer - Contacts | C90: Contact Info | D90: Contact Information | E90: Contact Detail | F90: Last update date and time / Last update type | G90: sms_perm_status_modified_dt | I90: crm_base.mv_customer360_contacts | K90: N | L90: Y | M90: Y | N90: Y | O90: Y | P90: Y | Q90: Y | S90: N | T90: one-to-one | U90: one-to-one | W90: 1 | X90: TransUnion | Y90: 1 | Z90: Not in C360, no waves | AA90: Easy Add | AB90: in dim_subscriber as sms_perm_status_modified_dt? or is it sys_last_modified_dt for the record in dim_customer_extn_hist | AH90: =IF(OR(AC90="X", AD90 = "X", AE90="X", AF90="X", AG90="X"), "Y", "") | AM90: =AND(AI90="Y",AJ90="Y",AK90="Y",AL90="Y") -> FALSE | AN90: =OR(AI90="Y",AJ90="Y",AK90="Y",AL90="Y") -> FALSE | AO90: Y
B91: Customer - Contacts | C91: Contact Info | D91: Contact Information | E91: Contact Detail | F91: Last update date and time / Last update type | G91: sms_double_optin_modified_dt | I91: crm_base.mv_customer360_contacts | K91: N | L91: Y | M91: Y | N91: Y | O91: Y | P91: Y | Q91: Y | R91: Y | S91: N | T91: one-to-one | U91: one-to-one | V91: 0 | W91: 1 | X91: TransUnion, Attentive | Y91: 1 | Z91: Need to Clarify with Global | AA91: Easy Add | AB91: in dim_subscriber as sms_double_optin_modified_dt? or is it sys_last_modified_dt for the record in dim_customer_extn_hist | AH91: =IF(OR(AC91="X", AD91 = "X", AE91="X", AF91="X", AG91="X"), "Y", "") | AM91: =AND(AI91="Y",AJ91="Y",AK91="Y",AL91="Y") -> FALSE | AN91: =OR(AI91="Y",AJ91="Y",AK91="Y",AL91="Y") -> FALSE | AO91: Y
B92: Customer - Contacts | C92: Contact Info | D92: Contact Information | E92: Contact Preference | F92: Sms contact permission/OptIn | G92: sms_double_optin | I92: crm_base.mv_customer360_contacts | K92: N | L92: Y | M92: Y | N92: Y | O92: Y | P92: Y | Q92: Y | R92: Y | S92: N | T92: one-to-one | U92: one-to-one | V92: CIP | W92: 2 | X92: No Use Case | Y92: 2 | Z92: In Global One Consumer Profile & GDM Analytics | AA92: Easy Add | AB92: in customer_contacts. DONE | AH92: =IF(OR(AC92="X", AD92 = "X", AE92="X", AF92="X", AG92="X"), "Y", "") | AI92: Y | AJ92: Y | AK92: Y | AL92: Y | AM92: =AND(AI92="Y",AJ92="Y",AK92="Y",AL92="Y") -> TRUE | AN92: =OR(AI92="Y",AJ92="Y",AK92="Y",AL92="Y") -> TRUE | AO92: Y
B93: Customer - Contacts | C93: Contact Info | D93: Contact Information | E93: Contact Preference | F93: Source of SMS opt-in collection | G93: sms_double_optin_modified_src | I93: crm_base.dim_subscriber | K93: N | L93: Y | M93: Y | N93: N | O93: N | P93: Y | S93: N | T93: one-to-one | U93: one-to-one | V93: CIP | W93: 2 | X93: No Use Case | Y93: 2 | Z93: Not in C360, no waves, reporting | AA93: Easy Add | AB93: in dim_subscriber | AH93: =IF(OR(AC93="X", AD93 = "X", AE93="X", AF93="X", AG93="X"), "Y", "") | AM93: =AND(AI93="Y",AJ93="Y",AK93="Y",AL93="Y") -> FALSE | AN93: =OR(AI93="Y",AJ93="Y",AK93="Y",AL93="Y") -> FALSE | AO93: Y
B94: Customer - Contacts | C94: Contact Info | D94: Contact Information | E94: Contact Detail | F94: Last modified date | G94: last_modified_dt | I94: crm_base.dim_subscriber | K94: N | L94: Y | M94: Y | N94: N | O94: N | P94: Y | Q94: Y | S94: N | T94: one-to-one | U94: one-to-one | V94: CIC | W94: 1 | X94: Liveramp | Y94: 1 | Z94: Reporting | AA94: Already have | AH94: =IF(OR(AC94="X", AD94 = "X", AE94="X", AF94="X", AG94="X"), "Y", "") | AI94: Y | AJ94: Y | AK94: Y | AL94: Y | AM94: =AND(AI94="Y",AJ94="Y",AK94="Y",AL94="Y") -> TRUE | AN94: =OR(AI94="Y",AJ94="Y",AK94="Y",AL94="Y") -> TRUE | AO94: Y
B95: Customer | C95: Acquisition Data | D95: Engagement | E95: N/A | F95: acquisition campaign name | G95: campaign_nm (acquisition-only) | H95: Bigger Project (don’t change color) | I95: crm_reporting.fact_customer_segment_by_brand_latest_snap | J95: Name of the campaign where the consumer was acquired | K95: Y | L95: N | M95: Y | N95: N | O95: N | P95: Y | S95: N | T95: one-to-one | U95: one-to-one | W95: 1 | X95: One Consumer Profile & C360 | Y95: N/A | Z95: In GDM & C360 | AA95: Easy Add | AH95: =IF(OR(AC95="X", AD95 = "X", AE95="X", AF95="X", AG95="X"), "Y", "") | AM95: =AND(AI95="Y",AJ95="Y",AK95="Y",AL95="Y") -> FALSE | AN95: =OR(AI95="Y",AJ95="Y",AK95="Y",AL95="Y") -> FALSE | AO95: Y
B96: Customer | C96: Acquisition Data | D96: Engagement | E96: Acquisition | F96: Acquisition channel device | G96: acquisition_device_key | I96: crm_reporting.fact_customer_segment_by_brand_latest_snap | K96: Y | L96: Y | M96: Y | N96: N | O96: N | P96: Y | S96: N | T96: one-to-one | U96: one-to-one | V96: EAC | W96: 1 | X96: One Consumer Profile & C360 | Y96: 2 | Z96: In GDM & C360 | AA96: Need Info | AH96: =IF(OR(AC96="X", AD96 = "X", AE96="X", AF96="X", AG96="X"), "Y", "") | AM96: =AND(AI96="Y",AJ96="Y",AK96="Y",AL96="Y") -> FALSE | AN96: =OR(AI96="Y",AJ96="Y",AK96="Y",AL96="Y") -> FALSE | AO96: Y
B97: Customer | C97: Acquisition Data | D97: Engagement | E97: Acquisition | F97: Acquisition channel key | G97: acquisition_channel_key | H97: Bigger Project (don’t change color) | I97: crm_base.customer360 | J97: This key is calculated based on the source at which the first engagement and the value is returned. UDF Logic to calculate acquisition channel: UDF receives all the interactions of the customer as Input. Input is divided into multiple lists as specified above. It retrieves the first record from the Profile Management list and retrieves the source name and acquisition source from the record. If the acquisition source is not empty or not null, then the source name is concatenated with acquisition source and the resultant value is returned, else if acquisition source is empty or null then the source name is returned. Note: If the resultant source name is ‘HARTEHANKS’ or ‘CRMLITE’ and if there is a record with the same interaction date with source name other than ‘HARTEHANKS’ or ‘CRMLITE’, then that record is considered as a priority. | K97: Y | L97: Y | M97: Y | N97: Y | O97: Y | P97: Y | Q97: Y | S97: N | T97: one-to-one | U97: one-to-one | V97: EAC | W97: 0 | X97: Use Case | Y97: 1 | Z97: In C360 | AA97: Already have | AC97: X | AE97: X | AH97: =IF(OR(AC97="X", AD97 = "X", AE97="X", AF97="X", AG97="X"), "Y", "") -> Y | AM97: =AND(AI97="Y",AJ97="Y",AK97="Y",AL97="Y") -> FALSE | AN97: =OR(AI97="Y",AJ97="Y",AK97="Y",AL97="Y") -> FALSE | AO97: Y
B98: Customer | C98: Acquisition Data | D98: Engagement | E98: N/A | F98: acquisition date key | G98: acquisition_date_key | I98: crm_base.customer360 | J98: The date of the first profile management record of the customer. UDF Logic to calculate acquisition date: UDF receives all the interactions of the customer as Input. Input is divided into multiple lists as specified above. It retrieves the first record from the Profile Management list and retrieves the date from the record. | K98: Y | L98: N | M98: Y | N98: Y | O98: Y | P98: Y | Q98: Y | S98: N | T98: one-to-one | U98: one-to-one | V98: EAC | W98: 0 | X98: Use Case | Y98: 1 | Z98: In C360 | AA98: Already have | AC98: X | AD98: X | AE98: X | AG98: X | AH98: =IF(OR(AC98="X", AD98 = "X", AE98="X", AF98="X", AG98="X"), "Y", "") -> Y | AI98: Y | AJ98: Y | AK98: Y | AL98: Y | AM98: =AND(AI98="Y",AJ98="Y",AK98="Y",AL98="Y") -> TRUE | AN98: =OR(AI98="Y",AJ98="Y",AK98="Y",AL98="Y") -> TRUE | AO98: Y
B99: Customer | C99: Acquisition Data | D99: Engagement | E99: Acquisition | F99: Acquisition medium | G99: acq_medium | H99: Bigger Project (don’t change color) | I99: crm_base.customer360 | J99: Acquisition medium | K99: N | L99: Y | M99: Y | N99: Y | O99: Y | P99: Y | Q99: Y | S99: N | T99: one-to-one | U99: one-to-one | V99: EAC | W99: 1 | X99: One Consumer Profile & C360 | Y99: 1 | Z99: DDX & Global One Consumer Data Profile | AA99: Easy Add | AH99: =IF(OR(AC99="X", AD99 = "X", AE99="X", AF99="X", AG99="X"), "Y", "") | AI99: Y | AJ99: Y | AK99: Y | AL99: Y | AM99: =AND(AI99="Y",AJ99="Y",AK99="Y",AL99="Y") -> TRUE | AN99: =OR(AI99="Y",AJ99="Y",AK99="Y",AL99="Y") -> TRUE | AO99: Y
B100: Customer | C100: Acquisition Data | D100: Engagement | E100: Acquisition | F100: Acquisition source | G100: source_name | I100: crm_base.customer360 | J100: Originating source system where the customer was acquired | K100: Y | L100: Y | M100: Y | N100: Y | O100: Y | P100: Y | Q100: Y | S100: N | T100: one-to-one | U100: one-to-one | V100: EAC | W100: 1 | X100: 1P Acquisition Framework/GDM | Y100: 1 | Z100: In GDM & C360 | AA100: Very Difficult | AB100: C | AE100: X | AG100: X | AH100: =IF(OR(AC100="X", AD100 = "X", AE100="X", AF100="X", AG100="X"), "Y", "") -> Y | AI100: Y | AJ100: Y | AK100: Y | AL100: Y | AM100: =AND(AI100="Y",AJ100="Y",AK100="Y",AL100="Y") -> TRUE | AN100: =OR(AI100="Y",AJ100="Y",AK100="Y",AL100="Y") -> TRUE | AO100: Y
B101: Customer | C101: Acquisition Data | D101: Engagement | E101: Acquisition | F101: Acquisition source | G101: acq_source | H101: Bigger Project (don’t change color) | I101: crm_base.customer360 | J101: This indicates the source where the customer was acquired from. Possible values: Website, Mobile. For manual upload, the following are the list: PopUp Store Media Leads Events Exhibits Product Launch Grand Opening Sweepstakes White Label Store Event 3rd Party Social Rewards Name Capture Cards Product Inserts | K101: N | L101: Y | M101: Y | N101: Y | O101: Y | P101: Y | Q101: Y | S101: N | T101: one-to-one | U101: one-to-one | V101: EAC | W101: 1 | X101: One Consumer Profile, C360, Liveramp | Y101: 1 | Z101: In C360 | AA101: Already have | AH101: =IF(OR(AC101="X", AD101 = "X", AE101="X", AF101="X", AG101="X"), "Y", "") | AI101: Y | AJ101: Y | AK101: Y | AL101: Y | AM101: =AND(AI101="Y",AJ101="Y",AK101="Y",AL101="Y") -> TRUE | AN101: =OR(AI101="Y",AJ101="Y",AK101="Y",AL101="Y") -> TRUE | AO101: Y
...

Sheet Customer
B2: Sub-Domain | C2: Source fields | D2: Source tables (Key DDX end table source of truth) | E2: In GDM Analytics Version? | F2: In GDM Activation Version? | G2: In C360 Tables? | H2: In Glossary? | I2: KPI? | J2: Customer Relationship | K2: Definition
B3: Identity | C3: brand_customer_id | D3: crm_reporting.fact_customer_segment_by_brand_latest_snap | E3: Y | F3: Y | H3: Y | J3: one-to-one
B4: Identity | C4: brand_mdm_id | D4: crm_reporting.fact_customer_segment_by_brand_latest_snap | G4: Y | H4: Y | J4: one-to-one | K4: Identifier for the customer associated with the brand, allowing tracking of brand-specific customer information
B5: Identity | C5: ekey | D5: crm_reporting.vw_dp_neustar_customer | H5: Y | J5: one-to-one | K5: TransUnion unique consumer identifier (to be leveraged for identity resolution)
B6: Identity | C6: brand_code | D6: crm_base.customer360 | E6: Y | F6: Y | G6: Y | H6: Y | J6: one-to-one | K6: Specifies the brand_code to which the customer belongs
B7: Identity | C7: division_code | D7: crm_base.customer360 | E7: Y | F7: Y | G7: Y | H7: Y | J7: one-to-one | K7: Specifies the division to which the customer belongs
B8: Identity | C8: country_code | D8: crm_reporting.fact_customer_segment_by_brand_latest_snap | E8: Y | F8: Y | H8: Y | J8: one-to-one | K8: Country code of the customer address
B9: Identity | C9: first_name | D9: crm_base.customer360 | F9: Y | G9: Y | H9: Y | J9: one-to-one | K9: The customer's first name
B10: Identity | C10: last_name | D10: crm_base.customer360 | F10: Y | G10: Y | H10: Y | J10: one-to-one | K10: The customer's last name
B11: Identity | C11: birth_month_day | D11: crm_base.customer360 | E11: Y | F11: Y | G11: Y | H11: Y | J11: one-to-one | K11: Specifies the customer's birth month and day
B12: Identity | C12: gender | D12: crm_reporting.fact_customer_segment_by_brand_latest_snap | E12: Y | F12: Y | H12: Y | J12: one-to-one | K12: Specifies the gender of the customer
B13: Identity | C13: segment_name | D13: crm_base.customer360 | G13: Y | H13: Y | J13: one-to-one | K13: Name of the customer's sociovision segment
B14: Identity | C14: ltfg | D14: crm_base.customer360 | G14: Y | H14: Y | J14: one-to-one | K14: Indicates whether the customer is part of our long term frozen control group (ltfg) for A/B testing
B15: Identity | C15: last_modified_dt | D15: crm_base.customer360 | E15: Y | F15: Y | G15: Y | H15: Y | J15: one-to-one | K15: Specifies the date the customer's profile was last modified
B16: Identity | C16: IsControl | D16: ADD US GDM SOURCE TABLES | E16: Y | F16: Y | H16: Y | J16: one-to-one | K16: Consumer is in a global control group
B17: Identity | C17: effective_start_dt | D17: crm_reporting.customer_control_grp | E17: Y | F17: Y | J17: one-to-one | K17: Date which the consumer was placed in a global control group
B18: Identity | C18: effective_end_dt | D18: crm_reporting.customer_control_grp | E18: Y | F18: Y | J18: one-to-one | K18: Date which the consumer was removed from a global control group
B19: Contactability | C19: contactability_key | D19: crm_base.customer360 | E19: Y | F19: Y | G19: Y | H19: Y | J19: one-to-one | K19: Indicates whether the customer can be contacted through email, direct mail or both If email_perm_status=’OPTIN’ AND address_perm_status!=’OPTIN’ AND phone_perm_status!=’OPTIN’ Then ‘CONEML’ If email_perm_status!=’OPTIN’ AND address_perm_staus!=’OPTIN’ AND phone_perm_status=’OPTIN’ Then ‘CONPHN’ If email_perm_status!=’OPTIN’ ANDa address_perm_status=’OPTIN’ AND phone_perm_status!=’OPTIN’ THEN ‘CONDML’ If email_perm_status=’OPTIN’ AND address_perm_status=’OPTIN’ AND phone_perm_status!=’OPTIN’ THEN ‘CONEMLDML’ If email_perm_status=’OPTIN’ AND address_perm_status!=’OPTIN’ AND phone_perm_status=’OPTIN’ THEN ‘CONEMLPHN’ If email_perm_status!=’OPTIN’ AND address_perm_status=’OPTIN’ AND phone_perm_status=’OPTIN’ THEN ‘CONDMLPHN’
B20: Contactability | C20: email_perm_status | D20: crm_base.customer360 | E20: Y | F20: Y | G20: Y | H20: Y | J20: one-to-one | K20: Indicates if account/professional has given permission (subscribed) to contact her on the given email.
B21: Contactability | C21: sms_double_optin | D21: crm_reporting.fact_customer_segment_by_brand_latest_snap | E21: Y | F21: Y | H21: Y | J21: one-to-one | K21: Represents the permission status of SMS communication, indicating whether the customer has given permission to be contacted via SMS or not.
B22: Contactability | C22: phone_perm_status | D22: crm_reporting.fact_customer_segment_by_brand_latest_snap | E22: Y | F22: Y | H22: Y | J22: one-to-one | K22: Indicates if account/professional has given permission (subscribed) to contact her on the given phone no.
B23: Contactability | C23: address_perm_status | D23: crm_reporting.fact_customer_segment_by_brand_latest_snap | E23: Y | F23: Y | H23: Y | J23: one-to-one | K23: Specifies if the account/professional can be contacted through direct mail or not
B24: Contactability | C24: targeted_advertisement_flag | D24: crm_base.customer360 | G24: Y | H24: Y | J24: one-to-one | K24: Represents the permission status of targeted advertisement communication, indicating whether the customer has given permission to be contacted via targeted ads or not.
B25: Contactability | C25: ValidEmail | D25: ADD US GDM SOURCE TABLES | E25: Y | F25: Y | J25: one-to-one | K25: Indicates whether or not the customer record has a valid email address
B26: Contactability | C26: ValidMobileNumber | D26: ADD US GDM SOURCE TABLES | E26: Y | F26: Y | J26: one-to-one | K26: Indicates whether or not the customer record has a valid phone number
B27: Contactability | C27: ValidAddress | D27: ADD US GDM SOURCE TABLES | E27: Y | F27: Y | J27: one-to-one | K27: Indicates whether or not the customer record has a valid mailing address
B28: Acquisition Data | C28: source_name | D28: crm_base.customer360 | E28: Y | F28: Y | G28: Y | H28: Y | J28: one-to-one | K28: Originating source system where the customer was acquired
B29: Acquisition Data | C29: acq_source | D29: crm_base.customer360 | G29: Y | H29: Y | J29: one-to-one | K29: This indicates the source where the customer was acquired from. Possible values: Website, Mobile. For manual upload, the following are the list: PopUp Store Media Leads Events Exhibits Product Launch Grand Opening Sweepstakes White Label Store Event 3rd Party Social Rewards Name Capture Cards Product Inserts
B30: Acquisition Data | C30: acq_sub_source | D30: crm_base.customer360 | E30: Y | F30: Y | G30: Y | H30: Y | J30: one-to-one | K30: Refers to the sub source of the acquisition
B31: Acquisition Data | C31: acq_medium | D31: crm_base.customer360 | G31: Y | H31: Y | J31: one-to-one | K31: Acquisition medium
B32: Acquisition Data | C32: acquisition_channel_key | D32: crm_base.customer360 | E32: Y | F32: Y | G32: Y | H32: Y | J32: one-to-one | K32: This key is calculated based on the source at which the first engagement and the value is returned. UDF Logic to calculate acquisition channel: UDF receives all the interactions of the customer as Input. Input is divided into multiple lists as specified above. It retrieves the first record from the Profile Management list and retrieves the source name and acquisition source from the record. If the acquisition source is not empty or not null, then the source name is concatenated with acquisition source and the resultant value is returned, else if acquisition source is empty or null then the source name is returned. Note: If the resultant source name is ‘HARTEHANKS’ or ‘CRMLITE’ and if there is a record with the same interaction date with source name other than ‘HARTEHANKS’ or ‘CRMLITE’, then that record is considered as a priority.
B33: Acquisition Data | C33: acquisition_device_key | D33: crm_reporting.fact_customer_segment_by_brand_latest_snap | E33: Y | F33: Y | J33: one-to-one
B34: Acquisition Data | C34: registration_source | D34: crm_base.customer360 | F34: Y | G34: Y | H34: Y | J34: one-to-one | K34: refers to the source of registration
B35: Acquisition Data | C35: registration_sub_source | D35: crm_base.customer360 | F35: Y | G35: Y | H35: Y | J35: one-to-one | K35: Refers to the sub source of the registration
B36: Acquisition Data | C36: registration_status_key | D36: crm_base.customer360 | F36: Y | G36: Y | H36: Y | J36: one-to-one | K36: Refers to registration at the brand website or any other channel where account/professional registration is possible Registered, Not Registered
B37: Acquisition Data | C37: acquisition_date_key | D37: crm_base.customer360 | E37: Y | F37: Y | G37: Y | H37: Y | J37: one-to-one | K37: The date of the first profile management record of the customer. UDF Logic to calculate acquisition date: UDF receives all the interactions of the customer as Input. Input is divided into multiple lists as specified above. It retrieves the first record from the Profile Management list and retrieves the date from the record.
B38: Acquisition Data | C38: acquisition_source_type | D38: crm_base.dim_customer | E38: Y | F38: Y | H38: Y | J38: one-to-one
B39: Acquisition Data | C39: acquisition_source_touchpoint | D39: crm_base.dim_customer | E39: Y | F39: Y | H39: Y | J39: one-to-one
B40: Acquisition Data | C40: acquisition_source_channel | D40: crm_base.dim_customer | E40: Y | F40: Y | H40: Y | J40: one-to-one
B41: Acquisition Data | C41: acquisition_source_benefitid | D41: crm_base.dim_customer | E41: Y | F41: Y | H41: Y | J41: one-to-one
B42: Acquisition Data | C42: campaign_nm (acquisition-only) | D42: crm_reporting.fact_customer_segment_by_brand_latest_snap | E42: Y | F42: Y | J42: one-to-one | K42: Name of the campaign where the consumer was acquired
B43: Acquisition Data | C43: ga_src_channel_grp | D43: REPLACE WITH GA4 TABLE | G43: Y | H43: Y | J43: one-to-one | K43: channel name of first anonymous interaction
B44: BMDM (Beauty Data) | C44: concern_improvement_goal | D44: crm_base.customer360 | F44: Y | G44: Y | H44: Y | J44: one-to-one | K44: Concern improvement goal
B45: BMDM (Beauty Data) | C45: ingredient_limit | D45: crm_base.customer360 | G45: Y | H45: Y | J45: one-to-one | K45: Paraben free, Mineral oil free, Oil free, Alcohol free, Sulfates free, Organic, All Natural, Silicone free, Hypoallergenic, Fragrance free, Unscented, Formaldehyde Free, PABA Free, Ammonia Free, Non-comedogenic, Halal, Vegan
B46: BMDM (Beauty Data) | C46: product_category | D46: crm_base.customer360 | G46: Y | H46: Y | J46: one-to-one | K46: Product category
B47: BMDM (Beauty Data) | C47: eye_color | D47: crm_base.customer360 | F47: Y | G47: Y | H47: Y | J47: one-to-one | K47: Eye color of the customer
B48: BMDM (Beauty Data) | C48: face_product_finish_preference | D48: crm_base.customer360 | G48: Y | H48: Y | J48: one-to-one | K48: Matte, Glowy, "Dewy, Satin", Natural, "Semi-matte, Natural radiance", Long wearing
B49: BMDM (Beauty Data) | C49: product_finish | D49: crm_base.customer360 | F49: Y | G49: Y | H49: Y | J49: one-to-one | K49: Describes the finish of the product, such as matte, glossy, or semi-matte.
B50: BMDM (Beauty Data) | C50: lash_look_priority | D50: crm_base.customer360 | G50: Y | H50: Y | J50: one-to-one | K50: Volume, Volumizing / Thickening, Length Lenghtening / Long lashes, Definition, Seperate lashes, Curl, Curling, Waterproof
B51: BMDM (Beauty Data) | C51: makeup_expectation | D51: crm_base.customer360 | G51: Y | H51: Y | J51: one-to-one | K51: Makeup Expectation of the customer
B52: BMDM (Beauty Data) | C52: makeup_lip_product | D52: crm_base.customer360 | F52: Y | G52: Y | H52: Y | J52: one-to-one | K52: Makeup lip product
B53: BMDM (Beauty Data) | C53: makeup_look | D53: crm_base.customer360 | G53: Y | H53: Y | J53: one-to-one | K53: Make up look
B54: BMDM (Beauty Data) | C54: makeup_nail_product | D54: crm_base.customer360 | F54: Y | G54: Y | H54: Y | J54: one-to-one | K54: Make up nail product
B55: BMDM (Beauty Data) | C55: makeup_skill_level | D55: crm_base.customer360 | G55: Y | H55: Y | J55: one-to-one | K55: Make up skill level
B56: BMDM (Beauty Data) | C56: nail_aesthetic | D56: crm_base.customer360 | G56: Y | H56: Y | J56: one-to-one | K56: Nail Aesthetic
B57: BMDM (Beauty Data) | C57: nail_color | D57: crm_base.customer360 | G57: Y | H57: Y | J57: one-to-one | K57: Nail color of the customer
B58: BMDM (Beauty Data) | C58: nail_skill_level | D58: crm_base.customer360 | G58: Y | H58: Y | J58: one-to-one | K58: Nail skill level
B59: BMDM (Beauty Data) | C59: product_coverage | D59: crm_base.customer360 | G59: Y | H59: Y | J59: one-to-one | K59: Product coverage
B60: BMDM (Beauty Data) | C60: channel_preference | D60: crm_base.customer360 | G60: Y | H60: Y | J60: one-to-one | K60: Cruelty free, Dermatologist Tested, Opthamolgist Tested, Allergy Tested, Suitable For Sensitive Eyes
B61: BMDM (Beauty Data) | C61: device_preference | D61: crm_base.customer360 | G61: Y | H61: Y | J61: one-to-one | K61: Tablet, Desktop Laptop, Mobile Device, Multiple, All
B62: BMDM (Beauty Data) | C62: fragrance_family | D62: crm_base.customer360 | G62: Y | H62: Y | J62: one-to-one | K62: Citrus, Floral, Fougere, Oriental, Woody, Musk, Chype
B63: BMDM (Beauty Data) | C63: fragrance_note | D63: crm_base.customer360 | G63: Y | H63: Y | J63: one-to-one | K63: Aqua, Green, Aromatic, Fruity, White floral, Rose, Violet, Musk, Power musk, Leather, Amber, Spicy
B64: BMDM (Beauty Data) | C64: colorful_hair | D64: crm_base.customer360 | F64: Y | G64: Y | H64: Y | J64: one-to-one | K64: Blue, Pink, Green, Red, Yellow, Purple, Rainbow, Multiple
B65: BMDM (Beauty Data) | C65: hair_color | D65: crm_base.customer360 | F65: Y | G65: Y | H65: Y | J65: one-to-one | K65: Hair color of the customer
B66: BMDM (Beauty Data) | C66: hair_color_cover | D66: crm_base.customer360 | G66: Y | H66: Y | J66: one-to-one | K66: Hair color cover
B67: BMDM (Beauty Data) | C67: hair_color_service | D67: crm_base.customer360 | G67: Y | H67: Y | J67: one-to-one | K67: Hair color service
B68: BMDM (Beauty Data) | C68: hair_coloring_skill_level | D68: crm_base.customer360 | G68: Y | H68: Y | J68: one-to-one | K68: Represents the skill level required to apply hair coloring products.
B69: BMDM (Beauty Data) | C69: hair_style_service | D69: crm_base.customer360 | G69: Y | H69: Y | J69: one-to-one | K69: Straightener, Brazilian keratin treatment, Perm, Relaxer, None
B70: BMDM (Beauty Data) | C70: curls_texture | D70: crm_base.customer360 | G70: Y | H70: Y | J70: one-to-one | K70: Curls texture of the customer
B71: BMDM (Beauty Data) | C71: hair_care_product | D71: crm_base.customer360 | G71: Y | H71: Y | J71: one-to-one | K71: Hair care products
B72: BMDM (Beauty Data) | C72: hair_state | D72: crm_base.customer360 | F72: Y | G72: Y | H72: Y | J72: one-to-one | K72: Straight, Wavy, Loose waves, Curls, Curly, Coily, Kinky, Frizzy, Tight Curls
B73: BMDM (Beauty Data) | C73: hair_texture | D73: crm_base.customer360 | F73: Y | G73: Y | H73: Y | J73: one-to-one | K73: Hair texture of the customer: Thin, Medium, Normal, Coarse, Thick, Don't Know
B74: BMDM (Beauty Data) | C74: hair_type | D74: crm_base.customer360 | F74: Y | G74: Y | H74: Y | J74: one-to-one | K74: Very Dry, Somewhat Dry, Normal, Somewhat Oily, Somewhat greasy, Very Oily, Very greasy, Combination, Greasy roots and dry ends, Don't Know
B75: BMDM (Beauty Data) | C75: scalp_type | D75: crm_base.customer360 | F75: Y | G75: Y | H75: Y | J75: one-to-one | K75: Very Dry, Somewhat Dry, Normal, Somewhat Oily, Somewhat greasy, Very Oily, Greasy scalp, Don’t Know
B76: BMDM (Beauty Data) | C76: beauty_specialty_multi_brand | D76: crm_base.customer360 | G76: Y | H76: Y | J76: one-to-one | K76: Sephora, Ulta
B77: BMDM (Beauty Data) | C77: dept_store_high_end | D77: crm_base.customer360 | G77: Y | H77: Y | J77: one-to-one | K77: Straightener, Brazilian keratin treatment, Perm, Relaxer, None
B78: BMDM (Beauty Data) | C78: dept_store_national | D78: crm_base.customer360 | G78: Y | H78: Y | J78: one-to-one | K78: Sears, JCP, Kohl’s
B79: BMDM (Beauty Data) | C79: dept_store_regional | D79: crm_base.customer360 | G79: Y | H79: Y | J79: one-to-one | K79: Instant results, Easy removal, All day lastingness, Skin respect, "Transformative, visible results", Surprising Magical effects, 'Natural, “me better” results',All day lastingness, "Skin (eyes, lips) respect", Comfortable wear, Easy application, Results that adapt to me, "Long term benefits (anti-aging, moisturizing etc)", Easy to carry in my bag, Long lasting, Hydration, Color in one stroke, No migration, No feathering, Change my lip shade, Volume, No transfer, Easy to touch up, Non sticky feel
B80: BMDM (Beauty Data) | C80: drugstore | D80: crm_base.customer360 | G80: Y | H80: Y | J80: one-to-one | K80: CVS, Walgreens
B81: BMDM (Beauty Data) | C81: grocery_supermarket | D81: crm_base.customer360 | G81: Y | H81: Y | J81: one-to-one | K81: Grocery Supermarket
B82: BMDM (Beauty Data) | C82: mass_merchandise | D82: crm_base.customer360 | G82: Y | H82: Y | J82: one-to-one | K82: Target, Walmart
B83: BMDM (Beauty Data) | C83: pure_players | D83: crm_base.customer360 | G83: Y | H83: Y | J83: one-to-one | K83: Amazon, Ebay, Jet
B84: BMDM (Beauty Data) | C84: retailer_preference | D84: crm_base.customer360 | G84: Y | H84: Y | J84: one-to-one | K84: Retailer preference of the customer
B85: BMDM (Beauty Data) | C85: product_type | D85: crm_base.customer360 | G85: Y | H85: Y | J85: one-to-one | K85: Product type
B86: BMDM (Beauty Data) | C86: skin_tone | D86: crm_base.customer360 | F86: Y | G86: Y | H86: Y | J86: one-to-one | K86: Skin tone of the customer. Possible Values- Light, Fair, Medium, Tan, Brown, Very deep, Black, Don't Know
B87: BMDM (Beauty Data) | C87: skin_type | D87: crm_base.customer360 | F87: Y | G87: Y | H87: Y | J87: one-to-one | K87: Skin type of the customer
B88: BMDM (Beauty Data) | C88: skin_undertone | D88: crm_base.customer360 | G88: Y | H88: Y | J88: one-to-one | K88: Color underneath the surface of the skin. - Cool, Warm, Neutral, Don't Know
B89: BMDM (Beauty Data) | C89: zones | D89: crm_base.customer360 | F89: Y | G89: Y | H89: Y | J89: one-to-one | K89: Zones
B90: BMDM (Beauty Data) | C90: has_beauty_profile | D90: crm_reporting.fact_customer_enriched | E90: Y | F90: Y | J90: one-to-one
B91: BMDM (Beauty Data) | C91: nail_product_finish_preference | D91: crm_base.customer360 | F91: Y | H91: Y | J91: one-to-one | K91: Shiny, Satin, Matte
B92: BMDM (Beauty Data) | C92: hair_color_finish | D92: crm_base.customer360 | H92: Y | J92: one-to-one | K92: Hair color finish
B93: BMDM (Beauty Data) | C93: hair_treatment | D93: crm_base.customer360 | H93: Y | J93: one-to-one
B94: BMDM (Beauty Data) | C94: hair_wash_frequency | D94: crm_base.customer360 | F94: Y | H94: Y | J94: one-to-one | K94: Represents the frequency of hair washing, providing insights into hair care habits.
B95: BMDM (Beauty Data) | C95: heating_tool | D95: crm_base.customer360 | F95: Y | H95: Y | J95: one-to-one
B96: BMDM (Beauty Data) | C96: pro_treatment_regimen | D96: crm_base.customer360 | H96: Y | J96: one-to-one | K96: Pro Treatment regimen
B97: BMDM (Beauty Data) | C97: pro_treatments | D97: crm_base.customer360 | H97: Y | J97: one-to-one | K97: Pro treatments
B98: Loyalty | C98: is_loyalty | D98: crm_base.customer360 | E98: Y | F98: Y | G98: Y | H98: Y | J98: one-to-one | K98: Indicates if customer has taken a loyalty membership
B99: Loyalty | C99: loyalty_member_start_dt | D99: crm_base.customer360 | E99: Y | F99: Y | G99: Y | H99: Y | J99: one-to-one | K99: Date on which Loyalty card is activated.
B100: Loyalty | C100: loyalty_last_activity_dt | D100: crm_base.customer360 | E100: Y | F100: Y | G100: Y | H100: Y | J100: one-to-one | K100: Date of enrolment. Might be different from created_at in the case of feed enrollment.
B101: Loyalty | C101: last_login_dt | D101: crm_reporting.dim_customer | E101: Y | F101: Y | H101: Y | J101: one-to-one
...

Sheet Contacts
B1: NOTE: We can choose to either represent contact info in its own table (following the C360 model) or reconfigure it within a customer entity table to be represented at the one-to-one level (ex. email1, email2...), accounting for customers having multiple emails, phone numbers, etc.
B2: Sub-Domain | C2: Source fields (What DDX field(s) is feeding this field?) | D2: Source tables (Key DDX end table source of truth) | E2: In GDM Analytics Version? | F2: In GDM Activation Version? | G2: In C360 Tables? | H2: In Glossary? | I2: Customer Relationship | J2: Definition
B3: Contact Info | C3: brand_code | D3: crm_base.mv_customer360_contacts | F3: Y | G3: Y | H3: Y | I3: one-to-one
B4: Contact Info | C4: division_code | D4: crm_base.mv_customer360_contacts | F4: Y | G4: Y | H4: Y | I4: one-to-one
B5: Contact Info | C5: brand_country | D5: crm_base.mv_customer360_contacts | G5: Y | H5: Y | I5: one-to-one
B6: Contact Info | C6: brand_mdm_id | D6: crm_base.mv_customer360_contacts | F6: Y | G6: Y | H6: Y | I6: one-to-one
B7: Contact Info | C7: contact_value | D7: crm_base.mv_customer360_contacts | G7: Y | H7: Y | I7: one-to-many
B8: Contact Info | C8: contact_type | D8: crm_base.mv_customer360_contacts | G8: Y | H8: Y | I8: one-to-many
B9: Contact Info | C9: contact_sub_type | D9: crm_base.mv_customer360_contacts | G9: Y | H9: Y | I9: one-to-many
B10: Contact Info | C10: last_modified_dt | D10: crm_base.dim_subscriber | F10: Y
B11: Contact Info | C11: email_perm_status | D11: crm_base.mv_customer360_contacts | F11: Y | G11: Y | H11: Y | I11: one-to-one
B12: Contact Info | C12: email_perm_status_modified_dt | D12: crm_base.mv_customer360_contacts | F12: Y | G12: Y | H12: Y | I12: one-to-one
B13: Contact Info | C13: Source of email opt-in collection | D13: TO CREATE PER NEW GDM SPECS | F13: Y
B14: Contact Info | C14: phone_perm_status | D14: crm_base.mv_customer360_contacts | F14: Y | G14: Y | H14: Y | I14: one-to-one
B15: Contact Info | C15: phone_perm_status_modified_dt | D15: crm_base.mv_customer360_contacts | F15: Y | G15: Y | H15: Y | I15: one-to-one
B16: Contact Info | C16: sms_perm_status | D16: crm_base.mv_customer360_contacts | F16: Y | G16: Y | H16: Y | I16: one-to-one
B17: Contact Info | C17: sms_perm_status_modified_dt | D17: crm_base.mv_customer360_contacts | F17: Y | G17: Y | H17: Y | I17: one-to-one
B18: Contact Info | C18: sms_perm_status_modified_src | D18: crm_base.dim_subscriber | F18: Y
B19: Contact Info | C19: sms_double_optin | D19: crm_base.mv_customer360_contacts | F19: Y | G19: Y | H19: Y | I19: one-to-one
B20: Contact Info | C20: sms_double_optin_modified_dt | D20: crm_base.mv_customer360_contacts | F20: Y | G20: Y | H20: Y | I20: one-to-one
B21: Contact Info | C21: sms_double_optin_modified_src | D21: crm_base.dim_subscriber | F21: Y
B22: Contact Info | C22: address_line1 | D22: crm_base.mv_customer360_contacts | G22: Y | H22: Y | I22: one-to-one
B23: Contact Info | C23: address_line2 | D23: crm_base.mv_customer360_contacts | G23: Y | H23: Y | I23: one-to-one
B24: Contact Info | C24: state_code | D24: crm_base.mv_customer360_contacts | F24: Y | G24: Y | H24: Y | I24: one-to-one
B25: Contact Info | C25: city | D25: crm_base.mv_customer360_contacts | G25: Y | H25: Y | I25: one-to-one
B26: Contact Info | C26: postal_code | D26: crm_base.mv_customer360_contacts | G26: Y | H26: Y | I26: one-to-one
B27: Contact Info | C27: zip4 | D27: crm_base.mv_customer360_contacts | G27: Y | H27: Y | I27: one-to-one
B28: Contact Info | C28: zip5 | D28: crm_base.mv_customer360_contacts | G28: Y | H28: Y | I28: one-to-one
B29: Contact Info | C29: country_code | D29: crm_base.mv_customer360_contacts | F29: Y | G29: Y | H29: Y | I29: one-to-one
B30: Contact Info | C30: address_last_updated_dt | D30: crm_base.mv_customer360_contacts | F30: Y | G30: Y | H30: Y | I30: one-to-one

Sheet Campaign
B2: Sub-Domain | C2: Source fields (What DDX field(s) is feeding this field?) | D2: Source tables (Key DDX end table source of truth) | E2: In GDM Analytics Version? | F2: In GDM Activation Version? | G2: In C360 Tables? | H2: In Glossary? | I2: KPI? | J2: Customer Relationship | K2: Campaign Relationship | L2: Definition
B3: Campaign Interactions | C3: brand_code | D3: crm_reporting.fact_customer_segment_by_brand_latest_snap | E3: Y | F3: Y | H3: Y | J3: one-to-many | K3: one-to-many | L3: Brand code
B4: Campaign Interactions | C4: division_code | D4: crm_reporting.fact_customer_segment_by_brand_latest_snap | E4: Y | F4: Y | H4: Y | J4: one-to-many | K4: one-to-many | L4: Division code
B5: Campaign Interactions | C5: country_code | D5: crm_reporting.fact_customer_segment_by_brand_latest_snap | E5: Y | F5: Y | H5: Y | J5: one-to-many | K5: one-to-many | L5: Country code
B6: Campaign Interactions | C6: campaign_unique_id | D6: crm_reporting.fact_customer_campaign_interaction_month | E6: Y | F6: Y | H6: Y | J6: one-to-many | K6: one-to-many | L6: CampaignID
B7: Campaign Interactions | C7: campaign_nm | D7: crm_reporting.fact_customer_campaign_interaction_month | E7: N | F7: N | H7: Y | J7: one-to-many | K7: one-to-many
B8: Campaign Interactions | C8: DeliveryID | D8: ADD GDM SOURCE TABLE | E8: Y | F8: Y | H8: N | J8: one-to-many | K8: one-to-many | L8: DeliveryID
B9: Campaign Interactions | C9: msg_channel | D9: crm_reporting.fact_customer_campaign_interaction_month | E9: Y | F9: Y | H9: N | J9: one-to-many | K9: one-to-many | L9: Channel of execution eg sms, email
B10: Campaign Interactions | C10: brand_customer_id | D10: crm_reporting.fact_customer_segment_by_brand_latest_snap | E10: Y | F10: Y | H10: N | J10: one-to-many | K10: one-to-many | L10: Unique key for this consumer in brand, country
B11: Campaign Interactions | C11: campaign_type | D11: crm_reporting.fact_customer_campaign_interaction_month | E11: Y | F11: Y | H11: Y | J11: one-to-many | K11: one-to-many | L11: Broadcast, trigger, Abandon cart, Abandon session, replenishment. To be aligned to naming convention
B12: Campaign Interactions | C12: subject_line | D12: crm_reporting.fact_customer_campaign_interaction_month | E12: Y | F12: Y | H12: Y | J12: one-to-many | K12: one-to-many | L12: Subject header content
B13: Campaign Interactions | C13: sent_cnt | D13: crm_reporting.fact_customer_campaign_interaction_month | H13: Y
B14: Campaign Interactions | C14: delivered_cnt | D14: crm_reporting.fact_customer_campaign_interaction_month | H14: Y
B15: Campaign Interactions | C15: bounced_cnt | D15: crm_reporting.fact_customer_campaign_interaction_month | H15: Y
B16: Campaign Interactions | C16: unique_open_cnt | D16: crm_reporting.fact_customer_campaign_interaction_month | H16: Y
B17: Campaign Interactions | C17: unique_click_cnt | D17: crm_reporting.fact_customer_campaign_interaction_month | H17: Y
B18: Campaign Interactions | C18: total_open_cnt | D18: crm_reporting.fact_customer_campaign_interaction_month | E18: Y | F18: Y | H18: Y | J18: one-to-many | K18: one-to-many | L18: The contact opened the campaign
B19: Campaign Interactions | C19: total_click_cnt | D19: crm_reporting.fact_customer_campaign_interaction_month | E19: Y | F19: Y | H19: Y | J19: one-to-many | K19: one-to-many | L19: The contact opened and clicked on the campaign
B20: Campaign Interactions | C20: unsubscribed_cnt | D20: crm_reporting.fact_customer_campaign_interaction_month | E20: Y | F20: Y | H20: Y | J20: one-to-many | K20: one-to-many | L20: The contact opted-out on the campaign
B21: Campaign Interactions | C21: net_qty | D21: crm_reporting.fact_customer_campaign_interaction_month | E21: Y | F21: Y | H21: Y | J21: one-to-many | K21: one-to-many | L21: The contact purchased on the campaign
B22: Campaign Interactions | C22: net_sales | D22: crm_reporting.fact_customer_campaign_interaction_month | E22: Y | F22: Y | H22: Y | J22: one-to-many | K22: one-to-many | L22: Revenue on click attribution
B23: Campaign Interactions | C23: interaction_device_dtl | D23: crm_reporting.fact_customer_interactions | E23: Y | F23: Y | H23: N | J23: one-to-many | K23: one-to-many | L23: Device from which interaction was recorded
B24: Campaign Interactions | C24: operating_system | D24: REPLACE WITH GA4 TABLE | E24: Y | F24: Y | H24: Y | J24: one-to-many | K24: one-to-many | L24: Operating system which interaction was recorded from `
B25: Loyalty Campaign Interactions | C25: campaign_code | D25: ADD SOURCE TABLES | H25: Y | J25: one-to-many | K25: one-to-many | L25: Identifier for specific campaign — used for attribution and ROI measurement.
B26: Loyalty Campaign Interactions | C26: engmt_channel | D26: ADD SOURCE TABLES | H26: Y | J26: one-to-many | K26: one-to-many | L26: to measure cross_channel_member_flag
B27: Loyalty Campaign Interactions | C27: engmt_sub_channel | D27: ADD SOURCE TABLES | H27: Y | J27: one-to-many | K27: one-to-many | L27: to measure cross_channel_member_flag
B28: Loyalty Campaign Interactions | C28: loyalty_amt | D28: ADD SOURCE TABLES | H28: Y | J28: one-to-many | K28: one-to-many | L28: The value supplied for the transaction.
B29: Loyalty Campaign Interactions | C29: promo_placement | D29: ADD SOURCE TABLES | H29: Y | J29: one-to-many | K29: one-to-many | L29: where and how a promotion is displayed or applied
B30: Loyalty Campaign Interactions | C30: tier ugrade | D30: ADD SOURCE TABLES | H30: Y | J30: one-to-many | K30: one-to-many | L30: Track tier progression & movements.
B31: Campaign Master | C31: brand_code | D31: crm_reporting.fact_customer_campaign_interaction_month | E31: Y | F31: Y | H31: Y | J31: one-to-many | K31: one-to-one | L31: Brand code
B32: Campaign Master | C32: division_code | D32: crm_reporting.fact_customer_segment_by_brand_latest_snap | E32: Y | F32: Y | H32: Y | J32: one-to-many | K32: one-to-one | L32: Division code
B33: Campaign Master | C33: country_code | D33: crm_reporting.fact_customer_segment_by_brand_latest_snap | E33: Y | F33: Y | H33: Y | J33: one-to-many | K33: one-to-one | L33: Country code
B34: Campaign Master | C34: campaign_unique_id | D34: crm_reporting.fact_customer_campaign_interaction_month | E34: Y | F34: Y | H34: Y | J34: one-to-many | K34: one-to-one | L34: CampaignID
B35: Campaign Master | C35: campaign_nm | D35: crm_reporting.fact_customer_campaign_interaction_month | E35: N | F35: N | H35: Y | J35: one-to-many | K35: one-to-one
B36: Campaign Master | C36: ControlGroupSize | D36: TO CREATE PER NEW GDM SPECS | F36: Y | I36: Y | J36: one-to-many | K36: one-to-one
B37: Campaign Master | C37: date_key | D37: crm_reporting.fact_customer_campaign_interaction_month | E37: Y | F37: Y | H37: Y | J37: one-to-many | K37: one-to-one | L37: Date of the Campaign ID
B38: Campaign Master | C38: DeliveryID | D38: ADD GDM SOURCE TABLE | E38: Y | F38: Y | H38: N | J38: one-to-many | K38: one-to-one | L38: DeliveryID
B39: Campaign Master | C39: DeliveryIDdate | D39: ADD GDM SOURCE TABLE | E39: Y | F39: Y | H39: N | J39: one-to-many | K39: one-to-one | L39: Date of the Delivery ID
B40: Campaign Master | C40: msg_channel | D40: crm_reporting.fact_customer_campaign_interaction_month | E40: Y | F40: Y | H40: Y | J40: one-to-many | K40: one-to-one | L40: Channel of execution eg sms, email
B41: Campaign Master | C41: campaign_type | D41: crm_reporting.fact_customer_campaign_interaction_month | E41: Y | F41: Y | H41: Y | J41: one-to-many | K41: one-to-one | L41: Broadcast, trigger, Abandon cart, Abandon session, replenishment. To be aligned to naming convention
B42: Campaign Master | C42: subject_line | D42: crm_reporting.fact_customer_campaign_interaction_month | E42: Y | F42: Y | H42: Y | J42: one-to-many | K42: one-to-one | L42: Subject header content
B43: Campaign Master | C43: Totalsent | D43: ADD GDM SOURCE TABLE | E43: Y | F43: Y | I43: Y | J43: one-to-many | K43: one-to-one | L43: The number of contacts targeted/sent within campaign or output
B44: Campaign Master | C44: Totaldelivered | D44: ADD GDM SOURCE TABLE | E44: Y | F44: Y | I44: Y | J44: one-to-many | K44: one-to-one | L44: The number of contacts who actually received your campaign
B45: Campaign Master | C45: Totalopened | D45: ADD GDM SOURCE TABLE | E45: Y | F45: Y | I45: Y | J45: one-to-many | K45: one-to-one | L45: The number of unique contacts who opened your campaign (deduped)
B46: Campaign Master | C46: Totalclicked | D46: ADD GDM SOURCE TABLE | E46: Y | F46: Y | I46: Y | J46: one-to-many | K46: one-to-one | L46: The number of contacts who received your campaign and click (deduped)
B47: Campaign Master | C47: TotalOptOut | D47: ADD GDM SOURCE TABLE | E47: Y | F47: Y | I47: Y | J47: one-to-many | K47: one-to-one | L47: The number of contacts who unsubscribed from unsubscribe link
B48: Campaign Master | C48: SUM(unique_open_cnt) for each campaign | D48: crm_reporting.fact_customer_campaign_interaction_month | E48: N | F48: N | H48: Y | I48: Y | J48: one-to-many | K48: one-to-one
B49: Campaign Master | C49: SUM(unique_click_cnt) for each campaign | D49: crm_reporting.fact_customer_campaign_interaction_month | E49: N | F49: N | H49: Y | I49: Y | J49: one-to-many | K49: one-to-one
B50: Campaign Master | C50: SUM(bounced_cnt) for each campaign | D50: crm_reporting.fact_customer_campaign_interaction_month | E50: N | F50: N | H50: Y | I50: Y | J50: one-to-many | K50: one-to-one
B51: Campaign Master | C51: TotalPurchases | D51: ADD GDM SOURCE TABLE | E51: Y | F51: Y | I51: Y | J51: one-to-many | K51: one-to-one | L51: Attributed total purchases
B52: Campaign Master | C52: AttributedRevenue | D52: ADD GDM SOURCE TABLE | E52: Y | F52: Y | I52: Y | J52: one-to-many | K52: one-to-one | L52: Assumed total revenue on click attribution
B53: Campaign Master | C53: segment_name | D53: crm_reporting.fact_customer_campaign_interaction_month | E53: Y | F53: Y | H53: Y | J53: one-to-many | K53: one-to-one | L53: Target segment of campaign. All base, Prospects, Active customers, New customers, Loyalty member tier
B54: Campaign Master | C54: source_name | D54: crm_reporting.fact_customer_campaign_interaction_month | E54: N | F54: N | H54: Y | J54: one-to-many | K54: one-to-one
B55: Campaign Master | C55: start_dt | D55: crm_reporting.dim_campaign | E55: Y | F55: Y | H55: N | J55: one-to-many | K55: one-to-one | L55: Campaign start date
B56: Campaign Master | C56: end_dt | D56: crm_reporting.dim_campaign | E56: Y | F56: Y | H56: N | J56: one-to-many | K56: one-to-one | L56: Campaign end date

Sheet Transactions
B2: Sub-Domain | C2: Source fields (What DDX field(s) is feeding this field?) | D2: Source tables (Key DDX end table source of truth) | E2: In GDM Analytics Version? | F2: In GDM Activation Version? | G2: In C360 Tables? | H2: In Glossary? | I2: KPI? | J2: Customer Relationship | K2: Transaction Relationship | L2: Definition
B3: Order Header | C3: brand_code | D3: crm_reporting.fact_customer_order_sales_month | E3: Y | F3: Y | H3: Y | J3: one-to-many | K3: one-to-one | L3: BrandCode
B4: Order Header | C4: division_code | D4: crm_reporting.fact_customer_order_sales_month | E4: Y | F4: Y | H4: Y | J4: one-to-many | K4: one-to-one | L4: DivisionCode
B5: Order Header | C5: country_code | D5: crm_reporting.fact_customer_order_sales_month | E5: Y | F5: Y | H5: Y | J5: one-to-many | K5: one-to-one | L5: CountryCode
B6: Order Header | C6: order_num | D6: crm_reporting.fact_customer_order_sales_month | E6: Y | F6: Y | H6: Y | J6: one-to-many | K6: one-to-one | L6: One record per order
B7: Order Header | C7: order_type | D7: fact_customer_order_sales_month | H7: Y | J7: one-to-many | K7: one-to-one | L7: Specifies the type of the order whether it is sold or returned
B8: Order Header | C8: order_channel | D8: fact_order_header | H8: Y | J8: one-to-many | K8: one-to-one | L8: Channel of purchase. Auto Replenished order, order_channel="order_group"
B9: Order Header | C9: OnlineOrderID | D9: ADD US GDM SOURCE TABLES | E9: Y | F9: Y | J9: one-to-many | K9: one-to-one | L9: OnlineOrderID
B10: Order Header | C10: OfflineOrderID | D10: ADD US GDM SOURCE TABLES | E10: Y | F10: Y | J10: one-to-many | K10: one-to-one | L10: OfflineOrderID
B11: Order Header | C11: brand_customer_id | D11: crm_reporting.fact_customer_order_sales_month | E11: Y | F11: Y | J11: one-to-many | K11: one-to-one | L11: Unique key for this consumer in brand, country
B12: Order Header | C12: date_key | D12: crm_reporting.fact_customer_order_sales_month | E12: Y | F12: Y | H12: Y | J12: one-to-many | K12: one-to-one | L12: Date of the order
B13: Order Header | C13: net_sales | D13: crm_reporting.fact_customer_order_sales_month | E13: Y | F13: Y | H13: Y | J13: one-to-many | K13: one-to-one | L13: Value of the order as paid by the consumer, amount including all tax, discount and shipping fees included
B14: Order Header | C14: purchase_channel | D14: crm_reporting.fact_customer_order_sales_month | E14: Y | F14: Y | H14: Y | J14: one-to-many | K14: one-to-one | L14: Online, Offline, Declared
B15: Order Header | C15: store_num | D15: crm_reporting.fact_customer_order_sales_month | E15: Y | F15: Y | H15: Y | J15: one-to-many | K15: one-to-one | L15: StoreID of purchase
B16: Order Header | C16: store_state | D16: fact_customer_order_sales_month | H16: Y | J16: one-to-many | K16: one-to-one | L16: Specifies the state where store located
B17: Order Header | C17: store_city | D17: fact_customer_order_sales_month | H17: Y | J17: one-to-many | K17: one-to-one | L17: Specifies the city where store located
B18: Order Header | C18: sales_associate_id | D18: crm_reporting.fact_customer_order_sales_month | E18: Y | F18: Y | H18: Y | J18: one-to-many | K18: one-to-one | L18: ID of instore associate
B19: Order Header | C19: promo_id | D19: crm_reporting.fact_order_price_adjustments | E19: Y | F19: Y | H19: Y | J19: one-to-many | K19: one-to-one | L19: Type of promotion applied to purchase
B20: Order Header | C20: header_coupon_id | D20: fact_customer_order_sales_month | H20: Y | J20: one-to-many | K20: one-to-one | L20: Coupon used while placing the order
B21: Order Header | C21: PromotionValue | D21: ADD US GDM SOURCE TABLES | E21: Y | F21: Y | J21: one-to-many | K21: one-to-one | L21: Promotional value applied to purchase
B22: Order Header | C22: order_total_before_discount | D22: fact_customer_order_sales_month | H22: Y | J22: one-to-many | K22: one-to-one | L22: Total sales before discount and tax
B23: Order Header | C23: order_total_after_discount | D23: fact_customer_order_sales_month | H23: Y | J23: one-to-many | K23: one-to-one | L23: Tatal sales after discount and before tax
B24: Order Header | C24: net_order_qty | D24: crm_reporting.fact_customer_order_sales_month | E24: Y | F24: Y | H24: Y | J24: one-to-many | K24: one-to-one | L24: Number of items in the order. A count of order line items for which the order line total amount (all tax, discount and shipping fee included) greater than 0
B25: Order Header | C25: currency_code | D25: crm_reporting.fact_customer_order_sales_month | E25: Y | F25: Y | J25: one-to-many | K25: one-to-one | L25: Currency of purchase
B26: Order Line | C26: brand_code | D26: crm_reporting.fact_customer_order_sales_month | E26: Y | F26: Y | H26: Y | J26: one-to-many | K26: one-to-many | L26: BrandCode
B27: Order Line | C27: division_code | D27: crm_reporting.fact_customer_order_sales_month | E27: Y | F27: Y | H27: Y | J27: one-to-many | K27: one-to-many | L27: DivisionCode
B28: Order Line | C28: country_code | D28: crm_reporting.fact_customer_order_sales_month | E28: Y | F28: Y | H28: Y | J28: one-to-many | K28: one-to-many | L28: CountryCode
B29: Order Line | C29: order_num | D29: crm_reporting.fact_customer_order_sales_month | E29: Y | F29: Y | H29: Y | J29: one-to-many | K29: one-to-many | L29: One record per order
B30: Order Line | C30: OnlineOrderID | D30: ADD US GDM SOURCE TABLES | E30: Y | F30: Y | J30: one-to-many | K30: one-to-many | L30: OnlineOrderID
B31: Order Line | C31: OfflineOrderID | D31: ADD US GDM SOURCE TABLES | E31: Y | F31: Y | J31: one-to-many | K31: one-to-many | L31: OfflineOrderID
B32: Order Line | C32: line_num | D32: crm_reporting.fact_customer_order_sales_month | E32: Y | F32: Y | H32: Y | J32: one-to-many | K32: one-to-many | L32: Order line number
B33: Order Line | C33: line_type | D33: fact_customer_order_sales_month | H33: Y | J33: one-to-many | K33: one-to-many | L33: Type of each lineitem after the order is placed
B34: Order Line | C34: net_order_qty | D34: crm_reporting.fact_customer_order_sales_month | E34: Y | F34: Y | H34: Y | J34: one-to-many | K34: one-to-many | L34: Number of items in the orderline.
B35: Order Line | C35: line_total_before_discount | D35: fact_customer_order_sales_month | H35: Y | J35: one-to-many | K35: one-to-many | L35: Line item total before discount and before tax
B36: Order Line | C36: line_total_after_discount | D36: crm_reporting.fact_customer_order_sales_month | E36: Y | F36: Y | H36: Y | J36: one-to-many | K36: one-to-many | L36: Orderline total amount (all tax, discount and shipping fee included)
B37: Order Line | C37: promo_id | D37: crm_reporting.fact_customer_order_sales_month | E37: Y | F37: Y | H37: Y | J37: one-to-many | K37: one-to-many | L37: Type of promotion applied to the item(s)
B38: Order Line | C38: PromotionValue | D38: ADD US GDM SOURCE TABLES | E38: Y | F38: Y | J38: one-to-many | K38: one-to-many | L38: Promotional value applied to the items(s)
B39: Order Line | C39: product_ean | D39: crm_reporting.fact_customer_order_sales_month | E39: Y | F39: Y | J39: one-to-many | K39: one-to-many | L39: Product Code
B40: Order Line | C40: product_code | D40: fact_customer_order_sales_month | H40: Y | J40: one-to-many | K40: one-to-many | L40: It specifies the unique ID assigned to each product
B41: Order Line | C41: product_name | D41: dim_product_hierarchy | H41: Y | J41: one-to-many | K41: one-to-many | L41: Name of the product
B42: Order Line | C42: prodmh_axe | D42: fact_customer_order_sales_month | H42: Y | J42: one-to-many | K42: one-to-many | L42: Sap Product information at Axe level
B43: Order Line | C43: prodmh_sub_axe | D43: fact_customer_order_sales_month | H43: Y | J43: one-to-many | K43: one-to-many | L43: Sap Product information at Sub-Axe level
B44: Order Line | C44: prodmh_function | D44: fact_customer_order_sales_month | H44: Y | J44: one-to-many | K44: one-to-many | L44: Sap Product information at function level
C47: FIELDS OMITTED (for review)
C48: order_sub_total | D48: fact_customer_order_sales_month | H48: Y | L48: Sub total of the order
C49: total_trans_revenue | D49: fact_anonymous_web_interaction | H49: Y | L49: Total transaction revenue, expressed as the value passed to Analytics multiplied by 10^6 (e.g., 2.40 would be given as 2400000).
C50: order_dt
C51: transaction_dt
C52: product_id

Sheet Interactions
B2: Sub-Domain | C2: Source fields (What DDX field(s) is feeding this field?) | D2: Source tables (Key DDX end table source of truth) | E2: In GDM Analytics Version? | F2: In GDM Activation Version? | G2: In C360 tables? | H2: In Glossary? | I2: KPI? | J2: Customer Relationship | K2: Interaction Relationship | L2: Definition
B3: Interaction Tracking | C3: brand_code | D3: crm_reporting.fact_customer_interactions | E3: Y | F3: Y | H3: Y | J3: one-to-many | K3: one-to-one | L3: BrandCode
B4: Interaction Tracking | C4: division_code | D4: crm_reporting.fact_customer_interactions | E4: Y | F4: Y | H4: Y | J4: one-to-many | K4: one-to-one | L4: DivisionCode
B5: Interaction Tracking | C5: country_code | D5: crm_reporting.fact_customer_interactions | E5: Y | F5: Y | H5: Y | J5: one-to-many | K5: one-to-one | L5: CountryCode
B6: Interaction Tracking | C6: brand_customer_id | D6: crm_reporting.fact_customer_interactions | E6: Y | F6: Y | H6: Y | J6: one-to-many | K6: one-to-one | L6: Unique key for this consumer in brand, country
B7: Interaction Tracking | C7: TrackingType | D7: ADD US GDM SOURCE TABLES | E7: Y | F7: Y | J7: one-to-many | K7: one-to-one | L7: Tracking event type e.g. session, recommendation, review, flag favourite, abandoned cart
B8: Interaction Tracking | C8: TrackingLabel | D8: ADD US GDM SOURCE TABLES | E8: Y | F8: Y | J8: one-to-many | K8: one-to-one | L8: Tracking event label e.g. EAN Code, URL,
B9: Interaction Tracking | C9: interaction_type | D9: crm_reporting.fact_customer_interactions | H9: Y | J9: one-to-many | K9: one-to-one | L9: Type of interaction. E.g. Order, Feedback, Referral, Loyalty, Email Campaign, SMS Campaign, Push Notification, Web Browse, Product Notification, Profile Management
B10: Interaction Tracking | C10: interaction_sub_type | D10: crm_reporting.fact_customer_interactions | H10: Y | J10: one-to-many | K10: one-to-one | L10: Interaction sub type. Order - Auto Replenishment, Box Order, Store Order, Online Order Feedback - Review, Question, Story Referral - Single Referral, Multiple Referral Loyalty - Points Earned, Points Expired, Tier Achievement, Tier Expired, Digital Reward Redeemed, Virtual Consultation Redeemed, Friend Referral Confirmation, Coupon Reward Redeemed, Product Samples Redeemed, Magazine Sub Redeemed, Giftcard Redeemed,Sweeps Giveaway Redeemed, Charity Donation Redeemed Email Campaign - Bounce, Click, Complaints, Not Sent,Open, Sent, Unsubs SMS Campaign - Failed, Delivered Push Notification - Failed, Delivered Web Browse - Product Notification - Request Registered, Notification Generated Profile Update - Profile Created, Profile Updated, Profile Deleted
B11: Interaction Tracking | C11: source_name | D11: crm_reporting.fact_customer_interactions | E11: Y | F11: Y | H11: Y | J11: one-to-many | K11: one-to-one | L11: Source from which the tracked event was captured
B12: Interaction Tracking | C12: interaction_dt | D12: crm_reporting.fact_customer_interactions | E12: Y | F12: Y | H12: Y | J12: one-to-many | K12: one-to-one | L12: Date tracking event was captured
B13: Interaction Tracking | C13: product_code | D13: Do we need product info here? | H13: Y | J13: one-to-many | K13: one-to-one | L13: It specifies the unique ID assigned to each product
B14: Interaction Tracking | C14: product_name | D14: Do we need product info here? | H14: Y | J14: one-to-many | K14: one-to-one | L14: Name of the product
B15: Interaction Tracking | C15: prodmh_axe | D15: Do we need product info here? | H15: Y | J15: one-to-many | K15: one-to-one | L15: Sap Product information at Axe level
B16: Interaction Tracking | C16: prodmh_sub_axe | D16: Do we need product info here? | H16: Y | J16: one-to-many | K16: one-to-one | L16: Sap Product information at Sub-Axe level
B17: Interaction Tracking | C17: prodmh_function | D17: Do we need product info here? | H17: Y | J17: one-to-many | K17: one-to-one | L17: Sap Product information at function level
B18: Website Interactions | C18: session_duration | D18: vw_ga4_interactions_raw | H18: Y | J18: one-to-many | K18: one-to-one | L18: The total amount of time (in seconds) a user spends in a session, measured from the first event to the last event in that session.
B19: Website Interactions | C19: page_view | D19: vw_ga4_interactions_raw | H19: Y | J19: one-to-many | K19: one-to-one | L19: An instance of the page_view event that is triggered each time a user loads or reloads a page on your website.
B20: Website Interactions | C20: site_load_service | D20: vw_ga4_interactions_raw | H20: Y | J20: one-to-many | K20: one-to-one | L20: Service selected by user and loaded
B21: Website Interactions | C21: salon_locator | D21: vw_ga4_interactions_raw | H21: Y | J21: one-to-many | K21: one-to-one | L21: Interaction with CTA button "find in stores" on product detail page
B22: Website Interactions | C22: use_filters | D22: vw_ga4_interactions_raw | H22: Y | J22: one-to-many | K22: one-to-one | L22: Engagement with filter elements on product selector pages or range pages (example : "skin type" | "price high to low"
B23: Website Interactions | C23: newsletter_registration | D23: vw_ga4_interactions_raw | H23: Y | J23: one-to-many | K23: one-to-one | L23: User signs up to newsletter after seeing product finder results
B24: Website Interactions | C24: validate_quiz | D24: vw_ga4_interactions_raw | H24: Y | J24: one-to-many | K24: one-to-one | L24: User finishes quizz, sign up required to see results
... B33: Website Interactions | C33: enhd_product_catgry | D33: vw_ga4_interactions_raw | H33: Y | J33: one-to-many | K33: one-to-one | L33: Product Category.
B34: Website Interactions | C34: total_pageviews | D34: vw_ga4_interactions_raw | H34: Y | I34: Y | J34: ?? | K34: one-to-one | L34: Total number of pageviews within the session.

Sheet All Domains
C1: DO NOT SORT ANY COLUMNS IN DEFAULT VIEW - please create a separate view.
N2: Global Data Presence | Q2: DDX Data Availability | U2: Strategic Value & Activation | X2: Data Structure & Relationship | Z2: Attribute Prioritization | AC2: Attribute Data Complexity | AE2: Pilot Use Case | AM2: SFMC | AN2: Attribute Owner | AO2: Divisional Prioritization | AU2: WIP - JULIA | AX2: Data Standardization
C3: Domain | D3: Sub-Domain | E3: Global Domain | F3: Global Sub Domain | G3: Business Term | H3: DDX Source Fields | I3: DDX Source Tables (Key DDX End Table Source of Truth) | J3: GoldTable | K3: GoldTable - AttributeName | L3: Hightouch Attribute Name | M3: Business Definition | N3: In GDM Analytics ? | O3: In Global One Consumer Profile? | P3: In Global OCP or GDM? | Q3: In C360 Tables? | R3: In Glossary | S3: Exists in DDX (as a field) | T3: Can be created in DDX | U3: LiveRamp | V3: Attentive | W3: KPI | X3: Customer Relationship | Y3: Domain Object Relationship | Z3: DataBricks Sprint # | AA3: Priority | AB3: Reason | AC3: Data Complexities | AD3: Notes ( from Databricks) | AE3: LOP | AF3: SkinC | AG3: VAL OLD | AH3: KER OLD | AI3: VAL NEW | AJ3: KER NEW | AK3: VAL Data M | AL3: In a Use Case? | AM3: SFMC | AN3: Owner/Schema | AO3: CPD | AP3: LDB | AQ3: LUXE | AR3: PPD | AS3: ALL | AT3: ANY | AU3: Attribute Exists? | AV3: Planned for Gold Layer? | AW3: Attribute Exists in Gold Layer? | AX3: Expectation Check | AY3: Metadata / Sample Data | AZ3: Gold Layer Status Check | BA3: Reason | BB3: Potential Lift
B4: Up to Date as Of | C4: NEW TABLE REQUIRED | D4: DISTINCT TABLES OPTIONAL
B5: 46076 | C5: Customer | D5: Identity | E5: Identity | F5: Core Identifiers | G5: Customer ID (within Brand) | H5: brand_customer_id | J5: All Customer Domain Tables | L5: Customer Brand ID | M5: The unique identifier atttached to the customer within a given brand | N5: Y | O5: Y | P5: =IF(OR(N5 = "Y", O5 = "Y"), "Y", "N") -> Y | Q5: N | R5: Y | S5: Y | T5: N/A | U5: Y | V5: Y | W5: N | X5: one-to-one | Y5: one-to-one | AA5: 0 | AB5: Use Case | AC5: Already have | AE5: X | AF5: X | AG5: X | AH5: X | AI5: X | AJ5: X | AK5: X | AL5: =IF(OR(AE5="X", AF5 = "X", AI5="X", AJ5="X", AK5="X"), "Y", "") -> Y | AN5: CDMO (crm_base/reporting) | AS5: =AND(AO5="Y",AP5="Y",AQ5="Y",AR5="Y") -> FALSE | AT5: =OR(AO5="Y",AP5="Y",AQ5="Y",AR5="Y") -> FALSE | AU5: Y | AX5: Should only contain alphabetical letters and numbers. If not: 1. Flag for standardization 2. Flag for source level monitoring | AY5: Sample: 01c4310fcc3ab4938ad0c66b4a98dd8c
B6: 46076 | C6: Customer | D6: Identity | E6: Identity | F6: Core Identifiers | G6: Consumer ID (LUSA-wide) | H6: global_customer_id | I6: crm_reporting.dim_customer_bridge | J6: All Customer Domain Tables | L6: Global Customer ID | M6: The unique identifier attached to the customer across all brands | N6: Y | O6: Y | P6: =IF(OR(N6 = "Y", O6 = "Y"), "Y", "N") -> Y | Q6: N | R6: N | S6: Y | T6: N/A | W6: N | X6: one-to-one | Y6: one-to-one | AA6: 1 | AB6: OneConsumerProfile | AC6: Done | AD6: All tables will have brand_customer_id and global_customer_id | AL6: =IF(OR(AE6="X", AF6 = "X", AI6="X", AJ6="X", AK6="X"), "Y", "") | AN6: CDMO (crm_base/reporting) | AS6: =AND(AO6="Y",AP6="Y",AQ6="Y",AR6="Y") -> FALSE | AT6: =OR(AO6="Y",AP6="Y",AQ6="Y",AR6="Y") -> FALSE | AU6: Y | AX6: Should only contain alphabetical letters and numbers. If not: 1. Flag for standardization 2. Flag for source level monitoring | AY6: Sample: 79c3e4dd6e3d1a660c984e2b051a3cf1 0930f75fa98f0e139589bbc384ff3238 27f997bb81b5d242eebaca4daf892942 90fa09cd7e74ebfe42f6e48d450ada29 d3198f87d3a097fb010e5d46969f7c91
B7: 46076 | C7: Customer | D7: Identity | E7: Identity | F7: N/A | G7: TransUnion Customer ID | H7: ekey | I7: crm_reporting.vw_dp_neustar_customer | J7: prod_us_catalog.ddx_b2c_gold.cdp__identity_v | K7: ekey | L7: TransUnion Customer ID | M7: TransUnion unique consumer identifier (to be leveraged for identity resolution) | N7: N | O7: N | P7: =IF(OR(N7 = "Y", O7 = "Y"), "Y", "N") -> N | Q7: N | R7: Y | S7: Y | T7: N/A | W7: N | X7: one-to-one | Y7: one-to-one | Z7: 0 | AA7: 0 | AB7: Use Case | AC7: Done | AD7: NC | AG7: X | AL7: =IF(OR(AE7="X", AF7 = "X", AI7="X", AJ7="X", AK7="X"), "Y", "") | AN7: TransUnion (crm_reporting) | AS7: =AND(AO7="Y",AP7="Y",AQ7="Y",AR7="Y") -> FALSE | AT7: =OR(AO7="Y",AP7="Y",AQ7="Y",AR7="Y") -> FALSE | AU7: Y | AX7: Should only contain numbers. If not: 1. Flag for standardization 2. Flag for source level monitoring | AY7: Sample: 115249017534 | AZ7: Validated
B8: 46076 | C8: Customer | D8: Identity | E8: Contact Information | F8: Contact Detail | G8: Brand Code | H8: brand_code | I8: crm_base.customer360 | J8: All Customer Domain Tables | L8: Brand Code | M8: Specifies the brand_code to which the customer belongs | N8: Y | O8: Y | P8: =IF(OR(N8 = "Y", O8 = "Y"), "Y", "N") -> Y | Q8: Y | R8: Y | S8: Y | T8: N/A | U8: Y | V8: Y | W8: N | X8: one-to-one | Y8: one-to-one | AA8: 0 | AB8: Use Case | AC8: Already have | AE8: X | AF8: X | AG8: X | AH8: X | AI8: X | AJ8: X | AK8: X | AL8: =IF(OR(AE8="X", AF8 = "X", AI8="X", AJ8="X", AK8="X"), "Y", "") -> Y | AM8: X | AN8: CDMO (crm_base/reporting) | AO8: Y | AP8: Y | AQ8: Y | AR8: Y | AS8: =AND(AO8="Y",AP8="Y",AQ8="Y",AR8="Y") -> TRUE | AT8: =OR(AO8="Y",AP8="Y",AQ8="Y",AR8="Y") -> TRUE | AU8: Y | AX8: Only accept data from brands that are currently active/owned by LUSA | AY8: YTTP LBS CER GIO SSC PRA OAP SBS AEO KER SCC VAL ESS SAA MUP MM VIC KIE MNY CAA NYX SKIN PUR ITC SCA BIOL RL VR RED GAR YSL LAN MIZ THY MUG MAT LP LRP UD | AZ8: Issue | BA8: 10 Brands are Present LAN OAP MNY NYX MAT RED GAR YSL GIO RL
B9: 46076 | C9: Customer | D9: Identity | E9: Contact Information | F9: Contact Detail | G9: Division Code | H9: division_code | I9: crm_base.customer360 | J9: All Customer Domain Tables | L9: Division Code | M9: Specifies the division to which the customer belongs | N9: Y | O9: Y | P9: =IF(OR(N9 = "Y", O9 = "Y"), "Y", "N") -> Y | Q9: Y | R9: Y | S9: Y | T9: N/A | U9: Y | W9: N | X9: one-to-one | Y9: one-to-one | AA9: 0 | AB9: Use Case | AC9: Already have | AF9: X | AL9: =IF(OR(AE9="X", AF9 = "X", AI9="X", AJ9="X", AK9="X"), "Y", "") -> Y | AN9: CDMO (crm_base/reporting) | AO9: Y | AP9: Y | AQ9: Y | AR9: Y | AS9: =AND(AO9="Y",AP9="Y",AQ9="Y",AR9="Y") -> TRUE | AT9: =OR(AO9="Y",AP9="Y",AQ9="Y",AR9="Y") -> TRUE | AU9: Y | AX9: All brands should be assigned division based on mapping sheet | AY9: ACD PPD CORP CPD LUXE
B10: 46076 | C10: Customer | D10: Identity | E10: Identity | F10: Core Identifiers | G10: Brand Country | H10: brand_country | I10: crm_base.customer360 | J10: All Customer Domain Tables | L10: Brand Country | M10: Used to identify the geographical market or country for the brand relevant to the customer. For LUSA, will be 'USA'. | N10: Y | O10: Y | P10: =IF(OR(N10 = "Y", O10 = "Y"), "Y", "N") -> Y | Q10: Y | R10: Y | S10: Y | T10: N/A | U10: Y | V10: Y | W10: N | X10: one-to-one | Y10: one-to-one | AA10: 0 | AB10: Tech Requirement | AC10: Done | AD10: DONE | AL10: =IF(OR(AE10="X", AF10 = "X", AI10="X", AJ10="X", AK10="X"), "Y", "") | AN10: CDMO (crm_base/reporting) | AS10: =AND(AO10="Y",AP10="Y",AQ10="Y",AR10="Y") -> FALSE | AT10: =OR(AO10="Y",AP10="Y",AQ10="Y",AR10="Y") -> FALSE | AU10: Y | AX10: Should either be US or Non-US. If not: 1. Flag for standardization | AY10: USA
B11: 46076 | C11: Customer | D11: Identity | E11: Identity | F11: Physical Contact | G11: Country | H11: country_code | I11: crm_reporting.fact_customer_segment_by_brand_latest_snap | J11: prod_us_catalog.ddx_b2c_gold.cdp__identity_v | L11: Country | M11: Country code of the customer's address | N11: Y | O11: Y | P11: =IF(OR(N11 = "Y", O11 = "Y"), "Y", "N") -> Y | Q11: N | R11: Y | S11: Y | T11: N/A | U11: Y | W11: N | X11: one-to-one | Y11: one-to-one | AA11: 1 | AB11: OneConsumerProfile | AC11: Done | AD11: C | AL11: =IF(OR(AE11="X", AF11 = "X", AI11="X", AJ11="X", AK11="X"), "Y", "") | AM11: X | AN11: CDMO (crm_base/reporting) | AO11: Y | AP11: Y | AQ11: Y | AR11: Y | AS11: =AND(AO11="Y",AP11="Y",AQ11="Y",AR11="Y") -> TRUE | AT11: =OR(AO11="Y",AP11="Y",AQ11="Y",AR11="Y") -> TRUE | AU11: Y | AX11: Should either be US or Non-US. If not: 1. Flag for standardization | AY11: UNKNOWN 56352043 United States 27143593 5466975 US 2116569 USA 1522541 - 177088 null 18369 China 12419 Canada 12378 United Kingdom 10161 UNITED STATES 8547 undefined 4837 CN 3851 Brazil 2344 UK 2076 France 1862
B12: 46076 | C12: Customer | D12: Identity | E12: Identity | F12: Personal Information | G12: First Name | H12: first_name | I12: crm_base.customer360 | J12: prod_us_catalog.ddx_b2c_gold.cdp__identity_v | K12: first_name | L12: First Name | M12: The customer's first name | N12: N | O12: Y | P12: =IF(OR(N12 = "Y", O12 = "Y"), "Y", "N") -> Y | Q12: Y | R12: Y | S12: Y | T12: N/A | U12: Y | W12: N | X12: one-to-one | Y12: one-to-one | Z12: 0 | AA12: 0 | AB12: Use Case | AC12: Already have | AE12: X | AF12: X | AG12: X | AH12: X | AI12: X | AJ12: X | AK12: X | AL12: =IF(OR(AE12="X", AF12 = "X", AI12="X", AJ12="X", AK12="X"), "Y", "") -> Y | AM12: X | AN12: CDMO (crm_base/reporting) | AO12: Y | AP12: Y | AQ12: Y | AR12: Y | AS12: =AND(AO12="Y",AP12="Y",AQ12="Y",AR12="Y") -> TRUE | AT12: =OR(AO12="Y",AP12="Y",AQ12="Y",AR12="Y") -> TRUE | AU12: Y | AX12: Should only contain alphabetical letters and hyphens. If not: 1. Flag for standardization 2. Flag for source level monitoring | AY12: Sample: Andrew Cathy Carmelita null | AZ12: Validated
B13: 46076 | C13: Customer | D13: Identity | E13: Identity | F13: Personal Information | G13: Last Name | H13: last_name | I13: crm_base.customer360 | J13: prod_us_catalog.ddx_b2c_gold.cdp__identity_v | K13: last_name | L13: Last Name | M13: The customer's last name | N13: N | O13: Y | P13: =IF(OR(N13 = "Y", O13 = "Y"), "Y", "N") -> Y | Q13: Y | R13: Y | S13: Y | T13: N/A | U13: Y | W13: N | X13: one-to-one | Y13: one-to-one | Z13: 0 | AA13: 0 | AB13: Use Case | AC13: Already have | AE13: X | AF13: X | AG13: X | AH13: X | AI13: X | AJ13: X | AK13: X | AL13: =IF(OR(AE13="X", AF13 = "X", AI13="X", AJ13="X", AK13="X"), "Y", "") -> Y | AM13: X | AN13: CDMO (crm_base/reporting) | AO13: Y | AP13: Y | AQ13: Y | AR13: Y | AS13: =AND(AO13="Y",AP13="Y",AQ13="Y",AR13="Y") -> TRUE | AT13: =OR(AO13="Y",AP13="Y",AQ13="Y",AR13="Y") -> TRUE | AU13: Y | AX13: Should only contain alphabetical letters and hyphens. If not: 1. Flag for standardization 2. Flag for source level monitoring | AY13: Sample: Clement Lopez null | AZ13: Validated
B14: 46076 | C14: Customer | D14: Identity | E14: Identity | F14: Personal Information | G14: Gender | H14: gender | I14: crm_reporting.fact_customer_segment_by_brand_latest_snap | J14: prod_us_catalog.ddx_b2c_gold.cdp__identity_v | K14: gender | L14: Gender | M14: Specifies the gender of the customer | N14: Y | O14: Y | P14: =IF(OR(N14 = "Y", O14 = "Y"), "Y", "N") -> Y | Q14: N | R14: Y | S14: Y | T14: N/A | W14: N | X14: one-to-one | Y14: one-to-one | Z14: 1 | AA14: 1 | AB14: OneConsumerProfile | AC14: Easy Add | AD14: in dim_customer_hist | AL14: =IF(OR(AE14="X", AF14 = "X", AI14="X", AJ14="X", AK14="X"), "Y", "") | AN14: CDMO (crm_base/reporting) | AO14: Y | AP14: Y | AQ14: Y | AR14: Y | AS14: =AND(AO14="Y",AP14="Y",AQ14="Y",AR14="Y") -> TRUE | AT14: =OR(AO14="Y",AP14="Y",AQ14="Y",AR14="Y") -> TRUE | AU14: Y | AX14: Should match with LUSA-recognized values (male, female, gender neutral, unknown) If not: 1. Flag for standardization 2. Flag for source level monitoring | AY14: FEMALE UNKNOWN MALE NEUTRAL | AZ14: Validated
B15: 46076 | C15: Customer | D15: Identity | E15: Identity | F15: Personal Information | G15: Month + Day of Birth | H15: birth_month_day | I15: crm_base.customer360 | J15: prod_us_catalog.ddx_b2c_gold.cdp__identity_v | L15: Day of Birth and Month (mm-dd) | M15: Specifies the customer's birth month and day | N15: Y | O15: Y | P15: =IF(OR(N15 = "Y", O15 = "Y"), "Y", "N") -> Y | Q15: Y | R15: Y | S15: Y | T15: N/A | V15: Y | W15: N | X15: one-to-one | Y15: one-to-one | AA15: 0 | AB15: Use Case | AC15: Already have | AF15: X | AK15: X | AL15: =IF(OR(AE15="X", AF15 = "X", AI15="X", AJ15="X", AK15="X"), "Y", "") -> Y | AM15: X | AN15: CDMO (crm_base/reporting) | AS15: =AND(AO15="Y",AP15="Y",AQ15="Y",AR15="Y") -> FALSE | AT15: =OR(AO15="Y",AP15="Y",AQ15="Y",AR15="Y") -> FALSE | AU15: Y | AX15: All values should follow the format MM-DD, only accepting month/day combos that exist as real dates. If not: 1. Flag for standardization 2. Flag for source level monitoring | AY15: Sample: 01-14 | AZ15: Validated
B16: 46076 | C16: Customer | D16: Identity | E16: Identity | F16: N/A | G16: long term frozen control group | H16: ltfcg | I16: crm_base.customer360 | J16: prod_us_catalog.ddx_b2c_gold.cdp__identity_v | K16: ltfcg | L16: Long Term Frozen Group | M16: Indicates whether the customer is part of our long term frozen control group (ltfg) for A/B testing | N16: N | O16: N | P16: =IF(OR(N16 = "Y", O16 = "Y"), "Y", "N") -> N | Q16: Y | R16: Y | S16: Y | T16: N/A | U16: Y | W16: N | X16: one-to-one | Y16: one-to-one | Z16: 0 | AA16: 0 | AB16: LiveRamp | AC16: DONE | AF16: X | AJ16: X | AL16: =IF(OR(AE16="X", AF16 = "X", AI16="X", AJ16="X", AK16="X"), "Y", "") -> Y | AN16: CDMO (crm_base/reporting) | AS16: =AND(AO16="Y",AP16="Y",AQ16="Y",AR16="Y") -> FALSE | AT16: =OR(AO16="Y",AP16="Y",AQ16="Y",AR16="Y") -> FALSE | AU16: Y | AX16: Only customers that have been identified by buisness as ltfcg members should have a non-null value | AY16: null Ltfcg_July24 | AZ16: Issue | BA16: Data does not match. What is the logic behind these new values?
B17: 46076 | C17: Customer | D17: Contactability | E17: Contact Information | F17: Contact Preference | G17: Contactability key | H17: contactability_key | I17: crm_base.customer360 | J17: prod_us_catalog.ddx_b2c_gold.cdp__contactability_v | K17: contactability_key | L17: Contactability Channel | M17: This attribute encodes the available contact channels for a customer. Each value is a concatenation of channel codes: CONEML: Email CONSMS: SMS CONPH: Phone CONDM: Direct Mail CONNONE: No contact channels available Logic: CONEML: Customer is only opted in for Email. CONNONE: Customer is not opted in for any channel. CONDM: Customer is only opted in for Direct Mail (Address). CONEMLDM: Customer is opted in for both Email and Direct Mail. CONEMLSMS: Customer is opted in for both Email and SMS. CONEMLDMPH: Customer is opted in for Email, Direct Mail, and Phone. CONSMS: Customer is only opted in for SMS. CONEMLDMSMS: Customer is opted in for Email, Direct Mail, and SMS. CONEMLPHN: Customer is opted in for both Email and Phone. CONDMPH: Customer is opted in for both Direct Mail and Phone. CONEMLDMPHSMS: Customer is opted in for Email, Direct Mail, Phone, and SMS. CONDMSMS: Customer is opted in for both Direct Mail and SMS. CONPH: Customer is only opted in for Phone. CONEMLPHSMS: Customer is opted in for Email, Phone, and SMS. CONDMPHSMS: Customer is opted in for Direct Mail, Phone, and SMS. CONPHSMS: Customer is opted in for Phone and SMS. | N17: Y | O17: Y | P17: =IF(OR(N17 = "Y", O17 = "Y"), "Y", "N") -> Y | Q17: Y | R17: Y | S17: Y | T17: N/A | U17: Y | W17: Y | X17: one-to-one | Y17: one-to-one | Z17: 1 | AA17: 1 | AB17: C360, OneConsumerProfile | AC17: Already have | AL17: =IF(OR(AE17="X", AF17 = "X", AI17="X", AJ17="X", AK17="X"), "Y", "") | AN17: CDMO (crm_base/reporting) | AO17: Y | AP17: Y | AQ17: Y | AR17: Y | AS17: =AND(AO17="Y",AP17="Y",AQ17="Y",AR17="Y") -> TRUE | AT17: =OR(AO17="Y",AP17="Y",AQ17="Y",AR17="Y") -> TRUE | AU17: Y | AX17: Column values should match UDF logic. If not: 1. Flag for remediation | AY17: CONEMLDM CONNONE CONEML CONDM CONEMLPH CONPH CONDMSMS CONSMS CONDMPH CONEMLDMPHSMS CONPHSMS CONEMLDMSMS CONDMPHSMS CONEMLSMS CONEMLDMPH CONEMLPHSMS | AZ17: Validated
B18: 46076 | C18: Customer | D18: Contactability | E18: Contact Information | F18: Contact Preference | G18: Email contact permission/OptIn | H18: email_perm_status | I18: crm_base.customer360 | J18: prod_us_catalog.ddx_b2c_gold.cdp__contactability_v | K18: email_perm_status | L18: Email OptIn Status | M18: Indicates if account/professional has given permission (subscribed) to contact her on any given email, examing the opt-in status attached to every email on file for the customer | N18: Y | O18: Y | P18: =IF(OR(N18 = "Y", O18 = "Y"), "Y", "N") -> Y | Q18: Y | R18: Y | S18: Y | T18: N/A | U18: Y | V18: Y | W18: Y | X18: one-to-one | Y18: one-to-one | Z18: 0 | AA18: 0 | AB18: Use Case | AC18: Already have | AE18: X | AG18: X | AK18: X | AL18: =IF(OR(AE18="X", AF18 = "X", AI18="X", AJ18="X", AK18="X"), "Y", "") -> Y | AM18: X | AN18: CDMO (crm_base/reporting) | AO18: Y | AP18: Y | AQ18: Y | AR18: Y | AS18: =AND(AO18="Y",AP18="Y",AQ18="Y",AR18="Y") -> TRUE | AT18: =OR(AO18="Y",AP18="Y",AQ18="Y",AR18="Y") -> TRUE | AU18: Y | AX18: Should be "Y" if consumer opted into contact on any email provided, "N" if they opted out; otherwise null. If not: 1. Flag for remediation/rejection 2. Flag for source level monitoring | AY18: Y N UNKNOWN | AZ18: Issue | BA18: Should check counts, all unknown were removed. What percentage of the data was removed? | BB18: Low
B19: 46076 | C19: Customer | D19: Contactability | E19: Contact Information | F19: Contact Preference | G19: OptInGroup | H19: OptInGroup | I19: N/A | J19: prod_us_catalog.ddx_b2c_gold.cdp__contactability_v | L19: OptInGroup | M19: Indicates the consumer's general consent to receive communications or be part of a specific contact group, often encompassing multiple communication channels. | N19: Y | O19: Y | P19: =IF(OR(N19 = "Y", O19 = "Y"), "Y", "N") -> Y | Q19: N | R19: N | S19: N | T19: N/A | W19: N | X19: one-to-one | Y19: one-to-one | AA19: 2 | AB19: OneConsumerProfile | AC19: Need info | AL19: =IF(OR(AE19="X", AF19 = "X", AI19="X", AJ19="X", AK19="X"), "Y", "") | AN19: Global (crm_data_sharing) | AS19: =AND(AO19="Y",AP19="Y",AQ19="Y",AR19="Y") -> FALSE | AT19: =OR(AO19="Y",AP19="Y",AQ19="Y",AR19="Y") -> FALSE | AU19: Y | AX19: WAITING ON GLOBAL | AY19: 0
B20: 46076 | C20: Customer | D20: Contactability | E20: Contact Information | F20: Contact Preference | G20: OptInOther | H20: OptInOther | I20: N/A | J20: prod_us_catalog.ddx_b2c_gold.cdp__contactability_v | L20: OptInOther | M20: Other marketing preference | N20: Y | O20: N | P20: =IF(OR(N20 = "Y", O20 = "Y"), "Y", "N") -> Y | Q20: N | R20: N | S20: N | T20: N/A | W20: N | X20: one-to-one | Y20: one-to-one | AA20: 2 | AC20: Need info | AL20: =IF(OR(AE20="X", AF20 = "X", AI20="X", AJ20="X", AK20="X"), "Y", "") | AN20: Global (crm_data_sharing) | AS20: =AND(AO20="Y",AP20="Y",AQ20="Y",AR20="Y") -> FALSE | AT20: =OR(AO20="Y",AP20="Y",AQ20="Y",AR20="Y") -> FALSE | AU20: Y | AX20: WAITING ON GLOBAL | AY20: 0
B21: 46076 | C21: Customer | D21: Contactability | E21: Contact Information | F21: Contact Preference | G21: OptInSNS | H21: OptInSNS | I21: N/A | J21: prod_us_catalog.ddx_b2c_gold.cdp__contactability_v | L21: OptIn SNS | M21: Social Media marketing optin | N21: Y | O21: Y | P21: =IF(OR(N21 = "Y", O21 = "Y"), "Y", "N") -> Y | Q21: N | R21: N | S21: N | T21: N/A | W21: N | X21: one-to-one | Y21: one-to-one | AA21: 2 | AB21: OneConsumerProfile | AL21: =IF(OR(AE21="X", AF21 = "X", AI21="X", AJ21="X", AK21="X"), "Y", "") | AN21: Global (crm_data_sharing) | AS21: =AND(AO21="Y",AP21="Y",AQ21="Y",AR21="Y") -> FALSE | AT21: =OR(AO21="Y",AP21="Y",AQ21="Y",AR21="Y") -> FALSE | AU21: Y | AX21: WAITING ON GLOBAL | AY21: 0
B22: 46076 | C22: Customer | D22: Contactability | E22: Contact Information | F22: Contact Preference | G22: Phone contact permission/OptIn | H22: phone_perm_status | I22: crm_reporting.fact_customer_segment_by_brand_latest_snap | J22: prod_us_catalog.ddx_b2c_gold.cdp__contactability_v | K22: phone_perm_status | L22: Phone OptIn Status | M22: Represents the permission status of phone communication, indicating whether the customer has given permission to be contacted via phone call or not on any provided phone number, examing the opt-in status attached to every phone number on file for the customer | N22: Y | O22: Y | P22: =IF(OR(N22 = "Y", O22 = "Y"), "Y", "N") -> Y | Q22: N | R22: Y | S22: Y | T22: N/A | U22: Y | W22: Y | X22: one-to-one | Y22: one-to-one | Z22: 1 | AA22: 1 | AB22: OneConsumerProfile | AC22: Easy Add | AD22: in customer_contacts. DONE | AG22: X | AH22: X | AL22: =IF(OR(AE22="X", AF22 = "X", AI22="X", AJ22="X", AK22="X"), "Y", "") | AN22: CDMO (crm_base/reporting) | AO22: Y | AP22: Y | AQ22: Y | AR22: Y | AS22: =AND(AO22="Y",AP22="Y",AQ22="Y",AR22="Y") -> TRUE | AT22: =OR(AO22="Y",AP22="Y",AQ22="Y",AR22="Y") -> TRUE | AU22: Y | AX22: Should be "Y" if consumer opted into contact, "N" if they opted out; otherwise null. If not: 1. Flag for remediation/rejection 2. Flag for source level monitoring | AY22: Y N UNKNOWN | AZ22: Validated | BA22: Unknowns are merged with No
B23: 46076 | C23: Customer | D23: Contactability | E23: Contact Information | F23: Contact Preference | G23: Postal contact permission/OptIn | H23: address_perm_status | I23: crm_reporting.fact_customer_segment_by_brand_latest_snap | J23: prod_us_catalog.ddx_b2c_gold.cdp__contactability_v | K23: address_perm_status | L23: Postal OptIn Status | M23: Represents the permission status for contacting a customer via direct mail at any given address. This takes into every address on file for the consumer. | N23: Y | O23: Y | P23: =IF(OR(N23 = "Y", O23 = "Y"), "Y", "N") -> Y | Q23: N | R23: Y | S23: Y | T23: N/A | U23: Y | W23: Y | X23: one-to-one | Y23: one-to-one | Z23: 1 | AA23: 1 | AB23: OneConsumerProfile | AC23: Easy Add | AD23: in customer_contacts. DONE | AL23: =IF(OR(AE23="X", AF23 = "X", AI23="X", AJ23="X", AK23="X"), "Y", "") | AN23: CDMO (crm_base/reporting) | AO23: Y | AP23: Y | AQ23: Y | AR23: Y | AS23: =AND(AO23="Y",AP23="Y",AQ23="Y",AR23="Y") -> TRUE | AT23: =OR(AO23="Y",AP23="Y",AQ23="Y",AR23="Y") -> TRUE | AU23: Y | AX23: Should be "Y" if consumer opted into contact, "N" if they opted out; otherwise null. If not: 1. Flag for remediation/rejection 2. Flag for source level monitoring | AY23: Y N | AZ23: Validated
B24: 46076 | C24: Customer | D24: Contactability | E24: Contact Information | F24: Contact Preference | G24: Sms contact permission/OptIn | H24: sms_double_optin | I24: crm_reporting.fact_customer_segment_by_brand_latest_snap | J24: prod_us_catalog.ddx_b2c_gold.cdp__contactability_v | K24: sms_double_optin | L24: SMS Double OptIn Status | M24: Represents the permission status of SMS communication, indicating whether the customer has given permission to be contacted via SMS or not on any provided phone number, examing the opt-in status attached to every phone number on file for the customer | N24: Y | O24: Y | P24: =IF(OR(N24 = "Y", O24 = "Y"), "Y", "N") -> Y | Q24: N | R24: Y | S24: Y | T24: N/A | U24: Y | V24: Y | W24: Y | X24: one-to-one | Y24: one-to-one | Z24: 0 | AA24: 0 | AB24: Use Case | AC24: DONE | AD24: in customer_contacts. DONE | AE24: X | AF24: X | AG24: X | AH24: X | AL24: =IF(OR(AE24="X", AF24 = "X", AI24="X", AJ24="X", AK24="X"), "Y", "") -> Y | AM24: X | AN24: CDMO (crm_base/reporting) | AO24: Y | AP24: Y | AQ24: Y | AR24: Y | AS24: =AND(AO24="Y",AP24="Y",AQ24="Y",AR24="Y") -> TRUE | AT24: =OR(AO24="Y",AP24="Y",AQ24="Y",AR24="Y") -> TRUE | AU24: Y | AX24: Should be "Y" if consumer opted into contact on any number provided, "N" if they opted out; otherwise null. If not: 1. Flag for remediation/rejection 2. Flag for source level monitoring | AY24: N UNKNOWN Y | AZ24: Issue | BA24: Should check counts, all unknown were removed. What percentage of the data was removed? | BB24: Low
B25: 46076 | C25: Customer | D25: Contactability | E25: Contact Information | F25: Contact Preference | G25: Targeted advertisement flag | H25: targeted_advertisement_flag | I25: crm_base.customer360 | J25: prod_us_catalog.ddx_b2c_gold.cdp__contactability_v | K25: targeted_advertisement_flag | L25: Targeted Advertisment Flag | M25: Indicates if a consumer has opted into receive targeted ads (only applicable for certain States) | N25: N | O25: Y | P25: =IF(OR(N25 = "Y", O25 = "Y"), "Y", "N") -> Y | Q25: Y | R25: Y | S25: Y | T25: N/A | U25: Y | W25: N | X25: one-to-one | Y25: one-to-one | Z25: 0 | AA25: 0 | AB25: Use Case | AC25: Already have | AE25: X | AF25: X | AG25: X | AH25: X | AJ25: X | AK25: X | AL25: =IF(OR(AE25="X", AF25 = "X", AI25="X", AJ25="X", AK25="X"), "Y", "") -> Y | AN25: CDMO (crm_base/reporting) | AS25: =AND(AO25="Y",AP25="Y",AQ25="Y",AR25="Y") -> FALSE | AT25: =OR(AO25="Y",AP25="Y",AQ25="Y",AR25="Y") -> FALSE | AU25: Y | AX25: Should be "Y" if consumer opted into contact, "N" if they opted out; otherwise null. If not: 1. Flag for remediation/rejection 2. Flag for source level monitoring | AY25: null Y N | AZ25: Issue | BA25: Should check counts, all unknown were removed. What percentage of the data was removed? | BB25: Low
B26: 46076 | C26: Customer | D26: Contactability | E26: Contact Information | F26: Digital Contact | G26: Valid contact email presence | H26: ValidEmail | I26: crm_data_sharing.sdds_contacts | J26: prod_us_catalog.ddx_b2c_gold.cdp__contactability_v | K26: ValidEmail | L26: Valid Email | M26: Indicates whether or not the customer record has a valid email address (format and structure) | N26: Y | O26: Y | P26: =IF(OR(N26 = "Y", O26 = "Y"), "Y", "N") -> Y | Q26: N | R26: N | S26: Y | T26: N/A | W26: N | X26: one-to-one | Y26: one-to-one | Z26: 4 | AA26: 2 | AB26: OneConsumerProfile | AC26: Very Difficult | AL26: =IF(OR(AE26="X", AF26 = "X", AI26="X", AJ26="X", AK26="X"), "Y", "") | AN26: Global (crm_data_sharing) | AX26: Should be "Y" if email recorded is valid, if not, "N" | AY26: Yes/No
B27: 46076 | C27: Customer | D27: Contactability | E27: Contact Information | F27: Digital Contact | G27: Valid contact phone presence | H27: ValidMobileNumber | I27: crm_data_sharing.sdds_contacts | J27: prod_us_catalog.ddx_b2c_gold.cdp__contactability_v | K27: ValidMobileNumber | L27: Valid Mobile | M27: Indicates whether or not the customer record has a valid phone number (format and structure) | N27: Y | O27: Y | P27: =IF(OR(N27 = "Y", O27 = "Y"), "Y", "N") -> Y | Q27: N | R27: N | S27: Y | T27: N/A | W27: N | X27: one-to-one | Y27: one-to-one | Z27: 4 | AA27: 2 | AB27: OneConsumerProfile | AC27: Very Difficult | AL27: =IF(OR(AE27="X", AF27 = "X", AI27="X", AJ27="X", AK27="X"), "Y", "") | AN27: Global (crm_data_sharing) | AX27: Should be "Y" if mobile number recorded is valid, if not, "N" | AY27: Yes/No
B28: 46076 | C28: Customer | D28: Contactability | E28: Contact Information | F28: Physical Contact | G28: Valid contact postal address presence | H28: ValidAddress | I28: crm_data_sharing.sdds_contacts | J28: prod_us_catalog.ddx_b2c_gold.cdp__contactability_v | K28: ValidAddress | L28: Valid Address | M28: Indicates whether or not the customer record has a valid mailing address (very standard formatting - no external service used now, if address is entered will be flagged as valid) | N28: Y | O28: Y | P28: =IF(OR(N28 = "Y", O28 = "Y"), "Y", "N") -> Y | Q28: N | R28: N | S28: Y | T28: N/A | W28: N | X28: one-to-one | Y28: one-to-one | Z28: 4 | AA28: 2 | AB28: OneConsumerProfile | AC28: Very Difficult | AL28: =IF(OR(AE28="X", AF28 = "X", AI28="X", AJ28="X", AK28="X"), "Y", "") | AN28: Global (crm_data_sharing) | AX28: Should be "Y" if address recorded is valid, if not, "N" | AY28: Yes/No
B29: 46076 | C29: Customer | D29: Loyalty | E29: Loyalty Program | F29: Membership | G29: Loyalty program member | H29: is_loyalty | I29: crm_base.customer360 | J29: prod_us_catalog.ddx_b2c_gold.cdp__loyalty_v | K29: is_loyalty | L29: Is Loyatly Member | M29: Signifies whether a particular customer is currently registered, enrolled, or recognized as a member in a brand's loyalty program. | N29: Y | O29: Y | P29: =IF(OR(N29 = "Y", O29 = "Y"), "Y", "N") -> Y | Q29: Y | R29: Y | S29: Y | T29: N/A | V29: Y | W29: N | X29: one-to-one | Y29: one-to-one | Z29: 1 | AA29: 1 | AB29: C360, OneConsumerProfile | AC29: Already have | AL29: =IF(OR(AE29="X", AF29 = "X", AI29="X", AJ29="X", AK29="X"), "Y", "") | AM29: X | AN29: CDMO (crm_base/reporting) | AQ29: Y | AR29: Y | AS29: =AND(AO29="Y",AP29="Y",AQ29="Y",AR29="Y") -> FALSE | AT29: =OR(AO29="Y",AP29="Y",AQ29="Y",AR29="Y") -> TRUE | AU29: Y | AX29: Column values should accurately indicate whther or not a customer is part of a loyalty program. Acccepted values = Y, N, or Null. If not: 1. Flag for remediation/rejection 2. Flag for source level monitoring | AY29: Y N
B30: 46076 | C30: Customer | D30: Loyalty | E30: Loyalty Program | F30: N/A | G30: Loyalty Email Address | H30: EmailAddress | I30: TO CREATE (NET NEW) | J30: prod_us_catalog.ddx_b2c_gold.cdp__loyalty_v | L30: Loyalty Email Address | M30: The email address associated with the customer's loyalty account (for their most recently active loyalty account). | N30: N | O30: N | P30: =IF(OR(N30 = "Y", O30 = "Y"), "Y", "N") -> N | Q30: N | R30: N | S30: N | T30: Y | W30: N | X30: one-to-one | Y30: one-to-one | Z30: 2 | AL30: =IF(OR(AE30="X", AF30 = "X", AI30="X", AJ30="X", AK30="X"), "Y", "") | AM30: X | AN30: CDMO (crm_base/reporting) | AX30: to fill | AY30: to fill
B31: 46076 | C31: Customer | D31: Loyalty | E31: Loyalty Program | F31: N/A | G31: Lifetime Balance | H31: loyalty_lifetime_balance | I31: TO CREATE (NET NEW) | J31: prod_us_catalog.ddx_b2c_gold.cdp__loyalty_v | L31: Lifetime Points Balance | M31: The total loyalty points the customer has earned /accumulated since joining the brand's loyalty progam (for their most recently active loyalty account). | N31: N | O31: N | P31: =IF(OR(N31 = "Y", O31 = "Y"), "Y", "N") -> N | Q31: N | R31: N | S31: N | T31: Y | W31: Y | X31: one-to-one | Y31: one-to-one | Z31: 2 | AL31: =IF(OR(AE31="X", AF31 = "X", AI31="X", AJ31="X", AK31="X"), "Y", "") | AM31: X | AN31: CDMO (crm_base/reporting) | AX31: to fill | AY31: to fill
B32: 46076 | C32: Customer | D32: Loyalty | E32: Loyalty Program | F32: Membership | G32: Loyalty status | H32: loyalty_status_key | I32: crm_reporting.fact_customer_segment_by_brand | J32: prod_us_catalog.ddx_b2c_gold.cdp__loyalty_v | L32: Loyalty Membership Status | M32: Reference that represents a customer's membership state (inactive, active, or lapsed) within the brands loyalty ecosystem (for their most recently active loyalty account). Possible Values: VCH_LOYLS_NA VCH_LOYLS_LM VCH_LOYLS_LLM | N32: N | O32: Y | P32: =IF(OR(N32 = "Y", O32 = "Y"), "Y", "N") -> Y | Q32: Y | R32: Y | S32: Y | T32: N/A | U32: Y | V32: Y | W32: Y | X32: one-to-one | Y32: one-to-one | Z32: 1 | AA32: 1 | AB32: BAR Filter | AC32: ? | AD32: loyalty_status_key has been replaced by loyalty_status_active_12months and loyalty_status_lapsed | AL32: =IF(OR(AE32="X", AF32 = "X", AI32="X", AJ32="X", AK32="X"), "Y", "") | AN32: CDMO (crm_base/reporting) | AQ32: Y | AR32: Y | AS32: =AND(AO32="Y",AP32="Y",AQ32="Y",AR32="Y") -> FALSE | AT32: =OR(AO32="Y",AP32="Y",AQ32="Y",AR32="Y") -> TRUE | AU32: Y | AX32: Column values should match values being recorded (VCH_LOYLS_NA, VCH_LOYLS_LM) Please remove VCH_LOYLS_LLM. If not: 1. Flag for remediation/rejection 2. Flag for source level monitoring | AY32: VCH_LOYLS_NA VCH_LOYLS_LM VCH_LOYLS_LLM
B33: 46076 | C33: Customer | D33: Loyalty | E33: Loyalty Program | F33: Membership | G33: Loyalty member start date | H33: loyalty_member_start_dt | I33: crm_base.customer360 | J33: prod_us_catalog.ddx_b2c_gold.cdp__loyalty_v | K33: loyalty_member_start_dt | L33: Loyalty Member Start Date | M33: Records the date when a customer enrolled in or was activated as a member of a brands loyalty program (for their most recently active loyalty account). | N33: Y | O33: Y | P33: =IF(OR(N33 = "Y", O33 = "Y"), "Y", "N") -> Y | Q33: Y | R33: Y | S33: Y | T33: N/A | U33: Y | W33: N | X33: one-to-one | Y33: one-to-one | Z33: 1 | AA33: 1 | AB33: C360, OneConsumerProfile | AC33: Already have | AL33: =IF(OR(AE33="X", AF33 = "X", AI33="X", AJ33="X", AK33="X"), "Y", "") | AN33: CDMO (crm_base/reporting) | AQ33: Y | AR33: Y | AS33: =AND(AO33="Y",AP33="Y",AQ33="Y",AR33="Y") -> FALSE | AT33: =OR(AO33="Y",AP33="Y",AQ33="Y",AR33="Y") -> TRUE | AU33: Y | AX33: Should follow valid timestamp format and accurately represent the when the consumer became a loyalty member 1. Flag for remediation/rejection 2. Flag for source level monitoring | AY33: Sample: 2021-08-24T01:51:12.000+00:00 | AZ33: Validated
B34: 46076 | C34: Customer | D34: Loyalty | E34: Loyalty Program | F34: N/A | G34: Loyalty preferred channel | H34: loyalty_channel | I34: crm_base.dim_customer | J34: prod_us_catalog.ddx_b2c_gold.cdp__loyalty_v | L34: Preferred Loyalty Channel | M34: Indicates the primary channel through which the customer engages with the loyalty program (for their most recently active loyalty account). | N34: N | O34: N | P34: =IF(OR(N34 = "Y", O34 = "Y"), "Y", "N") -> N | Q34: N | R34: Y | S34: Y | T34: N/A | W34: N | X34: one-to-one | Y34: one-to-one | Z34: 3 | AA34: 2 | AC34: Easy Add | AD34: in dim_customer_hist | AL34: =IF(OR(AE34="X", AF34 = "X", AI34="X", AJ34="X", AK34="X"), "Y", "") | AN34: CDMO (crm_base/reporting) | AS34: =AND(AO34="Y",AP34="Y",AQ34="Y",AR34="Y") -> FALSE | AT34: =OR(AO34="Y",AP34="Y",AQ34="Y",AR34="Y") -> FALSE | AU34: Y | AX34: Collects loyalty channel: Online, website, store, migration, offline (combine all duplicates like online and Online) | AY34: Sample: null 107694879 33296334 online 4822895 website 3076421 store 2904408 Online 684762 migration 576074 web 7297 Offline 901 instore 140 retail 36 email 8 2d1ede1ea566efe6b25a86e5e5d0e7a2 4 ef9f2727783d4acbdf8480a88edcd5c0 3 2a7d72349d6d4be11b7af231869bdb3a 3
B35: 46076 | C35: Customer | D35: Loyalty | E35: Loyalty Program | F35: Membership | G35: Loyalty tier name | H35: tier_name | I35: crm_base.customer360 | J35: prod_us_catalog.ddx_b2c_gold.cdp__loyalty_v | L35: Loyalty Tier Name | M35: Specifies the current status, level, or segment that a customer has achieved within a brands loyalty program (for their most recently active loyalty account). | N35: Y | O35: Y | P35: =IF(OR(N35 = "Y", O35 = "Y"), "Y", "N") -> Y | Q35: Y | R35: Y | S35: Y | T35: N/A | U35: Y | V35: Y | W35: N | X35: one-to-one | Y35: one-to-one | Z35: 1 | AA35: 1 | AB35: C360, OneConsumerProfile | AC35: Already have | AD35: in customer_profile | AL35: =IF(OR(AE35="X", AF35 = "X", AI35="X", AJ35="X", AK35="X"), "Y", "") | AM35: X | AN35: CDMO (crm_base/reporting) | AQ35: Y | AR35: Y | AS35: =AND(AO35="Y",AP35="Y",AQ35="Y",AR35="Y") -> FALSE | AT35: =OR(AO35="Y",AP35="Y",AQ35="Y",AR35="Y") -> TRUE | AU35: Y | AX35: Column values should match values being recorded for each brand;s loyaty program. If not: 1. Flag for remediation/rejection 2. Flag for source level monitoring | AY35: null EXTRA ROSEGOLD OBSESSED SILVER UNITY LIKEIT EXPLORER SUPER RED GOLD EVEREST FAN CRUSH EPIC PLATINUM LOVEIT ICON LOVE OBSESSEDWITHIT OBSESSION LOVER EXTRAORDINARY BLACK EXCLUSIVE POWER FREAK ICONIC DREAM ROCKSTAR Rose
B36: 46076 | C36: Customer | D36: Loyalty | E36: Loyalty Program | F36: N/A | G36: loyalty tier start date/time | H36: loyalty_tier_join_dt | I36: crm_base.dim_customer | J36: prod_us_catalog.ddx_b2c_gold.cdp__loyalty_v | K36: loyalty_tier_join_dt | L36: Loyalty Tier Start Date | M36: The date when the customer acheived their current loyalty membership tier (for their most recently active loyalty account) | N36: N | O36: N | P36: =IF(OR(N36 = "Y", O36 = "Y"), "Y", "N") -> N | Q36: N | R36: Y | S36: Y | T36: N/A | W36: N | X36: one-to-one | Y36: one-to-one | Z36: 4 | AA36: 2 | AC36: Easy Add | AD36: in dim_customer_hist | AL36: =IF(OR(AE36="X", AF36 = "X", AI36="X", AJ36="X", AK36="X"), "Y", "") | AM36: X | AN36: CDMO (crm_base/reporting) | AS36: =AND(AO36="Y",AP36="Y",AQ36="Y",AR36="Y") -> FALSE | AT36: =OR(AO36="Y",AP36="Y",AQ36="Y",AR36="Y") -> FALSE | AU36: Y | AX36: Should follow valid timestamp format 1. Flag for remediation/rejection 2. Flag for source level monitoring | AY36: Sample: 2021-12-02T15:39:22.000+00:00
B37: 46076 | C37: Customer | D37: Loyalty | E37: Loyalty Program | F37: N/A | G37: loyalty tier expiry date/time | H37: loyalty_tier_expiry_dt | I37: crm_base.customer360 | J37: prod_us_catalog.ddx_b2c_gold.cdp__loyalty_v | L37: Loyatly Tier Expiration Date | M37: The date when the loyalty member's current membership tier will expire (for their most recently active loyalty account). | N37: Y | O37: N | P37: =IF(OR(N37 = "Y", O37 = "Y"), "Y", "N") -> Y | Q37: Y | R37: Y | S37: Y | T37: N/A | U37: Y | W37: N | X37: one-to-one | Y37: one-to-one | Z37: 1 | AA37: 1 | AB37: C360 | AC37: Already have | AD37: in customer_profile | AL37: =IF(OR(AE37="X", AF37 = "X", AI37="X", AJ37="X", AK37="X"), "Y", "") | AN37: CDMO (crm_base/reporting) | AQ37: Y | AR37: Y | AS37: =AND(AO37="Y",AP37="Y",AQ37="Y",AR37="Y") -> FALSE | AT37: =OR(AO37="Y",AP37="Y",AQ37="Y",AR37="Y") -> TRUE | AU37: Y | AX37: Should follow valid timestamp format and accurately represent when the consumer's tier will expire at the end of the year. If not: Column values should match UDF logic. If not: 1. Flag for remediation/rejection 2. Flag for source level monitoring | AY37: 2025-12-31 23:59:59 517369 2026-12-31 23:59:59 482030 2024-12-31 23:59:59 434469 2023-12-31 23:59:59 305733 2023-12-31 00:00:00 18647 1900-01-01 00:00:00 40 2024-12-29 05:59:59 1 2024-12-29 04:59:59 1 (remove last three)
B38: 46076 | C38: Customer | D38: Loyalty | E38: Loyalty Program | F38: N/A | G38: loyalty last login date/time | H38: last_login_dt | I38: crm_base.dim_customer | J38: prod_us_catalog.ddx_b2c_gold.cdp__loyalty_v | L38: Loyalty Last Login Date | M38: The date when the loyalty member last logged into their loyalty account (for their most recently active loyalty account) | N38: Y | O38: N | P38: =IF(OR(N38 = "Y", O38 = "Y"), "Y", "N") -> Y | Q38: N | R38: Y | S38: Y | T38: N/A | W38: N | X38: one-to-one | Y38: one-to-one | Z38: 3 | AA38: 2 | AC38: ? | AD38: we have a loyalty last activity dt but the last login date/time. I do not know where is the source | AL38: =IF(OR(AE38="X", AF38 = "X", AI38="X", AJ38="X", AK38="X"), "Y", "") | AN38: CDMO (crm_base/reporting) | AS38: =AND(AO38="Y",AP38="Y",AQ38="Y",AR38="Y") -> FALSE | AT38: =OR(AO38="Y",AP38="Y",AQ38="Y",AR38="Y") -> FALSE | AU38: Y | AX38: Should follow valid timestamp format 1. Flag for remediation/rejection 2. Flag for source level monitoring | AY38: Sample: 0201-01-30T00:30:24.000+00:00
B39: 46076 | C39: Customer | D39: Loyalty | E39: Loyalty Program | F39: Membership | G39: Loyalty last activity date | H39: loyalty_last_activity_dt | I39: crm_base.customer360 | J39: prod_us_catalog.ddx_b2c_gold.cdp__loyalty_v | L39: Loyalty Last Activity Date | M39: The date when the loyalty member last interacted with their loyalty account (made a purchase, redeemed points, altered their profile, etc.) (for their most recently active loyalty account). | N39: Y | O39: Y | P39: =IF(OR(N39 = "Y", O39 = "Y"), "Y", "N") -> Y | Q39: Y | R39: Y | S39: Y | T39: N/A | U39: Y | V39: Y | W39: N | X39: one-to-one | Y39: one-to-one | Z39: 1 | AA39: 1 | AB39: C360, OneConsumerProfile | AC39: Already have | AL39: =IF(OR(AE39="X", AF39 = "X", AI39="X", AJ39="X", AK39="X"), "Y", "") | AN39: CDMO (crm_base/reporting) | AQ39: Y | AR39: Y | AS39: =AND(AO39="Y",AP39="Y",AQ39="Y",AR39="Y") -> FALSE | AT39: =OR(AO39="Y",AP39="Y",AQ39="Y",AR39="Y") -> TRUE | AU39: Y | AX39: Should follow valid timestamp format and accurately represent when the consumer's last loyalty activity (earning/redeeming points, or account creation) occurred. If not: Column values should match UDF logic. If not: 1. Flag for remediation/rejection 2. Flag for source level monitoring | AY39: Sample: 2025-05-01T02:53:56.000+00:00
B40: 46076 | C40: Customer | D40: Loyalty | E40: Loyalty Program | F40: Points & Rewards | G40: Loyalty points balance | H40: loyalty_balance | I40: crm_base.customer360 | J40: prod_us_catalog.ddx_b2c_gold.cdp__loyalty_v | K40: loyalty_balance | L40: Loyalty points balance | M40: Represents the current aggregated total of loyalty points that a customer has accumulated and currently holds within a brands loyalty program (for their most recently active loyalty account). | N40: Y | O40: Y | P40: =IF(OR(N40 = "Y", O40 = "Y"), "Y", "N") -> Y | Q40: Y | R40: Y | S40: Y | T40: N/A | U40: Y | V40: Y | W40: N | X40: one-to-one | Y40: one-to-one | Z40: 1 | AA40: 1 | AB40: C360, OneConsumerProfile | AC40: Already have | AL40: =IF(OR(AE40="X", AF40 = "X", AI40="X", AJ40="X", AK40="X"), "Y", "") | AM40: X | AN40: CDMO (crm_base/reporting) | AQ40: Y | AR40: Y | AS40: =AND(AO40="Y",AP40="Y",AQ40="Y",AR40="Y") -> FALSE | AT40: =OR(AO40="Y",AP40="Y",AQ40="Y",AR40="Y") -> TRUE | AU40: Y | AX40: Should be a number. If not: 1. Flag for remediation/rejection 2. Flag for source level monitoring | AY40: Sample: null 81762580 0.0 8281037 1.0 147771 50.0 147581 100.0 94912 15.0 80017 110.0 69861 2.0 68642 200.0 62607 | AZ40: Validated
B41: 46076 | C41: Customer | D41: Loyalty | E41: Loyalty Program | F41: Points & Rewards | G41: Loyalty points earned (current month) | H41: loyalty_points | I41: crm_base.customer360 | J41: prod_us_catalog.ddx_b2c_gold.cdp__loyalty_v | L41: Loyalty Current Month Earned Points | M41: Refers to the current points (earned) in the past month that are available to spend, not lifetime points earned (for their most recently active loyalty account). | N41: N | O41: Y | P41: =IF(OR(N41 = "Y", O41 = "Y"), "Y", "N") -> Y | Q41: Y | R41: Y | S41: Y | T41: N/A | U41: Y | W41: N | X41: one-to-one | Y41: one-to-one | Z41: 1 | AA41: 1 | AB41: C360, OneConsumerProfile | AC41: Already have | AL41: =IF(OR(AE41="X", AF41 = "X", AI41="X", AJ41="X", AK41="X"), "Y", "") | AM41: X | AN41: CDMO (crm_base/reporting) | AQ41: Y | AR41: Y | AS41: =AND(AO41="Y",AP41="Y",AQ41="Y",AR41="Y") -> FALSE | AT41: =OR(AO41="Y",AP41="Y",AQ41="Y",AR41="Y") -> TRUE | AU41: Y | AX41: Should be a non-negative number. If not: 1. Flag for remediation/rejection 2. Flag for source level monitoring | AY41: Sample: null 82076708 0 1861041 50 440853 20 413334 75 245033 100 215804 110 158451 2 158420 200 105600
B42: 46076 | C42: Customer | D42: Loyalty | E42: Loyalty Program | F42: Points & Rewards | G42: Loyalty points redeemed (current month) | H42: redeemed_points | I42: crm_base.customer360 | J42: prod_us_catalog.ddx_b2c_gold.cdp__loyalty_v | L42: Loyalty Current Month Redeemed Points | M42: Reflect points redeemed (spent) in the past month by the consumer (for their most recently active loyalty account). | N42: N | O42: Y | P42: =IF(OR(N42 = "Y", O42 = "Y"), "Y", "N") -> Y | Q42: Y | R42: Y | S42: Y | T42: N/A | U42: Y | W42: N | X42: one-to-one | Y42: one-to-one | Z42: 1 | AA42: 1 | AB42: C360, OneConsumerProfile | AC42: Already have | AL42: =IF(OR(AE42="X", AF42 = "X", AI42="X", AJ42="X", AK42="X"), "Y", "") | AN42: CDMO (crm_base/reporting) | AQ42: Y | AR42: Y | AS42: =AND(AO42="Y",AP42="Y",AQ42="Y",AR42="Y") -> FALSE | AT42: =OR(AO42="Y",AP42="Y",AQ42="Y",AR42="Y") -> TRUE | AU42: Y | AX42: Should be a non-negative number. If not: 1. Flag for remediation/rejection 2. Flag for source level monitoring | AY42: Sample: null 82076708 0 8561376 100 376218 1 181387 200 170909 300 118793 1000 97569 400 53605
B43: 46076 | C43: Customer | D43: Loyalty | E43: Loyalty Program | F43: N/A | G43: loyalty points expiring (current month) | H43: loyalty_points_expiring | I43: crm_base.customer360 | J43: prod_us_catalog.ddx_b2c_gold.cdp__loyalty_v | L43: Loyalty Current Month Expiring Points | M43: The number of loyalty points the member has that are flagged for expiration at the end of the current month (for their most recently active loyalty account). Used with loyalty_expiration_dt - this is the date that it will expire that month. | N43: N | O43: N | P43: =IF(OR(N43 = "Y", O43 = "Y"), "Y", "N") -> N | Q43: Y | R43: Y | S43: Y | T43: N/A | W43: N | X43: one-to-one | Y43: one-to-one | Z43: 1 | AA43: 1 | AB43: C360 | AC43: Already have | AL43: =IF(OR(AE43="X", AF43 = "X", AI43="X", AJ43="X", AK43="X"), "Y", "") | AN43: CDMO (crm_base/reporting) | AS43: =AND(AO43="Y",AP43="Y",AQ43="Y",AR43="Y") -> FALSE | AT43: =OR(AO43="Y",AP43="Y",AQ43="Y",AR43="Y") -> FALSE | AU43: Y | AX43: Should be a non-negative number. If not: 1. Flag for remediation/rejection 2. Flag for source level monitoring | AY43: Sample: null 92253269 15 15446 50 14208 100 11903 10 7203 200 6492 110 6361 150 3735 25 3704
B44: 46076 | C44: Customer | D44: Loyalty | E44: Loyalty Program | F44: N/A | G44: loyalty points expiration date (current month) | H44: loyalty_expiration_dt | I44: crm_base.customer360 | J44: prod_us_catalog.ddx_b2c_gold.cdp__loyalty_v | L44: Loyalty Current Month Points Expiration Date | M44: Records the earliest next point of expiration date during that month, used with loyalty_points_expirining (for their most recently active loyalty account). | N44: N | O44: N | P44: =IF(OR(N44 = "Y", O44 = "Y"), "Y", "N") -> N | Q44: Y | R44: Y | S44: Y | T44: N/A | W44: N | X44: one-to-one | Y44: one-to-one | Z44: 1 | AA44: 1 | AB44: C360 | AC44: Already have | AL44: =IF(OR(AE44="X", AF44 = "X", AI44="X", AJ44="X", AK44="X"), "Y", "") | AN44: CDMO (crm_base/reporting) | AS44: =AND(AO44="Y",AP44="Y",AQ44="Y",AR44="Y") -> FALSE | AT44: =OR(AO44="Y",AP44="Y",AQ44="Y",AR44="Y") -> FALSE | AU44: Y | AX44: Should follow valid timestamp format and accurately represent the when the consumer's loyalty points are expiring during the month. 1. Flag for remediation/rejection 2. Flag for source level monitoring | AY44: Sample: null 92253269 2025-12-31 330576 2025-12-26 318 2025-12-23 210 2025-12-27 173 2025-12-25 171 2025-12-22 170 2025-12-24 168 2025-12-28 125 2025-12-30 109 2025-12-29 100
B45: 46076 | C45: Customer | D45: Loyalty | E45: Loyalty Program | F45: Points & Rewards | G45: Loyalty expired points (last month) | H45: expired_points | I45: crm_base.customer360 | J45: prod_us_catalog.ddx_b2c_gold.cdp__loyalty_v | L45: Loyalty Last Month Expired Points | M45: Must be static (no time filter), then it should reflect "recent" points expired so set for this past month - i.e., how many points the customer has forgone in the past month (for their most recently active loyalty account). | N45: N | O45: Y | P45: =IF(OR(N45 = "Y", O45 = "Y"), "Y", "N") -> Y | Q45: Y | R45: Y | S45: Y | T45: N/A | U45: Y | W45: N | X45: one-to-one | Y45: one-to-one | Z45: 1 | AA45: 1 | AB45: C360, OneConsumerProfile | AC45: Already have | AL45: =IF(OR(AE45="X", AF45 = "X", AI45="X", AJ45="X", AK45="X"), "Y", "") | AN45: CDMO (crm_base/reporting) | AQ45: Y | AR45: Y | AS45: =AND(AO45="Y",AP45="Y",AQ45="Y",AR45="Y") -> FALSE | AT45: =OR(AO45="Y",AP45="Y",AQ45="Y",AR45="Y") -> TRUE | AU45: Y | AX45: Should be a non-negative number. If not: 1. Flag for remediation/rejection 2. Flag for source level monitoring | AY45: Sample: null 82079426 0 3520476 20 413626 50 310999 75 240065 100 201485 110 125099 250 110560
B46: 46076 | C46: Customer | D46: Loyalty | E46: Loyalty Program | F46: N/A | G46: loyalty points earned L12M | H46: NumberofPointsEarned0to12 | I46: crm_data_sharing.sdds_contacts | J46: prod_us_catalog.ddx_b2c_gold.cdp__loyalty_v | K46: earned_points_last_12m | L46: Number of Loyalty Points Earned Last 12M | M46: Refers to the number of points earned in the last 12 months (for their most recently active loyalty account). | N46: Y | O46: N | P46: =IF(OR(N46 = "Y", O46 = "Y"), "Y", "N") -> Y | Q46: N | R46: N | S46: Y | T46: N/A | W46: Y | X46: one-to-one | Y46: one-to-one | Z46: 3 | AA46: 2 | AC46: Easy Add | AD46: we already have the points earned in loyalty | AL46: =IF(OR(AE46="X", AF46 = "X", AI46="X", AJ46="X", AK46="X"), "Y", "") | AN46: Global (crm_data_sharing) | AS46: =AND(AO46="Y",AP46="Y",AQ46="Y",AR46="Y") -> FALSE | AT46: =OR(AO46="Y",AP46="Y",AQ46="Y",AR46="Y") -> FALSE | AU46: Y | AX46: WAITING ON GLOBAL | AY46: 0
B47: 46076 | C47: Customer | D47: Loyalty | E47: Loyalty Program | F47: N/A | G47: loyalty points redeemed L12M | H47: NumberofPointsSpent0to12 | I47: crm_data_sharing.sdds_contacts | J47: prod_us_catalog.ddx_b2c_gold.cdp__loyalty_v | K47: redeemed_points_last_12m | L47: Number of Loyalty Points Redeemed Last 12M | M47: Refers to the number of points redeemed (spent) in the last 12 months (for their most recently active loyalty account). | N47: Y | O47: N | P47: =IF(OR(N47 = "Y", O47 = "Y"), "Y", "N") -> Y | Q47: N | R47: N | S47: Y | T47: N/A | W47: Y | X47: one-to-one | Y47: one-to-one | Z47: 3 | AA47: 2 | AC47: Easy Add | AD47: we already have the points redeemed in loyalty | AL47: =IF(OR(AE47="X", AF47 = "X", AI47="X", AJ47="X", AK47="X"), "Y", "") | AM47: X | AN47: Global (crm_data_sharing) | AS47: =AND(AO47="Y",AP47="Y",AQ47="Y",AR47="Y") -> FALSE | AT47: =OR(AO47="Y",AP47="Y",AQ47="Y",AR47="Y") -> FALSE | AU47: Y | AX47: WAITING ON GLOBAL | AY47: 0
B48: 46076 | C48: Customer | D48: Campaign Control Group | E48: Identity | F48: Personal Information | G48: Global Control Group End Date | H48: ControlEndDate | I48: crm_data_sharing.sdds_contacts | J48: TBD | L48: Global Control Group End Date | M48: Date which the consumer was removed from a global control group (long term frozen control group) | N48: Y | O48: Y | P48: =IF(OR(N48 = "Y", O48 = "Y"), "Y", "N") -> Y | Q48: N | R48: N | S48: Y | T48: N/A | W48: N | X48: one-to-one | Y48: one-to-one | AA48: 2 | AB48: OneConsumerProfile | AL48: =IF(OR(AE48="X", AF48 = "X", AI48="X", AJ48="X", AK48="X"), "Y", "") | AN48: Global (crm_data_sharing) | AS48: =AND(AO48="Y",AP48="Y",AQ48="Y",AR48="Y") -> FALSE | AT48: =OR(AO48="Y",AP48="Y",AQ48="Y",AR48="Y") -> FALSE | AU48: Y | AX48: Should follow valid timestamp format and accurately represent the when the consumer became a loyalty member 1. Flag for remediation/rejection 2. Flag for source level monitoring | AY48: 15/03/2021
B49: 46076 | C49: Customer | D49: Campaign Control Group | E49: Identity | F49: Personal Information | G49: Global Control Group Start Date | H49: ControlStartDate | I49: crm_data_sharing.sdds_contacts | J49: TBD | L49: Global Control Group Start Date | M49: Date which the consumer was placed in a global control group (long term frozen control group) | N49: Y | O49: Y | P49: =IF(OR(N49 = "Y", O49 = "Y"), "Y", "N") -> Y | Q49: N | R49: N | S49: Y | T49: N/A | W49: N | X49: one-to-one | Y49: one-to-one | AA49: 2 | AB49: OneConsumerProfile | AC49: Very Difficult | AL49: =IF(OR(AE49="X", AF49 = "X", AI49="X", AJ49="X", AK49="X"), "Y", "") | AN49: Global (crm_data_sharing) | AS49: =AND(AO49="Y",AP49="Y",AQ49="Y",AR49="Y") -> FALSE | AT49: =OR(AO49="Y",AP49="Y",AQ49="Y",AR49="Y") -> FALSE | AU49: Y | AX49: Should follow valid timestamp format 1. Flag for remediation/rejection 2. Flag for source level monitoring | AY49: 15/03/2021
A50: x | B50: 46076 | C50: Customer | D50: Acquisition Data | E50: Engagement | F50: N/A | G50: acquisition campaign name | H50: campaign_nm (acquisition-only) | I50: crm_reporting.fact_customer_segment_by_brand_latest_snap | J50: prod_us_catalog.ddx_b2c_gold.acquisition_interaction_data_v | K50: campaign_nm | L50: Acquisition Campaign Name | M50: Name of the campaign where the consumer was acquired | N50: Y | O50: N | P50: =IF(OR(N50 = "Y", O50 = "Y"), "Y", "N") -> Y | Q50: N | R50: N | S50: Y | T50: N/A | W50: N | X50: one-to-one | Y50: one-to-one | Z50: 1 | AA50: 1 | AB50: BAR Filter | AC50: Easy Add | AI50: X | AL50: =IF(OR(AE50="X", AF50 = "X", AI50="X", AJ50="X", AK50="X"), "Y", "") -> Y | AM50: X | AN50: CDMO (crm_base/reporting) | AS50: =AND(AO50="Y",AP50="Y",AQ50="Y",AR50="Y") -> FALSE | AT50: =OR(AO50="Y",AP50="Y",AQ50="Y",AR50="Y") -> FALSE | AU50: Y | AX50: Should match with LUSA-recognized campaign naming conventions. If not: 1. Flag for remediation/rejection 2. Flag for source level monitoring | AY50: Sample: OAP_USA_ColorsonicSweeps_2025 Coupons_Revtrax CER_USA_Moisturizing-Cream-Sample_2023 CER_USA_AMFacial-Lotion-Sampling_2021 UNKNOWN CER_CP-MoisturizingCreamSampling-FBCampaign_2020 LOP Skincare Revitalift HA Serum CER_CP-MoisturizingCreamSampling_2020 CER_USA_Skin-Cleanser-Jebbit-Quiz_2022 | AZ50: Validated
A51: x | B51: 46076 | C51: Customer | D51: Acquisition Data | E51: Engagement | F51: Acquisition | G51: Acquisition channel device | H51: acquisition_device_key | I51: crm_reporting.fact_customer_segment_by_brand_latest_snap | J51: prod_us_catalog.ddx_b2c_gold.acquisition_interaction_data_v | L51: Acquisition Channel Device | M51: Used to identify the device type through which a consumer was acquired, such as mobile web (DVCMBW), desktop (DVCDSK), tablet web (DVCTBW), or unknown device (DVCUNK). | N51: Y | O51: Y | P51: =IF(OR(N51 = "Y", O51 = "Y"), "Y", "N") -> Y | Q51: N | R51: N | S51: Y | T51: N/A | W51: N | X51: one-to-one | Y51: one-to-one | Z51: 3 | AA51: 2 | AB51: OneConsumerProfile | AC51: Need Info | AL51: =IF(OR(AE51="X", AF51 = "X", AI51="X", AJ51="X", AK51="X"), "Y", "") | AN51: CDMO (crm_base/reporting) | AS51: =AND(AO51="Y",AP51="Y",AQ51="Y",AR51="Y") -> FALSE | AT51: =OR(AO51="Y",AP51="Y",AQ51="Y",AR51="Y") -> FALSE | AU51: Y | AX51: Collects mobile web (DVCMBW), desktop (DVCDSK), tablet web (DVCTBW), or unknown device (DVCUNK). | AY51: DVCMBW DVCDSK DVCTBW DVCUNK
A52: x | B52: 46076 | C52: Customer | D52: Acquisition Data | E52: Engagement | F52: Acquisition | G52: Acquisition channel key | H52: acquisition_channel_key | I52: crm_base.customer360 | J52: prod_us_catalog.ddx_b2c_gold.acquisition_interaction_data_v | K52: acquisition_channel_key | L52: Acquisition First Engagement | M52: This key is calculated based on the source at which the first engagement and the value is returned. UDF Logic to calculate acquisition channel: UDF receives all the interactions of the customer as Input. Input is divided into multiple lists as specified above. It retrieves the first record from the Profile Management list and retrieves the source name and acquisition source from the record. If the acquisition source is not empty or not null, then the source name is concatenated with acquisition source and the resultant value is returned, else if acquisition source is empty or null then the source name is returned. Note: If the resultant source name is ‘HARTEHANKS’ or ‘CRMLITE’ and if there is a record with the same interaction date with source name other than ‘HARTEHANKS’ or ‘CRMLITE’, then that record is considered as a priority. | N52: Y | O52: Y | P52: =IF(OR(N52 = "Y", O52 = "Y"), "Y", "N") -> Y | Q52: Y | R52: Y | S52: Y | T52: N/A | U52: Y | W52: N | X52: one-to-one | Y52: one-to-one | Z52: 1 | AA52: 1 | AB52: C360, OneConsumerProfile | AC52: Already have | AE52: X | AG52: X | AL52: =IF(OR(AE52="X", AF52 = "X", AI52="X", AJ52="X", AK52="X"), "Y", "") -> Y | AN52: CDMO (crm_base/reporting) | AS52: =AND(AO52="Y",AP52="Y",AQ52="Y",AR52="Y") -> FALSE | AT52: =OR(AO52="Y",AP52="Y",AQ52="Y",AR52="Y") -> FALSE | AU52: Y | AX52: Column values should match UDF logic. If not: 1. Flag for remediation/rejection 2. Flag for source level monitoring | AY52: DVCMBW | AZ52: Issue | BA52: Really large null count in gold layer that is not seen in customer 360
B53: 46076 | C53: Customer | D53: Acquisition Data | E53: Engagement | F53: N/A | G53: acquisition date key | H53: acquisition_date_key | I53: crm_base.customer360 | J53: prod_us_catalog.ddx_b2c_gold.acquisition_interaction_data_v | K53: acquisition_date_key | L53: Acquisition Date | M53: The date of the first profile management record of the customer. UDF Logic to calculate acquisition date: UDF receives all the interactions of the customer as Input. Input is divided into multiple lists as specified above. It retrieves the first record from the Profile Management list and retrieves the date from the record. | N53: Y | O53: N | P53: =IF(OR(N53 = "Y", O53 = "Y"), "Y", "N") -> Y | Q53: Y | R53: Y | S53: Y | T53: N/A | U53: Y | W53: N | X53: one-to-one | Y53: one-to-one | Z53: 0 | AA53: 0 | AB53: Use Case | AC53: Already have | AE53: X | AF53: X | AG53: X | AK53: X | AL53: =IF(OR(AE53="X", AF53 = "X", AI53="X", AJ53="X", AK53="X"), "Y", "") -> Y | AN53: CDMO (crm_base/reporting) | AO53: Y | AP53: Y | AQ53: Y | AR53: Y | AS53: =AND(AO53="Y",AP53="Y",AQ53="Y",AR53="Y") -> TRUE | AT53: =OR(AO53="Y",AP53="Y",AQ53="Y",AR53="Y") -> TRUE | AU53: Y | AX53: Column values should match UDF logic. If not: 1. Flag for remediation | AY53: DVCDSK | AZ53: Validated
